Workbook

Sheet README
A1: Rank changes: 2018 JAMA paper (data mostly 2013–2016) vs 2026 update (data mostly 2023–2025)
A2: How to read
A3: • Rank convention is the paper's: rank 1 = HIGHEST value in the row, whether high is good or bad.
A4: • Rank change = 2018 rank − 2026 rank. Positive (▲) = the country moved toward the top (its value is now higher RELATIVE to the others); negative (▼) = moved down.
A5: • To keep the comparison fair, ranks are recomputed among only the countries that have a comparable value in BOTH years (column 'n compared'). The ranks printed in the figures are shown alongside for reference.
A6: • Performance change = rank change × desirable direction (Directions sheet): +1 if higher is better (e.g. life expectancy), −1 if lower is better (e.g. infant mortality), 0 if the indicator is descriptive (spending, utilization, workforce). Positive = the country now does BETTER relative to the other countries; negative = WORSE.
A7: • This is relative standing only: a country can improve in absolute terms yet fall in rank if others improved faster.
A8: Sheets
A9: Country_Summary — per country: how many comparable indicators improved, worsened or did not move in relative terms, overall and by domain; with chart.
A10: Performance_Matrix — indicator × country grid of performance change (green better, red worse) for indicators with a desirable direction.
A11: Rank_Movement_Matrix — indicator × country grid of raw rank change for ALL indicators (blue up, orange down), including descriptive ones.
A12: Rank_Changes — the underlying table (one row per indicator × country), with values, ranks, and comparability notes. All ranks and changes are live formulas.
... A17: Indicators with no 2026 data (drug prices, NCEs, health-system views, etc.) cannot be compared and show as excluded.

Sheet Country_Summary
A1: Relative performance by country, 2018 paper vs 2026 update
A2: Counts of comparable indicators with a desirable direction where the country's rank (among countries with data in both years) improved, worsened or did not change.
A4: Country | B4: Indicators compared | C4: Better | D4: Worse | E4: No change | F4: Net (better − worse) | G4: Share better | H4: Mean positions gained
A5: US | B5: =COUNTIFS(Rank_Changes!$E$2:$E$1090,"USA",Rank_Changes!$S$2:$S$1090,"Better")+COUNTIFS(Rank_Changes!$E$2:$E$1090,"USA",Rank_Changes!$S$2:$S$1090,"Worse")+COUNTIFS(Rank_Changes!$E$2:$E$1090,"USA",Rank_Changes!$S$2:$S$1090,"No change") -> 30 | C5: =COUNTIFS(Rank_Changes!$E$2:$E$1090,"USA",Rank_Changes!$S$2:$S$1090,"Better") -> 8 | D5: =COUNTIFS(Rank_Changes!$E$2:$E$1090,"USA",Rank_Changes!$S$2:$S$1090,"Worse") -> 6 | E5: =COUNTIFS(Rank_Changes!$E$2:$E$1090,"USA",Rank_Changes!$S$2:$S$1090,"No change") -> 16 | F5: =C5-D5 -> 2 | G5: =IF(B5=0,"",C5/B5) -> 0.26666667 | H5: =IFERROR(AVERAGEIFS(Rank_Changes!$R$2:$R$1090,Rank_Changes!$E$2:$E$1090,"USA",Rank_Changes!$Q$2:$Q$1090,"<>0",Rank_Changes!$L$2:$L$1090,1),"") -> 0.26666667
A6: UK | B6: =COUNTIFS(Rank_Changes!$E$2:$E$1090,"GBR",Rank_Changes!$S$2:$S$1090,"Better")+COUNTIFS(Rank_Changes!$E$2:$E$1090,"GBR",Rank_Changes!$S$2:$S$1090,"Worse")+COUNTIFS(Rank_Changes!$E$2:$E$1090,"GBR",Rank_Changes!$S$2:$S$1090,"No change") -> 31 | C6: =COUNTIFS(Rank_Changes!$E$2:$E$1090,"GBR",Rank_Changes!$S$2:$S$1090,"Better") -> 7 | D6: =COUNTIFS(Rank_Changes!$E$2:$E$1090,"GBR",Rank_Changes!$S$2:$S$1090,"Worse") -> 15 | E6: =COUNTIFS(Rank_Changes!$E$2:$E$1090,"GBR",Rank_Changes!$S$2:$S$1090,"No change") -> 9 | F6: =C6-D6 -> -8 | G6: =IF(B6=0,"",C6/B6) -> 0.22580645 | H6: =IFERROR(AVERAGEIFS(Rank_Changes!$R$2:$R$1090,Rank_Changes!$E$2:$E$1090,"GBR",Rank_Changes!$Q$2:$Q$1090,"<>0",Rank_Changes!$L$2:$L$1090,1),"") -> -0.74193548
A7: Germany | B7: =COUNTIFS(Rank_Changes!$E$2:$E$1090,"DEU",Rank_Changes!$S$2:$S$1090,"Better")+COUNTIFS(Rank_Changes!$E$2:$E$1090,"DEU",Rank_Changes!$S$2:$S$1090,"Worse")+COUNTIFS(Rank_Changes!$E$2:$E$1090,"DEU",Rank_Changes!$S$2:$S$1090,"No change") -> 30 | C7: =COUNTIFS(Rank_Changes!$E$2:$E$1090,"DEU",Rank_Changes!$S$2:$S$1090,"Better") -> 9 | D7: =COUNTIFS(Rank_Changes!$E$2:$E$1090,"DEU",Rank_Changes!$S$2:$S$1090,"Worse") -> 14 | E7: =COUNTIFS(Rank_Changes!$E$2:$E$1090,"DEU",Rank_Changes!$S$2:$S$1090,"No change") -> 7 | F7: =C7-D7 -> -5 | G7: =IF(B7=0,"",C7/B7) -> 0.3 | H7: =IFERROR(AVERAGEIFS(Rank_Changes!$R$2:$R$1090,Rank_Changes!$E$2:$E$1090,"DEU",Rank_Changes!$Q$2:$Q$1090,"<>0",Rank_Changes!$L$2:$L$1090,1),"") -> -0.16666667
A8: Sweden | B8: =COUNTIFS(Rank_Changes!$E$2:$E$1090,"SWE",Rank_Changes!$S$2:$S$1090,"Better")+COUNTIFS(Rank_Changes!$E$2:$E$1090,"SWE",Rank_Changes!$S$2:$S$1090,"Worse")+COUNTIFS(Rank_Changes!$E$2:$E$1090,"SWE",Rank_Changes!$S$2:$S$1090,"No change") -> 30 | C8: =COUNTIFS(Rank_Changes!$E$2:$E$1090,"SWE",Rank_Changes!$S$2:$S$1090,"Better") -> 16 | D8: =COUNTIFS(Rank_Changes!$E$2:$E$1090,"SWE",Rank_Changes!$S$2:$S$1090,"Worse") -> 7 | E8: =COUNTIFS(Rank_Changes!$E$2:$E$1090,"SWE",Rank_Changes!$S$2:$S$1090,"No change") -> 7 | F8: =C8-D8 -> 9 | G8: =IF(B8=0,"",C8/B8) -> 0.53333333 | H8: =IFERROR(AVERAGEIFS(Rank_Changes!$R$2:$R$1090,Rank_Changes!$E$2:$E$1090,"SWE",Rank_Changes!$Q$2:$Q$1090,"<>0",Rank_Changes!$L$2:$L$1090,1),"") -> 0.9
A9: France | B9: =COUNTIFS(Rank_Changes!$E$2:$E$1090,"FRA",Rank_Changes!$S$2:$S$1090,"Better")+COUNTIFS(Rank_Changes!$E$2:$E$1090,"FRA",Rank_Changes!$S$2:$S$1090,"Worse")+COUNTIFS(Rank_Changes!$E$2:$E$1090,"FRA",Rank_Changes!$S$2:$S$1090,"No change") -> 29 | C9: =COUNTIFS(Rank_Changes!$E$2:$E$1090,"FRA",Rank_Changes!$S$2:$S$1090,"Better") -> 9 | D9: =COUNTIFS(Rank_Changes!$E$2:$E$1090,"FRA",Rank_Changes!$S$2:$S$1090,"Worse") -> 11 | E9: =COUNTIFS(Rank_Changes!$E$2:$E$1090,"FRA",Rank_Changes!$S$2:$S$1090,"No change") -> 9 | F9: =C9-D9 -> -2 | G9: =IF(B9=0,"",C9/B9) -> 0.31034483 | H9: =IFERROR(AVERAGEIFS(Rank_Changes!$R$2:$R$1090,Rank_Changes!$E$2:$E$1090,"FRA",Rank_Changes!$Q$2:$Q$1090,"<>0",Rank_Changes!$L$2:$L$1090,1),"") -> -0.20689655
A10: NLD | B10: =COUNTIFS(Rank_Changes!$E$2:$E$1090,"NLD",Rank_Changes!$S$2:$S$1090,"Better")+COUNTIFS(Rank_Changes!$E$2:$E$1090,"NLD",Rank_Changes!$S$2:$S$1090,"Worse")+COUNTIFS(Rank_Changes!$E$2:$E$1090,"NLD",Rank_Changes!$S$2:$S$1090,"No change") -> 28 | C10: =COUNTIFS(Rank_Changes!$E$2:$E$1090,"NLD",Rank_Changes!$S$2:$S$1090,"Better") -> 11 | D10: =COUNTIFS(Rank_Changes!$E$2:$E$1090,"NLD",Rank_Changes!$S$2:$S$1090,"Worse") -> 12 | E10: =COUNTIFS(Rank_Changes!$E$2:$E$1090,"NLD",Rank_Changes!$S$2:$S$1090,"No change") -> 5 | F10: =C10-D10 -> -1 | G10: =IF(B10=0,"",C10/B10) -> 0.39285714 | H10: =IFERROR(AVERAGEIFS(Rank_Changes!$R$2:$R$1090,Rank_Changes!$E$2:$E$1090,"NLD",Rank_Changes!$Q$2:$Q$1090,"<>0",Rank_Changes!$L$2:$L$1090,1),"") -> -0.35714286
A11: CHE | B11: =COUNTIFS(Rank_Changes!$E$2:$E$1090,"CHE",Rank_Changes!$S$2:$S$1090,"Better")+COUNTIFS(Rank_Changes!$E$2:$E$1090,"CHE",Rank_Changes!$S$2:$S$1090,"Worse")+COUNTIFS(Rank_Changes!$E$2:$E$1090,"CHE",Rank_Changes!$S$2:$S$1090,"No change") -> 27 | C11: =COUNTIFS(Rank_Changes!$E$2:$E$1090,"CHE",Rank_Changes!$S$2:$S$1090,"Better") -> 11 | D11: =COUNTIFS(Rank_Changes!$E$2:$E$1090,"CHE",Rank_Changes!$S$2:$S$1090,"Worse") -> 7 | E11: =COUNTIFS(Rank_Changes!$E$2:$E$1090,"CHE",Rank_Changes!$S$2:$S$1090,"No change") -> 9 | F11: =C11-D11 -> 4 | G11: =IF(B11=0,"",C11/B11) -> 0.40740741 | H11: =IFERROR(AVERAGEIFS(Rank_Changes!$R$2:$R$1090,Rank_Changes!$E$2:$E$1090,"CHE",Rank_Changes!$Q$2:$Q$1090,"<>0",Rank_Changes!$L$2:$L$1090,1),"") -> 0.14814815
A12: Denmark | B12: =COUNTIFS(Rank_Changes!$E$2:$E$1090,"DNK",Rank_Changes!$S$2:$S$1090,"Better")+COUNTIFS(Rank_Changes!$E$2:$E$1090,"DNK",Rank_Changes!$S$2:$S$1090,"Worse")+COUNTIFS(Rank_Changes!$E$2:$E$1090,"DNK",Rank_Changes!$S$2:$S$1090,"No change") -> 22 | C12: =COUNTIFS(Rank_Changes!$E$2:$E$1090,"DNK",Rank_Changes!$S$2:$S$1090,"Better") -> 9 | D12: =COUNTIFS(Rank_Changes!$E$2:$E$1090,"DNK",Rank_Changes!$S$2:$S$1090,"Worse") -> 7 | E12: =COUNTIFS(Rank_Changes!$E$2:$E$1090,"DNK",Rank_Changes!$S$2:$S$1090,"No change") -> 6 | F12: =C12-D12 -> 2 | G12: =IF(B12=0,"",C12/B12) -> 0.40909091 | H12: =IFERROR(AVERAGEIFS(Rank_Changes!$R$2:$R$1090,Rank_Changes!$E$2:$E$1090,"DNK",Rank_Changes!$Q$2:$Q$1090,"<>0",Rank_Changes!$L$2:$L$1090,1),"") -> 0.77272727
A13: Canada | B13: =COUNTIFS(Rank_Changes!$E$2:$E$1090,"CAN",Rank_Changes!$S$2:$S$1090,"Better")+COUNTIFS(Rank_Changes!$E$2:$E$1090,"CAN",Rank_Changes!$S$2:$S$1090,"Worse")+COUNTIFS(Rank_Changes!$E$2:$E$1090,"CAN",Rank_Changes!$S$2:$S$1090,"No change") -> 31 | C13: =COUNTIFS(Rank_Changes!$E$2:$E$1090,"CAN",Rank_Changes!$S$2:$S$1090,"Better") -> 7 | D13: =COUNTIFS(Rank_Changes!$E$2:$E$1090,"CAN",Rank_Changes!$S$2:$S$1090,"Worse") -> 10 | E13: =COUNTIFS(Rank_Changes!$E$2:$E$1090,"CAN",Rank_Changes!$S$2:$S$1090,"No change") -> 14 | F13: =C13-D13 -> -3 | G13: =IF(B13=0,"",C13/B13) -> 0.22580645 | H13: =IFERROR(AVERAGEIFS(Rank_Changes!$R$2:$R$1090,Rank_Changes!$E$2:$E$1090,"CAN",Rank_Changes!$Q$2:$Q$1090,"<>0",Rank_Changes!$L$2:$L$1090,1),"") -> -0.25806452
A14: Japan | B14: =COUNTIFS(Rank_Changes!$E$2:$E$1090,"JPN",Rank_Changes!$S$2:$S$1090,"Better")+COUNTIFS(Rank_Changes!$E$2:$E$1090,"JPN",Rank_Changes!$S$2:$S$1090,"Worse")+COUNTIFS(Rank_Changes!$E$2:$E$1090,"JPN",Rank_Changes!$S$2:$S$1090,"No change") -> 17 | C14: =COUNTIFS(Rank_Changes!$E$2:$E$1090,"JPN",Rank_Changes!$S$2:$S$1090,"Better") -> 4 | D14: =COUNTIFS(Rank_Changes!$E$2:$E$1090,"JPN",Rank_Changes!$S$2:$S$1090,"Worse") -> 3 | E14: =COUNTIFS(Rank_Changes!$E$2:$E$1090,"JPN",Rank_Changes!$S$2:$S$1090,"No change") -> 10 | F14: =C14-D14 -> 1 | G14: =IF(B14=0,"",C14/B14) -> 0.23529412 | H14: =IFERROR(AVERAGEIFS(Rank_Changes!$R$2:$R$1090,Rank_Changes!$E$2:$E$1090,"JPN",Rank_Changes!$Q$2:$Q$1090,"<>0",Rank_Changes!$L$2:$L$1090,1),"") -> 0.058823529
A15: Australia | B15: =COUNTIFS(Rank_Changes!$E$2:$E$1090,"AUS",Rank_Changes!$S$2:$S$1090,"Better")+COUNTIFS(Rank_Changes!$E$2:$E$1090,"AUS",Rank_Changes!$S$2:$S$1090,"Worse")+COUNTIFS(Rank_Changes!$E$2:$E$1090,"AUS",Rank_Changes!$S$2:$S$1090,"No change") -> 30 | C15: =COUNTIFS(Rank_Changes!$E$2:$E$1090,"AUS",Rank_Changes!$S$2:$S$1090,"Better") -> 7 | D15: =COUNTIFS(Rank_Changes!$E$2:$E$1090,"AUS",Rank_Changes!$S$2:$S$1090,"Worse") -> 12 | E15: =COUNTIFS(Rank_Changes!$E$2:$E$1090,"AUS",Rank_Changes!$S$2:$S$1090,"No change") -> 11 | F15: =C15-D15 -> -5 | G15: =IF(B15=0,"",C15/B15) -> 0.23333333 | H15: =IFERROR(AVERAGEIFS(Rank_Changes!$R$2:$R$1090,Rank_Changes!$E$2:$E$1090,"AUS",Rank_Changes!$Q$2:$Q$1090,"<>0",Rank_Changes!$L$2:$L$1090,1),"") -> -0.3
A17: Net (better − worse) by domain
A18: Country | B18: Population health | C18: Access & quality | D18: Equity | E18: Spending | F18: Pharmaceuticals
A19: US | B19: =COUNTIFS(Rank_Changes!$E$2:$E$1090,"USA",Rank_Changes!$A$2:$A$1090,4,Rank_Changes!$S$2:$S$1090,"Better")-COUNTIFS(Rank_Changes!$E$2:$E$1090,"USA",Rank_Changes!$A$2:$A$1090,4,Rank_Changes!$S$2:$S$1090,"Worse") -> 0 | C19: =COUNTIFS(Rank_Changes!$E$2:$E$1090,"USA",Rank_Changes!$A$2:$A$1090,10,Rank_Changes!$S$2:$S$1090,"Better")-COUNTIFS(Rank_Changes!$E$2:$E$1090,"USA",Rank_Changes!$A$2:$A$1090,10,Rank_Changes!$S$2:$S$1090,"Worse") -> 0 | D19: =COUNTIFS(Rank_Changes!$E$2:$E$1090,"USA",Rank_Changes!$A$2:$A$1090,11,Rank_Changes!$S$2:$S$1090,"Better")-COUNTIFS(Rank_Changes!$E$2:$E$1090,"USA",Rank_Changes!$A$2:$A$1090,11,Rank_Changes!$S$2:$S$1090,"Worse") -> 2 | E19: =COUNTIFS(Rank_Changes!$E$2:$E$1090,"USA",Rank_Changes!$A$2:$A$1090,1,Rank_Changes!$S$2:$S$1090,"Better")-COUNTIFS(Rank_Changes!$E$2:$E$1090,"USA",Rank_Changes!$A$2:$A$1090,1,Rank_Changes!$S$2:$S$1090,"Worse") -> 0 | F19: =COUNTIFS(Rank_Changes!$E$2:$E$1090,"USA",Rank_Changes!$A$2:$A$1090,9,Rank_Changes!$S$2:$S$1090,"Better")-COUNTIFS(Rank_Changes!$E$2:$E$1090,"USA",Rank_Changes!$A$2:$A$1090,9,Rank_Changes!$S$2:$S$1090,"Worse") -> 0
A20: UK | B20: =COUNTIFS(Rank_Changes!$E$2:$E$1090,"GBR",Rank_Changes!$A$2:$A$1090,4,Rank_Changes!$S$2:$S$1090,"Better")-COUNTIFS(Rank_Changes!$E$2:$E$1090,"GBR",Rank_Changes!$A$2:$A$1090,4,Rank_Changes!$S$2:$S$1090,"Worse") -> -1 | C20: =COUNTIFS(Rank_Changes!$E$2:$E$1090,"GBR",Rank_Changes!$A$2:$A$1090,10,Rank_Changes!$S$2:$S$1090,"Better")-COUNTIFS(Rank_Changes!$E$2:$E$1090,"GBR",Rank_Changes!$A$2:$A$1090,10,Rank_Changes!$S$2:$S$1090,"Worse") -> -3 | D20: =COUNTIFS(Rank_Changes!$E$2:$E$1090,"GBR",Rank_Changes!$A$2:$A$1090,11,Rank_Changes!$S$2:$S$1090,"Better")-COUNTIFS(Rank_Changes!$E$2:$E$1090,"GBR",Rank_Changes!$A$2:$A$1090,11,Rank_Changes!$S$2:$S$1090,"Worse") -> -3 | E20: =COUNTIFS(Rank_Changes!$E$2:$E$1090,"GBR",Rank_Changes!$A$2:$A$1090,1,Rank_Changes!$S$2:$S$1090,"Better")-COUNTIFS(Rank_Changes!$E$2:$E$1090,"GBR",Rank_Changes!$A$2:$A$1090,1,Rank_Changes!$S$2:$S$1090,"Worse") -> 0 | F20: =COUNTIFS(Rank_Changes!$E$2:$E$1090,"GBR",Rank_Changes!$A$2:$A$1090,9,Rank_Changes!$S$2:$S$1090,"Better")-COUNTIFS(Rank_Changes!$E$2:$E$1090,"GBR",Rank_Changes!$A$2:$A$1090,9,Rank_Changes!$S$2:$S$1090,"Worse") -> -1
A21: Germany | B21: =COUNTIFS(Rank_Changes!$E$2:$E$1090,"DEU",Rank_Changes!$A$2:$A$1090,4,Rank_Changes!$S$2:$S$1090,"Better")-COUNTIFS(Rank_Changes!$E$2:$E$1090,"DEU",Rank_Changes!$A$2:$A$1090,4,Rank_Changes!$S$2:$S$1090,"Worse") -> -1 | C21: =COUNTIFS(Rank_Changes!$E$2:$E$1090,"DEU",Rank_Changes!$A$2:$A$1090,10,Rank_Changes!$S$2:$S$1090,"Better")-COUNTIFS(Rank_Changes!$E$2:$E$1090,"DEU",Rank_Changes!$A$2:$A$1090,10,Rank_Changes!$S$2:$S$1090,"Worse") -> -2 | D21: =COUNTIFS(Rank_Changes!$E$2:$E$1090,"DEU",Rank_Changes!$A$2:$A$1090,11,Rank_Changes!$S$2:$S$1090,"Better")-COUNTIFS(Rank_Changes!$E$2:$E$1090,"DEU",Rank_Changes!$A$2:$A$1090,11,Rank_Changes!$S$2:$S$1090,"Worse") -> -1 | E21: =COUNTIFS(Rank_Changes!$E$2:$E$1090,"DEU",Rank_Changes!$A$2:$A$1090,1,Rank_Changes!$S$2:$S$1090,"Better")-COUNTIFS(Rank_Changes!$E$2:$E$1090,"DEU",Rank_Changes!$A$2:$A$1090,1,Rank_Changes!$S$2:$S$1090,"Worse") -> 0 | F21: =COUNTIFS(Rank_Changes!$E$2:$E$1090,"DEU",Rank_Changes!$A$2:$A$1090,9,Rank_Changes!$S$2:$S$1090,"Better")-COUNTIFS(Rank_Changes!$E$2:$E$1090,"DEU",Rank_Changes!$A$2:$A$1090,9,Rank_Changes!$S$2:$S$1090,"Worse") -> -1
A22: Sweden | B22: =COUNTIFS(Rank_Changes!$E$2:$E$1090,"SWE",Rank_Changes!$A$2:$A$1090,4,Rank_Changes!$S$2:$S$1090,"Better")-COUNTIFS(Rank_Changes!$E$2:$E$1090,"SWE",Rank_Changes!$A$2:$A$1090,4,Rank_Changes!$S$2:$S$1090,"Worse") -> 1 | C22: =COUNTIFS(Rank_Changes!$E$2:$E$1090,"SWE",Rank_Changes!$A$2:$A$1090,10,Rank_Changes!$S$2:$S$1090,"Better")-COUNTIFS(Rank_Changes!$E$2:$E$1090,"SWE",Rank_Changes!$A$2:$A$1090,10,Rank_Changes!$S$2:$S$1090,"Worse") -> 7 | D22: =COUNTIFS(Rank_Changes!$E$2:$E$1090,"SWE",Rank_Changes!$A$2:$A$1090,11,Rank_Changes!$S$2:$S$1090,"Better")-COUNTIFS(Rank_Changes!$E$2:$E$1090,"SWE",Rank_Changes!$A$2:$A$1090,11,Rank_Changes!$S$2:$S$1090,"Worse") -> 0 | E22: =COUNTIFS(Rank_Changes!$E$2:$E$1090,"SWE",Rank_Changes!$A$2:$A$1090,1,Rank_Changes!$S$2:$S$1090,"Better")-COUNTIFS(Rank_Changes!$E$2:$E$1090,"SWE",Rank_Changes!$A$2:$A$1090,1,Rank_Changes!$S$2:$S$1090,"Worse") -> 1 | F22: =COUNTIFS(Rank_Changes!$E$2:$E$1090,"SWE",Rank_Changes!$A$2:$A$1090,9,Rank_Changes!$S$2:$S$1090,"Better")-COUNTIFS(Rank_Changes!$E$2:$E$1090,"SWE",Rank_Changes!$A$2:$A$1090,9,Rank_Changes!$S$2:$S$1090,"Worse") -> 0
A23: France | B23: =COUNTIFS(Rank_Changes!$E$2:$E$1090,"FRA",Rank_Changes!$A$2:$A$1090,4,Rank_Changes!$S$2:$S$1090,"Better")-COUNTIFS(Rank_Changes!$E$2:$E$1090,"FRA",Rank_Changes!$A$2:$A$1090,4,Rank_Changes!$S$2:$S$1090,"Worse") -> -1 | C23: =COUNTIFS(Rank_Changes!$E$2:$E$1090,"FRA",Rank_Changes!$A$2:$A$1090,10,Rank_Changes!$S$2:$S$1090,"Better")-COUNTIFS(Rank_Changes!$E$2:$E$1090,"FRA",Rank_Changes!$A$2:$A$1090,10,Rank_Changes!$S$2:$S$1090,"Worse") -> -6 | D23: =COUNTIFS(Rank_Changes!$E$2:$E$1090,"FRA",Rank_Changes!$A$2:$A$1090,11,Rank_Changes!$S$2:$S$1090,"Better")-COUNTIFS(Rank_Changes!$E$2:$E$1090,"FRA",Rank_Changes!$A$2:$A$1090,11,Rank_Changes!$S$2:$S$1090,"Worse") -> 5 | E23: =COUNTIFS(Rank_Changes!$E$2:$E$1090,"FRA",Rank_Changes!$A$2:$A$1090,1,Rank_Changes!$S$2:$S$1090,"Better")-COUNTIFS(Rank_Changes!$E$2:$E$1090,"FRA",Rank_Changes!$A$2:$A$1090,1,Rank_Changes!$S$2:$S$1090,"Worse") -> 0 | F23: =COUNTIFS(Rank_Changes!$E$2:$E$1090,"FRA",Rank_Changes!$A$2:$A$1090,9,Rank_Changes!$S$2:$S$1090,"Better")-COUNTIFS(Rank_Changes!$E$2:$E$1090,"FRA",Rank_Changes!$A$2:$A$1090,9,Rank_Changes!$S$2:$S$1090,"Worse") -> 0
A24: NLD | B24: =COUNTIFS(Rank_Changes!$E$2:$E$1090,"NLD",Rank_Changes!$A$2:$A$1090,4,Rank_Changes!$S$2:$S$1090,"Better")-COUNTIFS(Rank_Changes!$E$2:$E$1090,"NLD",Rank_Changes!$A$2:$A$1090,4,Rank_Changes!$S$2:$S$1090,"Worse") -> -3 | C24: =COUNTIFS(Rank_Changes!$E$2:$E$1090,"NLD",Rank_Changes!$A$2:$A$1090,10,Rank_Changes!$S$2:$S$1090,"Better")-COUNTIFS(Rank_Changes!$E$2:$E$1090,"NLD",Rank_Changes!$A$2:$A$1090,10,Rank_Changes!$S$2:$S$1090,"Worse") -> 1 | D24: =COUNTIFS(Rank_Changes!$E$2:$E$1090,"NLD",Rank_Changes!$A$2:$A$1090,11,Rank_Changes!$S$2:$S$1090,"Better")-COUNTIFS(Rank_Changes!$E$2:$E$1090,"NLD",Rank_Changes!$A$2:$A$1090,11,Rank_Changes!$S$2:$S$1090,"Worse") -> 1 | E24: =COUNTIFS(Rank_Changes!$E$2:$E$1090,"NLD",Rank_Changes!$A$2:$A$1090,1,Rank_Changes!$S$2:$S$1090,"Better")-COUNTIFS(Rank_Changes!$E$2:$E$1090,"NLD",Rank_Changes!$A$2:$A$1090,1,Rank_Changes!$S$2:$S$1090,"Worse") -> 0 | F24: =COUNTIFS(Rank_Changes!$E$2:$E$1090,"NLD",Rank_Changes!$A$2:$A$1090,9,Rank_Changes!$S$2:$S$1090,"Better")-COUNTIFS(Rank_Changes!$E$2:$E$1090,"NLD",Rank_Changes!$A$2:$A$1090,9,Rank_Changes!$S$2:$S$1090,"Worse") -> 0
A25: CHE | B25: =COUNTIFS(Rank_Changes!$E$2:$E$1090,"CHE",Rank_Changes!$A$2:$A$1090,4,Rank_Changes!$S$2:$S$1090,"Better")-COUNTIFS(Rank_Changes!$E$2:$E$1090,"CHE",Rank_Changes!$A$2:$A$1090,4,Rank_Changes!$S$2:$S$1090,"Worse") -> 3 | C25: =COUNTIFS(Rank_Changes!$E$2:$E$1090,"CHE",Rank_Changes!$A$2:$A$1090,10,Rank_Changes!$S$2:$S$1090,"Better")-COUNTIFS(Rank_Changes!$E$2:$E$1090,"CHE",Rank_Changes!$A$2:$A$1090,10,Rank_Changes!$S$2:$S$1090,"Worse") -> -1 | D25: =COUNTIFS(Rank_Changes!$E$2:$E$1090,"CHE",Rank_Changes!$A$2:$A$1090,11,Rank_Changes!$S$2:$S$1090,"Better")-COUNTIFS(Rank_Changes!$E$2:$E$1090,"CHE",Rank_Changes!$A$2:$A$1090,11,Rank_Changes!$S$2:$S$1090,"Worse") -> 1 | E25: =COUNTIFS(Rank_Changes!$E$2:$E$1090,"CHE",Rank_Changes!$A$2:$A$1090,1,Rank_Changes!$S$2:$S$1090,"Better")-COUNTIFS(Rank_Changes!$E$2:$E$1090,"CHE",Rank_Changes!$A$2:$A$1090,1,Rank_Changes!$S$2:$S$1090,"Worse") -> 1 | F25: =COUNTIFS(Rank_Changes!$E$2:$E$1090,"CHE",Rank_Changes!$A$2:$A$1090,9,Rank_Changes!$S$2:$S$1090,"Better")-COUNTIFS(Rank_Changes!$E$2:$E$1090,"CHE",Rank_Changes!$A$2:$A$1090,9,Rank_Changes!$S$2:$S$1090,"Worse") -> 0
A26: Denmark | B26: =COUNTIFS(Rank_Changes!$E$2:$E$1090,"DNK",Rank_Changes!$A$2:$A$1090,4,Rank_Changes!$S$2:$S$1090,"Better")-COUNTIFS(Rank_Changes!$E$2:$E$1090,"DNK",Rank_Changes!$A$2:$A$1090,4,Rank_Changes!$S$2:$S$1090,"Worse") -> 4 | C26: =COUNTIFS(Rank_Changes!$E$2:$E$1090,"DNK",Rank_Changes!$A$2:$A$1090,10,Rank_Changes!$S$2:$S$1090,"Better")-COUNTIFS(Rank_Changes!$E$2:$E$1090,"DNK",Rank_Changes!$A$2:$A$1090,10,Rank_Changes!$S$2:$S$1090,"Worse") -> 1 | D26: =COUNTIFS(Rank_Changes!$E$2:$E$1090,"DNK",Rank_Changes!$A$2:$A$1090,11,Rank_Changes!$S$2:$S$1090,"Better")-COUNTIFS(Rank_Changes!$E$2:$E$1090,"DNK",Rank_Changes!$A$2:$A$1090,11,Rank_Changes!$S$2:$S$1090,"Worse") -> -2 | E26: =COUNTIFS(Rank_Changes!$E$2:$E$1090,"DNK",Rank_Changes!$A$2:$A$1090,1,Rank_Changes!$S$2:$S$1090,"Better")-COUNTIFS(Rank_Changes!$E$2:$E$1090,"DNK",Rank_Changes!$A$2:$A$1090,1,Rank_Changes!$S$2:$S$1090,"Worse") -> 0 | F26: =COUNTIFS(Rank_Changes!$E$2:$E$1090,"DNK",Rank_Changes!$A$2:$A$1090,9,Rank_Changes!$S$2:$S$1090,"Better")-COUNTIFS(Rank_Changes!$E$2:$E$1090,"DNK",Rank_Changes!$A$2:$A$1090,9,Rank_Changes!$S$2:$S$1090,"Worse") -> -1
A27: Canada | B27: =COUNTIFS(Rank_Changes!$E$2:$E$1090,"CAN",Rank_Changes!$A$2:$A$1090,4,Rank_Changes!$S$2:$S$1090,"Better")-COUNTIFS(Rank_Changes!$E$2:$E$1090,"CAN",Rank_Changes!$A$2:$A$1090,4,Rank_Changes!$S$2:$S$1090,"Worse") -> -4 | C27: =COUNTIFS(Rank_Changes!$E$2:$E$1090,"CAN",Rank_Changes!$A$2:$A$1090,10,Rank_Changes!$S$2:$S$1090,"Better")-COUNTIFS(Rank_Changes!$E$2:$E$1090,"CAN",Rank_Changes!$A$2:$A$1090,10,Rank_Changes!$S$2:$S$1090,"Worse") -> 0 | D27: =COUNTIFS(Rank_Changes!$E$2:$E$1090,"CAN",Rank_Changes!$A$2:$A$1090,11,Rank_Changes!$S$2:$S$1090,"Better")-COUNTIFS(Rank_Changes!$E$2:$E$1090,"CAN",Rank_Changes!$A$2:$A$1090,11,Rank_Changes!$S$2:$S$1090,"Worse") -> -1 | E27: =COUNTIFS(Rank_Changes!$E$2:$E$1090,"CAN",Rank_Changes!$A$2:$A$1090,1,Rank_Changes!$S$2:$S$1090,"Better")-COUNTIFS(Rank_Changes!$E$2:$E$1090,"CAN",Rank_Changes!$A$2:$A$1090,1,Rank_Changes!$S$2:$S$1090,"Worse") -> 1 | F27: =COUNTIFS(Rank_Changes!$E$2:$E$1090,"CAN",Rank_Changes!$A$2:$A$1090,9,Rank_Changes!$S$2:$S$1090,"Better")-COUNTIFS(Rank_Changes!$E$2:$E$1090,"CAN",Rank_Changes!$A$2:$A$1090,9,Rank_Changes!$S$2:$S$1090,"Worse") -> 1
A28: Japan | B28: =COUNTIFS(Rank_Changes!$E$2:$E$1090,"JPN",Rank_Changes!$A$2:$A$1090,4,Rank_Changes!$S$2:$S$1090,"Better")-COUNTIFS(Rank_Changes!$E$2:$E$1090,"JPN",Rank_Changes!$A$2:$A$1090,4,Rank_Changes!$S$2:$S$1090,"Worse") -> -1 | C28: =COUNTIFS(Rank_Changes!$E$2:$E$1090,"JPN",Rank_Changes!$A$2:$A$1090,10,Rank_Changes!$S$2:$S$1090,"Better")-COUNTIFS(Rank_Changes!$E$2:$E$1090,"JPN",Rank_Changes!$A$2:$A$1090,10,Rank_Changes!$S$2:$S$1090,"Worse") -> 0 | D28: =COUNTIFS(Rank_Changes!$E$2:$E$1090,"JPN",Rank_Changes!$A$2:$A$1090,11,Rank_Changes!$S$2:$S$1090,"Better")-COUNTIFS(Rank_Changes!$E$2:$E$1090,"JPN",Rank_Changes!$A$2:$A$1090,11,Rank_Changes!$S$2:$S$1090,"Worse") -> 2 | E28: =COUNTIFS(Rank_Changes!$E$2:$E$1090,"JPN",Rank_Changes!$A$2:$A$1090,1,Rank_Changes!$S$2:$S$1090,"Better")-COUNTIFS(Rank_Changes!$E$2:$E$1090,"JPN",Rank_Changes!$A$2:$A$1090,1,Rank_Changes!$S$2:$S$1090,"Worse") -> 0 | F28: =COUNTIFS(Rank_Changes!$E$2:$E$1090,"JPN",Rank_Changes!$A$2:$A$1090,9,Rank_Changes!$S$2:$S$1090,"Better")-COUNTIFS(Rank_Changes!$E$2:$E$1090,"JPN",Rank_Changes!$A$2:$A$1090,9,Rank_Changes!$S$2:$S$1090,"Worse") -> 0
A29: Australia | B29: =COUNTIFS(Rank_Changes!$E$2:$E$1090,"AUS",Rank_Changes!$A$2:$A$1090,4,Rank_Changes!$S$2:$S$1090,"Better")-COUNTIFS(Rank_Changes!$E$2:$E$1090,"AUS",Rank_Changes!$A$2:$A$1090,4,Rank_Changes!$S$2:$S$1090,"Worse") -> -4 | C29: =COUNTIFS(Rank_Changes!$E$2:$E$1090,"AUS",Rank_Changes!$A$2:$A$1090,10,Rank_Changes!$S$2:$S$1090,"Better")-COUNTIFS(Rank_Changes!$E$2:$E$1090,"AUS",Rank_Changes!$A$2:$A$1090,10,Rank_Changes!$S$2:$S$1090,"Worse") -> 3 | D29: =COUNTIFS(Rank_Changes!$E$2:$E$1090,"AUS",Rank_Changes!$A$2:$A$1090,11,Rank_Changes!$S$2:$S$1090,"Better")-COUNTIFS(Rank_Changes!$E$2:$E$1090,"AUS",Rank_Changes!$A$2:$A$1090,11,Rank_Changes!$S$2:$S$1090,"Worse") -> -3 | E29: =COUNTIFS(Rank_Changes!$E$2:$E$1090,"AUS",Rank_Changes!$A$2:$A$1090,1,Rank_Changes!$S$2:$S$1090,"Better")-COUNTIFS(Rank_Changes!$E$2:$E$1090,"AUS",Rank_Changes!$A$2:$A$1090,1,Rank_Changes!$S$2:$S$1090,"Worse") -> -1 | F29: =COUNTIFS(Rank_Changes!$E$2:$E$1090,"AUS",Rank_Changes!$A$2:$A$1090,9,Rank_Changes!$S$2:$S$1090,"Better")-COUNTIFS(Rank_Changes!$E$2:$E$1090,"AUS",Rank_Changes!$A$2:$A$1090,9,Rank_Changes!$S$2:$S$1090,"Worse") -> 0
A30: Domains with directional indicators only (Spending: poverty and coverage; Pharmaceuticals: antibiotic use). Workforce and Utilization indicators are descriptive — see Rank_Movement_Matrix.

Sheet Directions
A1: Indicator ID | B1: Figure | C1: Indicator | D1: Desirable direction (+1 higher better, −1 lower better, 0 none) | E1: Rationale
A2: F1_01 | B2: 1 | C2: Overall population (in millions) | D2: 0 | E2: Descriptive / context: no normative better-or-worse direction
A3: F1_02 | B3: 1 | C3: Population ≥65 y, % | D3: 0 | E3: Descriptive / context: no normative better-or-worse direction
A4: F1_03 | B4: 1 | C4: GDP per capita, US $ (in thousands) | D4: 0 | E4: Descriptive / context: no normative better-or-worse direction
A5: F1_04 | B5: 1 | C5: Land area (× 1000 sq km) | D5: 0 | E5: Descriptive / context: no normative better-or-worse direction
A6: F1_05 | B6: 1 | C6: Poverty rate, % below poverty line of 60% | D6: -1 | E6: Less poverty is better
A7: F1_06 | B7: 1 | C7: Total spending on health, % of total national GDP | D7: 0 | E7: Descriptive / context: no normative better-or-worse direction
A8: F1_07 | B8: 1 | C8: Public spending on health, % of total national GDP | D8: 0 | E8: Descriptive / context: no normative better-or-worse direction
A9: F1_08 | B9: 1 | C9: Mean spending on health per capita, US $ | D9: 0 | E9: Descriptive / context: no normative better-or-worse direction
A10: F1_09 | B10: 1 | C10: Inpatient care | D10: 0 | E10: Descriptive / context: no normative better-or-worse direction
A11: F1_10 | B11: 1 | C11: Outpatient care | D11: 0 | E11: Descriptive / context: no normative better-or-worse direction
A12: F1_11 | B12: 1 | C12: Long-term care | D12: 0 | E12: Descriptive / context: no normative better-or-worse direction
A13: F1_12 | B13: 1 | C13: Medical goods | D13: 0 | E13: Descriptive / context: no normative better-or-worse direction
... A100: F11_10 | B100: 11 | C100: Rural physicians per 1000 population | D100: 0 | E100: Descriptive / context: no normative better-or-worse direction

Sheet Rank_Changes
A1: Figure | B1: Domain | C1: Indicator ID | D1: Indicator | E1: Country | F1: Country label | G1: 2018 value (paper) | H1: 2026 value | I1: 2026 obs. year | J1: Rank in 2018 figure | K1: Rank in 2026 figure | L1: Include (1/0) | M1: n compared | N1: Rank 2018 (common set) | O1: Rank 2026 (common set) | P1: Rank change (+ = up) | Q1: Desirable direction | R1: Performance change (+ = better) | S1: Relative performance | T1: Comparability note | U1: Key
A2: 1 | B2: Spending | C2: F1_01 | D2: Overall population (in millions) | E2: USA | F2: US | G2: 323 | H2: 341.785 | I2: 2025 | J2: 1 | K2: 1 | L2: 1 | M2: =IF(L2=1,COUNTIFS($C$2:$C$1090,C2,$L$2:$L$1090,1),"") -> 11 | N2: =IF(L2=1,1+COUNTIFS($C$2:$C$1090,C2,$L$2:$L$1090,1,$G$2:$G$1090,">"&G2),"") -> 1 | O2: =IF(L2=1,1+COUNTIFS($C$2:$C$1090,C2,$L$2:$L$1090,1,$H$2:$H$1090,">"&H2),"") -> 1 | P2: =IF(L2=1,N2-O2,"") -> 0 | Q2: =INDEX(Directions!$D$2:$D$100,MATCH(C2,Directions!$A$2:$A$100,0)) -> 0 | R2: =IF(L2=1,P2*Q2,"") -> 0 | S2: =IF(L2<>1,"Excluded",IF(Q2=0,"No direction",IF(R2>0,"Better",IF(R2<0,"Worse","No change")))) -> No direction | U2: =C2&"|"&E2 -> F1_01|USA
A3: 1 | B3: Spending | C3: F1_01 | D3: Overall population (in millions) | E3: GBR | F3: UK | G3: 66 | H3: 69.487 | I3: 2025 | J3: 4 | K3: 4 | L3: 1 | M3: =IF(L3=1,COUNTIFS($C$2:$C$1090,C3,$L$2:$L$1090,1),"") -> 11 | N3: =IF(L3=1,1+COUNTIFS($C$2:$C$1090,C3,$L$2:$L$1090,1,$G$2:$G$1090,">"&G3),"") -> 4 | O3: =IF(L3=1,1+COUNTIFS($C$2:$C$1090,C3,$L$2:$L$1090,1,$H$2:$H$1090,">"&H3),"") -> 4 | P3: =IF(L3=1,N3-O3,"") -> 0 | Q3: =INDEX(Directions!$D$2:$D$100,MATCH(C3,Directions!$A$2:$A$100,0)) -> 0 | R3: =IF(L3=1,P3*Q3,"") -> 0 | S3: =IF(L3<>1,"Excluded",IF(Q3=0,"No direction",IF(R3>0,"Better",IF(R3<0,"Worse","No change")))) -> No direction | U3: =C3&"|"&E3 -> F1_01|GBR
A4: 1 | B4: Spending | C4: F1_01 | D4: Overall population (in millions) | E4: DEU | F4: Germany | G4: 83 | H4: 83.491 | I4: 2025 | J4: 3 | K4: 3 | L4: 1 | M4: =IF(L4=1,COUNTIFS($C$2:$C$1090,C4,$L$2:$L$1090,1),"") -> 11 | N4: =IF(L4=1,1+COUNTIFS($C$2:$C$1090,C4,$L$2:$L$1090,1,$G$2:$G$1090,">"&G4),"") -> 3 | O4: =IF(L4=1,1+COUNTIFS($C$2:$C$1090,C4,$L$2:$L$1090,1,$H$2:$H$1090,">"&H4),"") -> 3 | P4: =IF(L4=1,N4-O4,"") -> 0 | Q4: =INDEX(Directions!$D$2:$D$100,MATCH(C4,Directions!$A$2:$A$100,0)) -> 0 | R4: =IF(L4=1,P4*Q4,"") -> 0 | S4: =IF(L4<>1,"Excluded",IF(Q4=0,"No direction",IF(R4>0,"Better",IF(R4<0,"Worse","No change")))) -> No direction | U4: =C4&"|"&E4 -> F1_01|DEU
A5: 1 | B5: Spending | C5: F1_01 | D5: Overall population (in millions) | E5: SWE | F5: Sweden | G5: 10 | H5: 10.597 | I5: 2025 | J5: 9 | K5: 9 | L5: 1 | M5: =IF(L5=1,COUNTIFS($C$2:$C$1090,C5,$L$2:$L$1090,1),"") -> 11 | N5: =IF(L5=1,1+COUNTIFS($C$2:$C$1090,C5,$L$2:$L$1090,1,$G$2:$G$1090,">"&G5),"") -> 9 | O5: =IF(L5=1,1+COUNTIFS($C$2:$C$1090,C5,$L$2:$L$1090,1,$H$2:$H$1090,">"&H5),"") -> 9 | P5: =IF(L5=1,N5-O5,"") -> 0 | Q5: =INDEX(Directions!$D$2:$D$100,MATCH(C5,Directions!$A$2:$A$100,0)) -> 0 | R5: =IF(L5=1,P5*Q5,"") -> 0 | S5: =IF(L5<>1,"Excluded",IF(Q5=0,"No direction",IF(R5>0,"Better",IF(R5<0,"Worse","No change")))) -> No direction | U5: =C5&"|"&E5 -> F1_01|SWE
A6: 1 | B6: Spending | C6: F1_01 | D6: Overall population (in millions) | E6: FRA | F6: France | G6: 64 | H6: 68.72 | I6: 2025 | J6: 5 | K6: 5 | L6: 1 | M6: =IF(L6=1,COUNTIFS($C$2:$C$1090,C6,$L$2:$L$1090,1),"") -> 11 | N6: =IF(L6=1,1+COUNTIFS($C$2:$C$1090,C6,$L$2:$L$1090,1,$G$2:$G$1090,">"&G6),"") -> 5 | O6: =IF(L6=1,1+COUNTIFS($C$2:$C$1090,C6,$L$2:$L$1090,1,$H$2:$H$1090,">"&H6),"") -> 5 | P6: =IF(L6=1,N6-O6,"") -> 0 | Q6: =INDEX(Directions!$D$2:$D$100,MATCH(C6,Directions!$A$2:$A$100,0)) -> 0 | R6: =IF(L6=1,P6*Q6,"") -> 0 | S6: =IF(L6<>1,"Excluded",IF(Q6=0,"No direction",IF(R6>0,"Better",IF(R6<0,"Worse","No change")))) -> No direction | U6: =C6&"|"&E6 -> F1_01|FRA
A7: 1 | B7: Spending | C7: F1_01 | D7: Overall population (in millions) | E7: NLD | F7: NLD | G7: 17 | H7: 18.088 | I7: 2025 | J7: 8 | K7: 8 | L7: 1 | M7: =IF(L7=1,COUNTIFS($C$2:$C$1090,C7,$L$2:$L$1090,1),"") -> 11 | N7: =IF(L7=1,1+COUNTIFS($C$2:$C$1090,C7,$L$2:$L$1090,1,$G$2:$G$1090,">"&G7),"") -> 8 | O7: =IF(L7=1,1+COUNTIFS($C$2:$C$1090,C7,$L$2:$L$1090,1,$H$2:$H$1090,">"&H7),"") -> 8 | P7: =IF(L7=1,N7-O7,"") -> 0 | Q7: =INDEX(Directions!$D$2:$D$100,MATCH(C7,Directions!$A$2:$A$100,0)) -> 0 | R7: =IF(L7=1,P7*Q7,"") -> 0 | S7: =IF(L7<>1,"Excluded",IF(Q7=0,"No direction",IF(R7>0,"Better",IF(R7<0,"Worse","No change")))) -> No direction | U7: =C7&"|"&E7 -> F1_01|NLD
A8: 1 | B8: Spending | C8: F1_01 | D8: Overall population (in millions) | E8: CHE | F8: CHE | G8: 8 | H8: 9.092 | I8: 2025 | J8: 10 | K8: 10 | L8: 1 | M8: =IF(L8=1,COUNTIFS($C$2:$C$1090,C8,$L$2:$L$1090,1),"") -> 11 | N8: =IF(L8=1,1+COUNTIFS($C$2:$C$1090,C8,$L$2:$L$1090,1,$G$2:$G$1090,">"&G8),"") -> 10 | O8: =IF(L8=1,1+COUNTIFS($C$2:$C$1090,C8,$L$2:$L$1090,1,$H$2:$H$1090,">"&H8),"") -> 10 | P8: =IF(L8=1,N8-O8,"") -> 0 | Q8: =INDEX(Directions!$D$2:$D$100,MATCH(C8,Directions!$A$2:$A$100,0)) -> 0 | R8: =IF(L8=1,P8*Q8,"") -> 0 | S8: =IF(L8<>1,"Excluded",IF(Q8=0,"No direction",IF(R8>0,"Better",IF(R8<0,"Worse","No change")))) -> No direction | U8: =C8&"|"&E8 -> F1_01|CHE
A9: 1 | B9: Spending | C9: F1_01 | D9: Overall population (in millions) | E9: DNK | F9: Denmark | G9: 6 | H9: 6.009 | I9: 2025 | J9: 11 | K9: 11 | L9: 1 | M9: =IF(L9=1,COUNTIFS($C$2:$C$1090,C9,$L$2:$L$1090,1),"") -> 11 | N9: =IF(L9=1,1+COUNTIFS($C$2:$C$1090,C9,$L$2:$L$1090,1,$G$2:$G$1090,">"&G9),"") -> 11 | O9: =IF(L9=1,1+COUNTIFS($C$2:$C$1090,C9,$L$2:$L$1090,1,$H$2:$H$1090,">"&H9),"") -> 11 | P9: =IF(L9=1,N9-O9,"") -> 0 | Q9: =INDEX(Directions!$D$2:$D$100,MATCH(C9,Directions!$A$2:$A$100,0)) -> 0 | R9: =IF(L9=1,P9*Q9,"") -> 0 | S9: =IF(L9<>1,"Excluded",IF(Q9=0,"No direction",IF(R9>0,"Better",IF(R9<0,"Worse","No change")))) -> No direction | U9: =C9&"|"&E9 -> F1_01|DNK
A10: 1 | B10: Spending | C10: F1_01 | D10: Overall population (in millions) | E10: CAN | F10: Canada | G10: 36 | H10: 41.652 | I10: 2025 | J10: 6 | K10: 6 | L10: 1 | M10: =IF(L10=1,COUNTIFS($C$2:$C$1090,C10,$L$2:$L$1090,1),"") -> 11 | N10: =IF(L10=1,1+COUNTIFS($C$2:$C$1090,C10,$L$2:$L$1090,1,$G$2:$G$1090,">"&G10),"") -> 6 | O10: =IF(L10=1,1+COUNTIFS($C$2:$C$1090,C10,$L$2:$L$1090,1,$H$2:$H$1090,">"&H10),"") -> 6 | P10: =IF(L10=1,N10-O10,"") -> 0 | Q10: =INDEX(Directions!$D$2:$D$100,MATCH(C10,Directions!$A$2:$A$100,0)) -> 0 | R10: =IF(L10=1,P10*Q10,"") -> 0 | S10: =IF(L10<>1,"Excluded",IF(Q10=0,"No direction",IF(R10>0,"Better",IF(R10<0,"Worse","No change")))) -> No direction | U10: =C10&"|"&E10 -> F1_01|CAN
A11: 1 | B11: Spending | C11: F1_01 | D11: Overall population (in millions) | E11: JPN | F11: Japan | G11: 127 | H11: 123.367 | I11: 2025 | J11: 2 | K11: 2 | L11: 1 | M11: =IF(L11=1,COUNTIFS($C$2:$C$1090,C11,$L$2:$L$1090,1),"") -> 11 | N11: =IF(L11=1,1+COUNTIFS($C$2:$C$1090,C11,$L$2:$L$1090,1,$G$2:$G$1090,">"&G11),"") -> 2 | O11: =IF(L11=1,1+COUNTIFS($C$2:$C$1090,C11,$L$2:$L$1090,1,$H$2:$H$1090,">"&H11),"") -> 2 | P11: =IF(L11=1,N11-O11,"") -> 0 | Q11: =INDEX(Directions!$D$2:$D$100,MATCH(C11,Directions!$A$2:$A$100,0)) -> 0 | R11: =IF(L11=1,P11*Q11,"") -> 0 | S11: =IF(L11<>1,"Excluded",IF(Q11=0,"No direction",IF(R11>0,"Better",IF(R11<0,"Worse","No change")))) -> No direction | U11: =C11&"|"&E11 -> F1_01|JPN
A12: 1 | B12: Spending | C12: F1_01 | D12: Overall population (in millions) | E12: AUS | F12: Australia | G12: 24 | H12: 27.614 | I12: 2025 | J12: 7 | K12: 7 | L12: 1 | M12: =IF(L12=1,COUNTIFS($C$2:$C$1090,C12,$L$2:$L$1090,1),"") -> 11 | N12: =IF(L12=1,1+COUNTIFS($C$2:$C$1090,C12,$L$2:$L$1090,1,$G$2:$G$1090,">"&G12),"") -> 7 | O12: =IF(L12=1,1+COUNTIFS($C$2:$C$1090,C12,$L$2:$L$1090,1,$H$2:$H$1090,">"&H12),"") -> 7 | P12: =IF(L12=1,N12-O12,"") -> 0 | Q12: =INDEX(Directions!$D$2:$D$100,MATCH(C12,Directions!$A$2:$A$100,0)) -> 0 | R12: =IF(L12=1,P12*Q12,"") -> 0 | S12: =IF(L12<>1,"Excluded",IF(Q12=0,"No direction",IF(R12>0,"Better",IF(R12<0,"Worse","No change")))) -> No direction | U12: =C12&"|"&E12 -> F1_01|AUS
A13: 1 | B13: Spending | C13: F1_02 | D13: Population ≥65 y, % | E13: USA | F13: US | G13: 14.5 | H13: 18.9 | I13: 2025 | J13: 11 | K13: 10 | L13: 1 | M13: =IF(L13=1,COUNTIFS($C$2:$C$1090,C13,$L$2:$L$1090,1),"") -> 11 | N13: =IF(L13=1,1+COUNTIFS($C$2:$C$1090,C13,$L$2:$L$1090,1,$G$2:$G$1090,">"&G13),"") -> 11 | O13: =IF(L13=1,1+COUNTIFS($C$2:$C$1090,C13,$L$2:$L$1090,1,$H$2:$H$1090,">"&H13),"") -> 10 | P13: =IF(L13=1,N13-O13,"") -> 1 | Q13: =INDEX(Directions!$D$2:$D$100,MATCH(C13,Directions!$A$2:$A$100,0)) -> 0 | R13: =IF(L13=1,P13*Q13,"") -> 0 | S13: =IF(L13<>1,"Excluded",IF(Q13=0,"No direction",IF(R13>0,"Better",IF(R13<0,"Worse","No change")))) -> No direction | U13: =C13&"|"&E13 -> F1_02|USA
... A34: 1 | B34: Spending | C34: F1_03 | D34: GDP per capita, US $ (in thousands) | E34: AUS | F34: Australia | G34: 45.1 | H34: 75.21 | I34: 2025 | J34: 6 | K34: 6 | L34: 1 | M34: =IF(L34=1,COUNTIFS($C$2:$C$1090,C34,$L$2:$L$1090,1),"") -> 11 | N34: =IF(L34=1,1+COUNTIFS($C$2:$C$1090,C34,$L$2:$L$1090,1,$G$2:$G$1090,">"&G34),"") -> 6 | O34: =IF(L34=1,1+COUNTIFS($C$2:$C$1090,C34,$L$2:$L$1090,1,$H$2:$H$1090,">"&H34),"") -> 6 | P34: =IF(L34=1,N34-O34,"") -> 0 | Q34: =INDEX(Directions!$D$2:$D$100,MATCH(C34,Directions!$A$2:$A$100,0)) -> 0 | R34: =IF(L34=1,P34*Q34,"") -> 0 | S34: =IF(L34<>1,"Excluded",IF(Q34=0,"No direction",IF(R34>0,"Better",IF(R34<0,"Worse","No change")))) -> No direction | U34: =C34&"|"&E34 -> F1_03|AUS
A35: 1 | B35: Spending | C35: F1_04 | D35: Land area (× 1000 sq km) | E35: USA | F35: US | G35: 9834 | H35: 9147.4 | I35: 2023 | J35: 2 | K35: 1 | L35: 1 | M35: =IF(L35=1,COUNTIFS($C$2:$C$1090,C35,$L$2:$L$1090,1),"") -> 11 | N35: =IF(L35=1,1+COUNTIFS($C$2:$C$1090,C35,$L$2:$L$1090,1,$G$2:$G$1090,">"&G35),"") -> 2 | O35: =IF(L35=1,1+COUNTIFS($C$2:$C$1090,C35,$L$2:$L$1090,1,$H$2:$H$1090,">"&H35),"") -> 1 | P35: =IF(L35=1,N35-O35,"") -> 1 | Q35: =INDEX(Directions!$D$2:$D$100,MATCH(C35,Directions!$A$2:$A$100,0)) -> 0 | R35: =IF(L35=1,P35*Q35,"") -> 0 | S35: =IF(L35<>1,"Excluded",IF(Q35=0,"No direction",IF(R35>0,"Better",IF(R35<0,"Worse","No change")))) -> No direction | T35: Land area now vs surface area in 2018 (Canada/US order is an artifact) | U35: =C35&"|"&E35 -> F1_04|USA
A36: 1 | B36: Spending | C36: F1_04 | D36: Land area (× 1000 sq km) | E36: GBR | F36: UK | G36: 244 | H36: 241.9 | I36: 2023 | J36: 8 | K36: 8 | L36: 1 | M36: =IF(L36=1,COUNTIFS($C$2:$C$1090,C36,$L$2:$L$1090,1),"") -> 11 | N36: =IF(L36=1,1+COUNTIFS($C$2:$C$1090,C36,$L$2:$L$1090,1,$G$2:$G$1090,">"&G36),"") -> 8 | O36: =IF(L36=1,1+COUNTIFS($C$2:$C$1090,C36,$L$2:$L$1090,1,$H$2:$H$1090,">"&H36),"") -> 8 | P36: =IF(L36=1,N36-O36,"") -> 0 | Q36: =INDEX(Directions!$D$2:$D$100,MATCH(C36,Directions!$A$2:$A$100,0)) -> 0 | R36: =IF(L36=1,P36*Q36,"") -> 0 | S36: =IF(L36<>1,"Excluded",IF(Q36=0,"No direction",IF(R36>0,"Better",IF(R36<0,"Worse","No change")))) -> No direction | T36: Land area now vs surface area in 2018 (Canada/US order is an artifact) | U36: =C36&"|"&E36 -> F1_04|GBR
A37: 1 | B37: Spending | C37: F1_04 | D37: Land area (× 1000 sq km) | E37: DEU | F37: Germany | G37: 357 | H37: 349.4 | I37: 2023 | J37: 7 | K37: 7 | L37: 1 | M37: =IF(L37=1,COUNTIFS($C$2:$C$1090,C37,$L$2:$L$1090,1),"") -> 11 | N37: =IF(L37=1,1+COUNTIFS($C$2:$C$1090,C37,$L$2:$L$1090,1,$G$2:$G$1090,">"&G37),"") -> 7 | O37: =IF(L37=1,1+COUNTIFS($C$2:$C$1090,C37,$L$2:$L$1090,1,$H$2:$H$1090,">"&H37),"") -> 7 | P37: =IF(L37=1,N37-O37,"") -> 0 | Q37: =INDEX(Directions!$D$2:$D$100,MATCH(C37,Directions!$A$2:$A$100,0)) -> 0 | R37: =IF(L37=1,P37*Q37,"") -> 0 | S37: =IF(L37<>1,"Excluded",IF(Q37=0,"No direction",IF(R37>0,"Better",IF(R37<0,"Worse","No change")))) -> No direction | T37: Land area now vs surface area in 2018 (Canada/US order is an artifact) | U37: =C37&"|"&E37 -> F1_04|DEU
A38: 1 | B38: Spending | C38: F1_04 | D38: Land area (× 1000 sq km) | E38: SWE | F38: Sweden | G38: 450 | H38: 407.3 | I38: 2023 | J38: 5 | K38: 5 | L38: 1 | M38: =IF(L38=1,COUNTIFS($C$2:$C$1090,C38,$L$2:$L$1090,1),"") -> 11 | N38: =IF(L38=1,1+COUNTIFS($C$2:$C$1090,C38,$L$2:$L$1090,1,$G$2:$G$1090,">"&G38),"") -> 5 | O38: =IF(L38=1,1+COUNTIFS($C$2:$C$1090,C38,$L$2:$L$1090,1,$H$2:$H$1090,">"&H38),"") -> 5 | P38: =IF(L38=1,N38-O38,"") -> 0 | Q38: =INDEX(Directions!$D$2:$D$100,MATCH(C38,Directions!$A$2:$A$100,0)) -> 0 | R38: =IF(L38=1,P38*Q38,"") -> 0 | S38: =IF(L38<>1,"Excluded",IF(Q38=0,"No direction",IF(R38>0,"Better",IF(R38<0,"Worse","No change")))) -> No direction | T38: Land area now vs surface area in 2018 (Canada/US order is an artifact) | U38: =C38&"|"&E38 -> F1_04|SWE
A39: 1 | B39: Spending | C39: F1_04 | D39: Land area (× 1000 sq km) | E39: FRA | F39: France | G39: 549 | H39: 539 | I39: 2023 | J39: 4 | K39: 4 | L39: 1 | M39: =IF(L39=1,COUNTIFS($C$2:$C$1090,C39,$L$2:$L$1090,1),"") -> 11 | N39: =IF(L39=1,1+COUNTIFS($C$2:$C$1090,C39,$L$2:$L$1090,1,$G$2:$G$1090,">"&G39),"") -> 4 | O39: =IF(L39=1,1+COUNTIFS($C$2:$C$1090,C39,$L$2:$L$1090,1,$H$2:$H$1090,">"&H39),"") -> 4 | P39: =IF(L39=1,N39-O39,"") -> 0 | Q39: =INDEX(Directions!$D$2:$D$100,MATCH(C39,Directions!$A$2:$A$100,0)) -> 0 | R39: =IF(L39=1,P39*Q39,"") -> 0 | S39: =IF(L39<>1,"Excluded",IF(Q39=0,"No direction",IF(R39>0,"Better",IF(R39<0,"Worse","No change")))) -> No direction | T39: Land area now vs surface area in 2018 (Canada/US order is an artifact) | U39: =C39&"|"&E39 -> F1_04|FRA
A40: 1 | B40: Spending | C40: F1_04 | D40: Land area (× 1000 sq km) | E40: NLD | F40: NLD | G40: 42 | H40: 33.7 | I40: 2023 | J40: 10 | K40: 11 | L40: 1 | M40: =IF(L40=1,COUNTIFS($C$2:$C$1090,C40,$L$2:$L$1090,1),"") -> 11 | N40: =IF(L40=1,1+COUNTIFS($C$2:$C$1090,C40,$L$2:$L$1090,1,$G$2:$G$1090,">"&G40),"") -> 10 | O40: =IF(L40=1,1+COUNTIFS($C$2:$C$1090,C40,$L$2:$L$1090,1,$H$2:$H$1090,">"&H40),"") -> 11 | P40: =IF(L40=1,N40-O40,"") -> -1 | Q40: =INDEX(Directions!$D$2:$D$100,MATCH(C40,Directions!$A$2:$A$100,0)) -> 0 | R40: =IF(L40=1,P40*Q40,"") -> 0 | S40: =IF(L40<>1,"Excluded",IF(Q40=0,"No direction",IF(R40>0,"Better",IF(R40<0,"Worse","No change")))) -> No direction | T40: Land area now vs surface area in 2018 (Canada/US order is an artifact) | U40: =C40&"|"&E40 -> F1_04|NLD
A41: 1 | B41: Spending | C41: F1_04 | D41: Land area (× 1000 sq km) | E41: CHE | F41: CHE | G41: 42 | H41: 39.5 | I41: 2023 | J41: 11 | K41: 10 | L41: 1 | M41: =IF(L41=1,COUNTIFS($C$2:$C$1090,C41,$L$2:$L$1090,1),"") -> 11 | N41: =IF(L41=1,1+COUNTIFS($C$2:$C$1090,C41,$L$2:$L$1090,1,$G$2:$G$1090,">"&G41),"") -> 10 | O41: =IF(L41=1,1+COUNTIFS($C$2:$C$1090,C41,$L$2:$L$1090,1,$H$2:$H$1090,">"&H41),"") -> 10 | P41: =IF(L41=1,N41-O41,"") -> 0 | Q41: =INDEX(Directions!$D$2:$D$100,MATCH(C41,Directions!$A$2:$A$100,0)) -> 0 | R41: =IF(L41=1,P41*Q41,"") -> 0 | S41: =IF(L41<>1,"Excluded",IF(Q41=0,"No direction",IF(R41>0,"Better",IF(R41<0,"Worse","No change")))) -> No direction | T41: Land area now vs surface area in 2018 (Canada/US order is an artifact) | U41: =C41&"|"&E41 -> F1_04|CHE
A42: 1 | B42: Spending | C42: F1_04 | D42: Land area (× 1000 sq km) | E42: DNK | F42: Denmark | G42: 43 | H42: 40 | I42: 2023 | J42: 9 | K42: 9 | L42: 1 | M42: =IF(L42=1,COUNTIFS($C$2:$C$1090,C42,$L$2:$L$1090,1),"") -> 11 | N42: =IF(L42=1,1+COUNTIFS($C$2:$C$1090,C42,$L$2:$L$1090,1,$G$2:$G$1090,">"&G42),"") -> 9 | O42: =IF(L42=1,1+COUNTIFS($C$2:$C$1090,C42,$L$2:$L$1090,1,$H$2:$H$1090,">"&H42),"") -> 9 | P42: =IF(L42=1,N42-O42,"") -> 0 | Q42: =INDEX(Directions!$D$2:$D$100,MATCH(C42,Directions!$A$2:$A$100,0)) -> 0 | R42: =IF(L42=1,P42*Q42,"") -> 0 | S42: =IF(L42<>1,"Excluded",IF(Q42=0,"No direction",IF(R42>0,"Better",IF(R42<0,"Worse","No change")))) -> No direction | T42: Land area now vs surface area in 2018 (Canada/US order is an artifact) | U42: =C42&"|"&E42 -> F1_04|DNK
A43: 1 | B43: Spending | C43: F1_04 | D43: Land area (× 1000 sq km) | E43: CAN | F43: Canada | G43: 9985 | H43: 8788.7 | I43: 2023 | J43: 1 | K43: 2 | L43: 1 | M43: =IF(L43=1,COUNTIFS($C$2:$C$1090,C43,$L$2:$L$1090,1),"") -> 11 | N43: =IF(L43=1,1+COUNTIFS($C$2:$C$1090,C43,$L$2:$L$1090,1,$G$2:$G$1090,">"&G43),"") -> 1 | O43: =IF(L43=1,1+COUNTIFS($C$2:$C$1090,C43,$L$2:$L$1090,1,$H$2:$H$1090,">"&H43),"") -> 2 | P43: =IF(L43=1,N43-O43,"") -> -1 | Q43: =INDEX(Directions!$D$2:$D$100,MATCH(C43,Directions!$A$2:$A$100,0)) -> 0 | R43: =IF(L43=1,P43*Q43,"") -> 0 | S43: =IF(L43<>1,"Excluded",IF(Q43=0,"No direction",IF(R43>0,"Better",IF(R43<0,"Worse","No change")))) -> No direction | T43: Land area now vs surface area in 2018 (Canada/US order is an artifact) | U43: =C43&"|"&E43 -> F1_04|CAN
A44: 1 | B44: Spending | C44: F1_04 | D44: Land area (× 1000 sq km) | E44: JPN | F44: Japan | G44: 378 | H44: 364.6 | I44: 2023 | J44: 6 | K44: 6 | L44: 1 | M44: =IF(L44=1,COUNTIFS($C$2:$C$1090,C44,$L$2:$L$1090,1),"") -> 11 | N44: =IF(L44=1,1+COUNTIFS($C$2:$C$1090,C44,$L$2:$L$1090,1,$G$2:$G$1090,">"&G44),"") -> 6 | O44: =IF(L44=1,1+COUNTIFS($C$2:$C$1090,C44,$L$2:$L$1090,1,$H$2:$H$1090,">"&H44),"") -> 6 | P44: =IF(L44=1,N44-O44,"") -> 0 | Q44: =INDEX(Directions!$D$2:$D$100,MATCH(C44,Directions!$A$2:$A$100,0)) -> 0 | R44: =IF(L44=1,P44*Q44,"") -> 0 | S44: =IF(L44<>1,"Excluded",IF(Q44=0,"No direction",IF(R44>0,"Better",IF(R44<0,"Worse","No change")))) -> No direction | T44: Land area now vs surface area in 2018 (Canada/US order is an artifact) | U44: =C44&"|"&E44 -> F1_04|JPN
A45: 1 | B45: Spending | C45: F1_04 | D45: Land area (× 1000 sq km) | E45: AUS | F45: Australia | G45: 7741 | H45: 7692 | I45: 2023 | J45: 3 | K45: 3 | L45: 1 | M45: =IF(L45=1,COUNTIFS($C$2:$C$1090,C45,$L$2:$L$1090,1),"") -> 11 | N45: =IF(L45=1,1+COUNTIFS($C$2:$C$1090,C45,$L$2:$L$1090,1,$G$2:$G$1090,">"&G45),"") -> 3 | O45: =IF(L45=1,1+COUNTIFS($C$2:$C$1090,C45,$L$2:$L$1090,1,$H$2:$H$1090,">"&H45),"") -> 3 | P45: =IF(L45=1,N45-O45,"") -> 0 | Q45: =INDEX(Directions!$D$2:$D$100,MATCH(C45,Directions!$A$2:$A$100,0)) -> 0 | R45: =IF(L45=1,P45*Q45,"") -> 0 | S45: =IF(L45<>1,"Excluded",IF(Q45=0,"No direction",IF(R45>0,"Better",IF(R45<0,"Worse","No change")))) -> No direction | T45: Land area now vs surface area in 2018 (Canada/US order is an artifact) | U45: =C45&"|"&E45 -> F1_04|AUS
A46: 1 | B46: Spending | C46: F1_05 | D46: Poverty rate, % below poverty line of 60% | E46: USA | F46: US | G46: 24 | H46: 25.1 | I46: 2023 | J46: 1 | K46: 1 | L46: 1 | M46: =IF(L46=1,COUNTIFS($C$2:$C$1090,C46,$L$2:$L$1090,1),"") -> 11 | N46: =IF(L46=1,1+COUNTIFS($C$2:$C$1090,C46,$L$2:$L$1090,1,$G$2:$G$1090,">"&G46),"") -> 1 | O46: =IF(L46=1,1+COUNTIFS($C$2:$C$1090,C46,$L$2:$L$1090,1,$H$2:$H$1090,">"&H46),"") -> 1 | P46: =IF(L46=1,N46-O46,"") -> 0 | Q46: =INDEX(Directions!$D$2:$D$100,MATCH(C46,Directions!$A$2:$A$100,0)) -> -1 | R46: =IF(L46=1,P46*Q46,"") -> 0 | S46: =IF(L46<>1,"Excluded",IF(Q46=0,"No direction",IF(R46>0,"Better",IF(R46<0,"Worse","No change")))) -> No change | U46: =C46&"|"&E46 -> F1_05|USA
A47: 1 | B47: Spending | C47: F1_05 | D47: Poverty rate, % below poverty line of 60% | E47: GBR | F47: UK | G47: 18 | H47: 18.4 | I47: 2023 | J47: 5 | K47: 5 | L47: 1 | M47: =IF(L47=1,COUNTIFS($C$2:$C$1090,C47,$L$2:$L$1090,1),"") -> 11 | N47: =IF(L47=1,1+COUNTIFS($C$2:$C$1090,C47,$L$2:$L$1090,1,$G$2:$G$1090,">"&G47),"") -> 5 | O47: =IF(L47=1,1+COUNTIFS($C$2:$C$1090,C47,$L$2:$L$1090,1,$H$2:$H$1090,">"&H47),"") -> 5 | P47: =IF(L47=1,N47-O47,"") -> 0 | Q47: =INDEX(Directions!$D$2:$D$100,MATCH(C47,Directions!$A$2:$A$100,0)) -> -1 | R47: =IF(L47=1,P47*Q47,"") -> 0 | S47: =IF(L47<>1,"Excluded",IF(Q47=0,"No direction",IF(R47>0,"Better",IF(R47<0,"Worse","No change")))) -> No change | U47: =C47&"|"&E47 -> F1_05|GBR
A48: 1 | B48: Spending | C48: F1_05 | D48: Poverty rate, % below poverty line of 60% | E48: DEU | F48: Germany | G48: 16 | H48: 17.5 | I48: 2023 | J48: 8 | K48: 6 | L48: 1 | M48: =IF(L48=1,COUNTIFS($C$2:$C$1090,C48,$L$2:$L$1090,1),"") -> 11 | N48: =IF(L48=1,1+COUNTIFS($C$2:$C$1090,C48,$L$2:$L$1090,1,$G$2:$G$1090,">"&G48),"") -> 8 | O48: =IF(L48=1,1+COUNTIFS($C$2:$C$1090,C48,$L$2:$L$1090,1,$H$2:$H$1090,">"&H48),"") -> 6 | P48: =IF(L48=1,N48-O48,"") -> 2 | Q48: =INDEX(Directions!$D$2:$D$100,MATCH(C48,Directions!$A$2:$A$100,0)) -> -1 | R48: =IF(L48=1,P48*Q48,"") -> -2 | S48: =IF(L48<>1,"Excluded",IF(Q48=0,"No direction",IF(R48>0,"Better",IF(R48<0,"Worse","No change")))) -> Worse | U48: =C48&"|"&E48 -> F1_05|DEU
A49: 1 | B49: Spending | C49: F1_05 | D49: Poverty rate, % below poverty line of 60% | E49: SWE | F49: Sweden | G49: 17 | H49: 15.5 | I49: 2024 | J49: 6 | K49: 8 | L49: 1 | M49: =IF(L49=1,COUNTIFS($C$2:$C$1090,C49,$L$2:$L$1090,1),"") -> 11 | N49: =IF(L49=1,1+COUNTIFS($C$2:$C$1090,C49,$L$2:$L$1090,1,$G$2:$G$1090,">"&G49),"") -> 6 | O49: =IF(L49=1,1+COUNTIFS($C$2:$C$1090,C49,$L$2:$L$1090,1,$H$2:$H$1090,">"&H49),"") -> 8 | P49: =IF(L49=1,N49-O49,"") -> -2 | Q49: =INDEX(Directions!$D$2:$D$100,MATCH(C49,Directions!$A$2:$A$100,0)) -> -1 | R49: =IF(L49=1,P49*Q49,"") -> 2 | S49: =IF(L49<>1,"Excluded",IF(Q49=0,"No direction",IF(R49>0,"Better",IF(R49<0,"Worse","No change")))) -> Better | U49: =C49&"|"&E49 -> F1_05|SWE
A50: 1 | B50: Spending | C50: F1_05 | D50: Poverty rate, % below poverty line of 60% | E50: FRA | F50: France | G50: 15 | H50: 15.4 | I50: 2023 | J50: 9 | K50: 9 | L50: 1 | M50: =IF(L50=1,COUNTIFS($C$2:$C$1090,C50,$L$2:$L$1090,1),"") -> 11 | N50: =IF(L50=1,1+COUNTIFS($C$2:$C$1090,C50,$L$2:$L$1090,1,$G$2:$G$1090,">"&G50),"") -> 9 | O50: =IF(L50=1,1+COUNTIFS($C$2:$C$1090,C50,$L$2:$L$1090,1,$H$2:$H$1090,">"&H50),"") -> 9 | P50: =IF(L50=1,N50-O50,"") -> 0 | Q50: =INDEX(Directions!$D$2:$D$100,MATCH(C50,Directions!$A$2:$A$100,0)) -> -1 | R50: =IF(L50=1,P50*Q50,"") -> 0 | S50: =IF(L50<>1,"Excluded",IF(Q50=0,"No direction",IF(R50>0,"Better",IF(R50<0,"Worse","No change")))) -> No change | U50: =C50&"|"&E50 -> F1_05|FRA
A51: 1 | B51: Spending | C51: F1_05 | D51: Poverty rate, % below poverty line of 60% | E51: NLD | F51: NLD | G51: 15 | H51: 15 | I51: 2024 | J51: 10 | K51: 10 | L51: 1 | M51: =IF(L51=1,COUNTIFS($C$2:$C$1090,C51,$L$2:$L$1090,1),"") -> 11 | N51: =IF(L51=1,1+COUNTIFS($C$2:$C$1090,C51,$L$2:$L$1090,1,$G$2:$G$1090,">"&G51),"") -> 9 | O51: =IF(L51=1,1+COUNTIFS($C$2:$C$1090,C51,$L$2:$L$1090,1,$H$2:$H$1090,">"&H51),"") -> 10 | P51: =IF(L51=1,N51-O51,"") -> -1 | Q51: =INDEX(Directions!$D$2:$D$100,MATCH(C51,Directions!$A$2:$A$100,0)) -> -1 | R51: =IF(L51=1,P51*Q51,"") -> 1 | S51: =IF(L51<>1,"Excluded",IF(Q51=0,"No direction",IF(R51>0,"Better",IF(R51<0,"Worse","No change")))) -> Better | U51: =C51&"|"&E51 -> F1_05|NLD
A52: 1 | B52: Spending | C52: F1_05 | D52: Poverty rate, % below poverty line of 60% | E52: CHE | F52: CHE | G52: 17 | H52: 16.4 | I52: 2023 | J52: 7 | K52: 7 | L52: 1 | M52: =IF(L52=1,COUNTIFS($C$2:$C$1090,C52,$L$2:$L$1090,1),"") -> 11 | N52: =IF(L52=1,1+COUNTIFS($C$2:$C$1090,C52,$L$2:$L$1090,1,$G$2:$G$1090,">"&G52),"") -> 6 | O52: =IF(L52=1,1+COUNTIFS($C$2:$C$1090,C52,$L$2:$L$1090,1,$H$2:$H$1090,">"&H52),"") -> 7 | P52: =IF(L52=1,N52-O52,"") -> -1 | Q52: =INDEX(Directions!$D$2:$D$100,MATCH(C52,Directions!$A$2:$A$100,0)) -> -1 | R52: =IF(L52=1,P52*Q52,"") -> 1 | S52: =IF(L52<>1,"Excluded",IF(Q52=0,"No direction",IF(R52>0,"Better",IF(R52<0,"Worse","No change")))) -> Better | U52: =C52&"|"&E52 -> F1_05|CHE
A53: 1 | B53: Spending | C53: F1_05 | D53: Poverty rate, % below poverty line of 60% | E53: DNK | F53: Denmark | G53: 12 | H53: 12.9 | I53: 2022 | J53: 11 | K53: 11 | L53: 1 | M53: =IF(L53=1,COUNTIFS($C$2:$C$1090,C53,$L$2:$L$1090,1),"") -> 11 | N53: =IF(L53=1,1+COUNTIFS($C$2:$C$1090,C53,$L$2:$L$1090,1,$G$2:$G$1090,">"&G53),"") -> 11 | O53: =IF(L53=1,1+COUNTIFS($C$2:$C$1090,C53,$L$2:$L$1090,1,$H$2:$H$1090,">"&H53),"") -> 11 | P53: =IF(L53=1,N53-O53,"") -> 0 | Q53: =INDEX(Directions!$D$2:$D$100,MATCH(C53,Directions!$A$2:$A$100,0)) -> -1 | R53: =IF(L53=1,P53*Q53,"") -> 0 | S53: =IF(L53<>1,"Excluded",IF(Q53=0,"No direction",IF(R53>0,"Better",IF(R53<0,"Worse","No change")))) -> No change | U53: =C53&"|"&E53 -> F1_05|DNK
A54: 1 | B54: Spending | C54: F1_05 | D54: Poverty rate, % below poverty line of 60% | E54: CAN | F54: Canada | G54: 21 | H54: 18.8 | I54: 2023 | J54: 3 | K54: 4 | L54: 1 | M54: =IF(L54=1,COUNTIFS($C$2:$C$1090,C54,$L$2:$L$1090,1),"") -> 11 | N54: =IF(L54=1,1+COUNTIFS($C$2:$C$1090,C54,$L$2:$L$1090,1,$G$2:$G$1090,">"&G54),"") -> 3 | O54: =IF(L54=1,1+COUNTIFS($C$2:$C$1090,C54,$L$2:$L$1090,1,$H$2:$H$1090,">"&H54),"") -> 4 | P54: =IF(L54=1,N54-O54,"") -> -1 | Q54: =INDEX(Directions!$D$2:$D$100,MATCH(C54,Directions!$A$2:$A$100,0)) -> -1 | R54: =IF(L54=1,P54*Q54,"") -> 1 | S54: =IF(L54<>1,"Excluded",IF(Q54=0,"No direction",IF(R54>0,"Better",IF(R54<0,"Worse","No change")))) -> Better | U54: =C54&"|"&E54 -> F1_05|CAN
A55: 1 | B55: Spending | C55: F1_05 | D55: Poverty rate, % below poverty line of 60% | E55: JPN | F55: Japan | G55: 22 | H55: 21.3 | I55: 2021 | J55: 2 | K55: 2 | L55: 1 | M55: =IF(L55=1,COUNTIFS($C$2:$C$1090,C55,$L$2:$L$1090,1),"") -> 11 | N55: =IF(L55=1,1+COUNTIFS($C$2:$C$1090,C55,$L$2:$L$1090,1,$G$2:$G$1090,">"&G55),"") -> 2 | O55: =IF(L55=1,1+COUNTIFS($C$2:$C$1090,C55,$L$2:$L$1090,1,$H$2:$H$1090,">"&H55),"") -> 2 | P55: =IF(L55=1,N55-O55,"") -> 0 | Q55: =INDEX(Directions!$D$2:$D$100,MATCH(C55,Directions!$A$2:$A$100,0)) -> -1 | R55: =IF(L55=1,P55*Q55,"") -> 0 | S55: =IF(L55<>1,"Excluded",IF(Q55=0,"No direction",IF(R55>0,"Better",IF(R55<0,"Worse","No change")))) -> No change | U55: =C55&"|"&E55 -> F1_05|JPN
A56: 1 | B56: Spending | C56: F1_05 | D56: Poverty rate, % below poverty line of 60% | E56: AUS | F56: Australia | G56: 20 | H56: 20.4 | I56: 2020 | J56: 4 | K56: 3 | L56: 1 | M56: =IF(L56=1,COUNTIFS($C$2:$C$1090,C56,$L$2:$L$1090,1),"") -> 11 | N56: =IF(L56=1,1+COUNTIFS($C$2:$C$1090,C56,$L$2:$L$1090,1,$G$2:$G$1090,">"&G56),"") -> 4 | O56: =IF(L56=1,1+COUNTIFS($C$2:$C$1090,C56,$L$2:$L$1090,1,$H$2:$H$1090,">"&H56),"") -> 3 | P56: =IF(L56=1,N56-O56,"") -> 1 | Q56: =INDEX(Directions!$D$2:$D$100,MATCH(C56,Directions!$A$2:$A$100,0)) -> -1 | R56: =IF(L56=1,P56*Q56,"") -> -1 | S56: =IF(L56<>1,"Excluded",IF(Q56=0,"No direction",IF(R56>0,"Better",IF(R56<0,"Worse","No change")))) -> Worse | U56: =C56&"|"&E56 -> F1_05|AUS
A57: 1 | B57: Spending | C57: F1_06 | D57: Total spending on health, % of total national GDP | E57: USA | F57: US | G57: 17.8 | H57: 16.69 | I57: 2023 | J57: 1 | K57: 1 | L57: 1 | M57: =IF(L57=1,COUNTIFS($C$2:$C$1090,C57,$L$2:$L$1090,1),"") -> 11 | N57: =IF(L57=1,1+COUNTIFS($C$2:$C$1090,C57,$L$2:$L$1090,1,$G$2:$G$1090,">"&G57),"") -> 1 | O57: =IF(L57=1,1+COUNTIFS($C$2:$C$1090,C57,$L$2:$L$1090,1,$H$2:$H$1090,">"&H57),"") -> 1 | P57: =IF(L57=1,N57-O57,"") -> 0 | Q57: =INDEX(Directions!$D$2:$D$100,MATCH(C57,Directions!$A$2:$A$100,0)) -> 0 | R57: =IF(L57=1,P57*Q57,"") -> 0 | S57: =IF(L57<>1,"Excluded",IF(Q57=0,"No direction",IF(R57>0,"Better",IF(R57<0,"Worse","No change")))) -> No direction | U57: =C57&"|"&E57 -> F1_06|USA
... A72: 1 | B72: Spending | C72: F1_07 | D72: Public spending on health, % of total national GDP | E72: FRA | F72: France | G72: 8.7 | H72: 7.89 | I72: 2024 | J72: 5 | K72: 7 | L72: 1 | M72: =IF(L72=1,COUNTIFS($C$2:$C$1090,C72,$L$2:$L$1090,1),"") -> 9 | N72: =IF(L72=1,1+COUNTIFS($C$2:$C$1090,C72,$L$2:$L$1090,1,$G$2:$G$1090,">"&G72),"") -> 3 | O72: =IF(L72=1,1+COUNTIFS($C$2:$C$1090,C72,$L$2:$L$1090,1,$H$2:$H$1090,">"&H72),"") -> 7 | P72: =IF(L72=1,N72-O72,"") -> -4 | Q72: =INDEX(Directions!$D$2:$D$100,MATCH(C72,Directions!$A$2:$A$100,0)) -> 0 | R72: =IF(L72=1,P72*Q72,"") -> 0 | S72: =IF(L72<>1,"Excluded",IF(Q72=0,"No direction",IF(R72>0,"Better",IF(R72<0,"Worse","No change")))) -> No direction | U72: =C72&"|"&E72 -> F1_07|FRA
A73: 1 | B73: Spending | C73: F1_07 | D73: Public spending on health, % of total national GDP | E73: NLD | F73: NLD | G73: 9.5 | H73: 6.72 | I73: 2023 | J73: 2 | K73: 10 | L73: 0 | M73: =IF(L73=1,COUNTIFS($C$2:$C$1090,C73,$L$2:$L$1090,1),"") | N73: =IF(L73=1,1+COUNTIFS($C$2:$C$1090,C73,$L$2:$L$1090,1,$G$2:$G$1090,">"&G73),"") | O73: =IF(L73=1,1+COUNTIFS($C$2:$C$1090,C73,$L$2:$L$1090,1,$H$2:$H$1090,">"&H73),"") | P73: =IF(L73=1,N73-O73,"") | Q73: =INDEX(Directions!$D$2:$D$100,MATCH(C73,Directions!$A$2:$A$100,0)) -> 0 | R73: =IF(L73=1,P73*Q73,"") | S73: =IF(L73<>1,"Excluded",IF(Q73=0,"No direction",IF(R73>0,"Better",IF(R73<0,"Worse","No change")))) -> Excluded | T73: Excluded: Mandatory insurance now classed as private in WHO GHED | U73: =C73&"|"&E73 -> F1_07|NLD
A74: 1 | B74: Spending | C74: F1_07 | D74: Public spending on health, % of total national GDP | E74: CHE | F74: CHE | G74: 7.7 | H74: 3.87 | I74: 2023 | J74: 8 | K74: 11 | L74: 0 | M74: =IF(L74=1,COUNTIFS($C$2:$C$1090,C74,$L$2:$L$1090,1),"") | N74: =IF(L74=1,1+COUNTIFS($C$2:$C$1090,C74,$L$2:$L$1090,1,$G$2:$G$1090,">"&G74),"") | O74: =IF(L74=1,1+COUNTIFS($C$2:$C$1090,C74,$L$2:$L$1090,1,$H$2:$H$1090,">"&H74),"") | P74: =IF(L74=1,N74-O74,"") | Q74: =INDEX(Directions!$D$2:$D$100,MATCH(C74,Directions!$A$2:$A$100,0)) -> 0 | R74: =IF(L74=1,P74*Q74,"") | S74: =IF(L74<>1,"Excluded",IF(Q74=0,"No direction",IF(R74>0,"Better",IF(R74<0,"Worse","No change")))) -> Excluded | T74: Excluded: Mandatory insurance now classed as private in WHO GHED | U74: =C74&"|"&E74 -> F1_07|CHE
A75: 1 | B75: Spending | C75: F1_07 | D75: Public spending on health, % of total national GDP | E75: DNK | F75: Denmark | G75: 9.2 | H75: 7.83 | I75: 2024 | J75: 3 | K75: 8 | L75: 1 | M75: =IF(L75=1,COUNTIFS($C$2:$C$1090,C75,$L$2:$L$1090,1),"") -> 9 | N75: =IF(L75=1,1+COUNTIFS($C$2:$C$1090,C75,$L$2:$L$1090,1,$G$2:$G$1090,">"&G75),"") -> 2 | O75: =IF(L75=1,1+COUNTIFS($C$2:$C$1090,C75,$L$2:$L$1090,1,$H$2:$H$1090,">"&H75),"") -> 8 | P75: =IF(L75=1,N75-O75,"") -> -6 | Q75: =INDEX(Directions!$D$2:$D$100,MATCH(C75,Directions!$A$2:$A$100,0)) -> 0 | R75: =IF(L75=1,P75*Q75,"") -> 0 | S75: =IF(L75<>1,"Excluded",IF(Q75=0,"No direction",IF(R75>0,"Better",IF(R75<0,"Worse","No change")))) -> No direction | U75: =C75&"|"&E75 -> F1_07|DNK
A76: 1 | B76: Spending | C76: F1_07 | D76: Public spending on health, % of total national GDP | E76: CAN | F76: Canada | G76: 7.4 | H76: 7.94 | I76: 2024 | J76: 10 | K76: 6 | L76: 1 | M76: =IF(L76=1,COUNTIFS($C$2:$C$1090,C76,$L$2:$L$1090,1),"") -> 9 | N76: =IF(L76=1,1+COUNTIFS($C$2:$C$1090,C76,$L$2:$L$1090,1,$G$2:$G$1090,">"&G76),"") -> 8 | O76: =IF(L76=1,1+COUNTIFS($C$2:$C$1090,C76,$L$2:$L$1090,1,$H$2:$H$1090,">"&H76),"") -> 6 | P76: =IF(L76=1,N76-O76,"") -> 2 | Q76: =INDEX(Directions!$D$2:$D$100,MATCH(C76,Directions!$A$2:$A$100,0)) -> 0 | R76: =IF(L76=1,P76*Q76,"") -> 0 | S76: =IF(L76<>1,"Excluded",IF(Q76=0,"No direction",IF(R76>0,"Better",IF(R76<0,"Worse","No change")))) -> No direction | U76: =C76&"|"&E76 -> F1_07|CAN
A77: 1 | B77: Spending | C77: F1_07 | D77: Public spending on health, % of total national GDP | E77: JPN | F77: Japan | G77: 8.6 | H77: 9.11 | I77: 2023 | J77: 6 | K77: 3 | L77: 1 | M77: =IF(L77=1,COUNTIFS($C$2:$C$1090,C77,$L$2:$L$1090,1),"") -> 9 | N77: =IF(L77=1,1+COUNTIFS($C$2:$C$1090,C77,$L$2:$L$1090,1,$G$2:$G$1090,">"&G77),"") -> 5 | O77: =IF(L77=1,1+COUNTIFS($C$2:$C$1090,C77,$L$2:$L$1090,1,$H$2:$H$1090,">"&H77),"") -> 3 | P77: =IF(L77=1,N77-O77,"") -> 2 | Q77: =INDEX(Directions!$D$2:$D$100,MATCH(C77,Directions!$A$2:$A$100,0)) -> 0 | R77: =IF(L77=1,P77*Q77,"") -> 0 | S77: =IF(L77<>1,"Excluded",IF(Q77=0,"No direction",IF(R77>0,"Better",IF(R77<0,"Worse","No change")))) -> No direction | U77: =C77&"|"&E77 -> F1_07|JPN
A78: 1 | B78: Spending | C78: F1_07 | D78: Public spending on health, % of total national GDP | E78: AUS | F78: Australia | G78: 6.3 | H78: 7.66 | I78: 2023 | J78: 11 | K78: 9 | L78: 1 | M78: =IF(L78=1,COUNTIFS($C$2:$C$1090,C78,$L$2:$L$1090,1),"") -> 9 | N78: =IF(L78=1,1+COUNTIFS($C$2:$C$1090,C78,$L$2:$L$1090,1,$G$2:$G$1090,">"&G78),"") -> 9 | O78: =IF(L78=1,1+COUNTIFS($C$2:$C$1090,C78,$L$2:$L$1090,1,$H$2:$H$1090,">"&H78),"") -> 9 | P78: =IF(L78=1,N78-O78,"") -> 0 | Q78: =INDEX(Directions!$D$2:$D$100,MATCH(C78,Directions!$A$2:$A$100,0)) -> 0 | R78: =IF(L78=1,P78*Q78,"") -> 0 | S78: =IF(L78<>1,"Excluded",IF(Q78=0,"No direction",IF(R78>0,"Better",IF(R78<0,"Worse","No change")))) -> No direction | U78: =C78&"|"&E78 -> F1_07|AUS
A79: 1 | B79: Spending | C79: F1_08 | D79: Mean spending on health per capita, US $ | E79: USA | F79: US | G79: 9403 | H79: 13473 | I79: 2023 | J79: 1 | K79: 1 | L79: 1 | M79: =IF(L79=1,COUNTIFS($C$2:$C$1090,C79,$L$2:$L$1090,1),"") -> 11 | N79: =IF(L79=1,1+COUNTIFS($C$2:$C$1090,C79,$L$2:$L$1090,1,$G$2:$G$1090,">"&G79),"") -> 1 | O79: =IF(L79=1,1+COUNTIFS($C$2:$C$1090,C79,$L$2:$L$1090,1,$H$2:$H$1090,">"&H79),"") -> 1 | P79: =IF(L79=1,N79-O79,"") -> 0 | Q79: =INDEX(Directions!$D$2:$D$100,MATCH(C79,Directions!$A$2:$A$100,0)) -> 0 | R79: =IF(L79=1,P79*Q79,"") -> 0 | S79: =IF(L79<>1,"Excluded",IF(Q79=0,"No direction",IF(R79>0,"Better",IF(R79<0,"Worse","No change")))) -> No direction | T79: 2018 basis uncertain (stated nominal US$, text says PPP); 2026 is PPP | U79: =C79&"|"&E79 -> F1_08|USA
A80: 1 | B80: Spending | C80: F1_08 | D80: Mean spending on health per capita, US $ | E80: GBR | F80: UK | G80: 3377 | H80: 6606 | I80: 2024 | J80: 11 | K80: 10 | L80: 1 | M80: =IF(L80=1,COUNTIFS($C$2:$C$1090,C80,$L$2:$L$1090,1),"") -> 11 | N80: =IF(L80=1,1+COUNTIFS($C$2:$C$1090,C80,$L$2:$L$1090,1,$G$2:$G$1090,">"&G80),"") -> 11 | O80: =IF(L80=1,1+COUNTIFS($C$2:$C$1090,C80,$L$2:$L$1090,1,$H$2:$H$1090,">"&H80),"") -> 10 | P80: =IF(L80=1,N80-O80,"") -> 1 | Q80: =INDEX(Directions!$D$2:$D$100,MATCH(C80,Directions!$A$2:$A$100,0)) -> 0 | R80: =IF(L80=1,P80*Q80,"") -> 0 | S80: =IF(L80<>1,"Excluded",IF(Q80=0,"No direction",IF(R80>0,"Better",IF(R80<0,"Worse","No change")))) -> No direction | T80: 2018 basis uncertain (stated nominal US$, text says PPP); 2026 is PPP | U80: =C80&"|"&E80 -> F1_08|GBR
A81: 1 | B81: Spending | C81: F1_08 | D81: Mean spending on health per capita, US $ | E81: DEU | F81: Germany | G81: 5182 | H81: 8826 | I81: 2024 | J81: 6 | K81: 3 | L81: 1 | M81: =IF(L81=1,COUNTIFS($C$2:$C$1090,C81,$L$2:$L$1090,1),"") -> 11 | N81: =IF(L81=1,1+COUNTIFS($C$2:$C$1090,C81,$L$2:$L$1090,1,$G$2:$G$1090,">"&G81),"") -> 6 | O81: =IF(L81=1,1+COUNTIFS($C$2:$C$1090,C81,$L$2:$L$1090,1,$H$2:$H$1090,">"&H81),"") -> 3 | P81: =IF(L81=1,N81-O81,"") -> 3 | Q81: =INDEX(Directions!$D$2:$D$100,MATCH(C81,Directions!$A$2:$A$100,0)) -> 0 | R81: =IF(L81=1,P81*Q81,"") -> 0 | S81: =IF(L81<>1,"Excluded",IF(Q81=0,"No direction",IF(R81>0,"Better",IF(R81<0,"Worse","No change")))) -> No direction | T81: 2018 basis uncertain (stated nominal US$, text says PPP); 2026 is PPP | U81: =C81&"|"&E81 -> F1_08|DEU
A82: 1 | B82: Spending | C82: F1_08 | D82: Mean spending on health per capita, US $ | E82: SWE | F82: Sweden | G82: 6808 | H82: 7770 | I82: 2024 | J82: 2 | K82: 5 | L82: 1 | M82: =IF(L82=1,COUNTIFS($C$2:$C$1090,C82,$L$2:$L$1090,1),"") -> 11 | N82: =IF(L82=1,1+COUNTIFS($C$2:$C$1090,C82,$L$2:$L$1090,1,$G$2:$G$1090,">"&G82),"") -> 2 | O82: =IF(L82=1,1+COUNTIFS($C$2:$C$1090,C82,$L$2:$L$1090,1,$H$2:$H$1090,">"&H82),"") -> 5 | P82: =IF(L82=1,N82-O82,"") -> -3 | Q82: =INDEX(Directions!$D$2:$D$100,MATCH(C82,Directions!$A$2:$A$100,0)) -> 0 | R82: =IF(L82=1,P82*Q82,"") -> 0 | S82: =IF(L82<>1,"Excluded",IF(Q82=0,"No direction",IF(R82>0,"Better",IF(R82<0,"Worse","No change")))) -> No direction | T82: 2018 basis uncertain (stated nominal US$, text says PPP); 2026 is PPP | U82: =C82&"|"&E82 -> F1_08|SWE
A83: 1 | B83: Spending | C83: F1_08 | D83: Mean spending on health per capita, US $ | E83: FRA | F83: France | G83: 3661 | H83: 6868 | I83: 2024 | J83: 10 | K83: 9 | L83: 1 | M83: =IF(L83=1,COUNTIFS($C$2:$C$1090,C83,$L$2:$L$1090,1),"") -> 11 | N83: =IF(L83=1,1+COUNTIFS($C$2:$C$1090,C83,$L$2:$L$1090,1,$G$2:$G$1090,">"&G83),"") -> 10 | O83: =IF(L83=1,1+COUNTIFS($C$2:$C$1090,C83,$L$2:$L$1090,1,$H$2:$H$1090,">"&H83),"") -> 9 | P83: =IF(L83=1,N83-O83,"") -> 1 | Q83: =INDEX(Directions!$D$2:$D$100,MATCH(C83,Directions!$A$2:$A$100,0)) -> 0 | R83: =IF(L83=1,P83*Q83,"") -> 0 | S83: =IF(L83<>1,"Excluded",IF(Q83=0,"No direction",IF(R83>0,"Better",IF(R83<0,"Worse","No change")))) -> No direction | T83: 2018 basis uncertain (stated nominal US$, text says PPP); 2026 is PPP | U83: =C83&"|"&E83 -> F1_08|FRA
A84: 1 | B84: Spending | C84: F1_08 | D84: Mean spending on health per capita, US $ | E84: NLD | F84: NLD | G84: 5202 | H84: 8195 | I84: 2024 | J84: 5 | K84: 4 | L84: 1 | M84: =IF(L84=1,COUNTIFS($C$2:$C$1090,C84,$L$2:$L$1090,1),"") -> 11 | N84: =IF(L84=1,1+COUNTIFS($C$2:$C$1090,C84,$L$2:$L$1090,1,$G$2:$G$1090,">"&G84),"") -> 5 | O84: =IF(L84=1,1+COUNTIFS($C$2:$C$1090,C84,$L$2:$L$1090,1,$H$2:$H$1090,">"&H84),"") -> 4 | P84: =IF(L84=1,N84-O84,"") -> 1 | Q84: =INDEX(Directions!$D$2:$D$100,MATCH(C84,Directions!$A$2:$A$100,0)) -> 0 | R84: =IF(L84=1,P84*Q84,"") -> 0 | S84: =IF(L84<>1,"Excluded",IF(Q84=0,"No direction",IF(R84>0,"Better",IF(R84<0,"Worse","No change")))) -> No direction | T84: 2018 basis uncertain (stated nominal US$, text says PPP); 2026 is PPP | U84: =C84&"|"&E84 -> F1_08|NLD
A85: 1 | B85: Spending | C85: F1_08 | D85: Mean spending on health per capita, US $ | E85: CHE | F85: CHE | G85: 6787 | H85: 10602 | I85: 2023 | J85: 3 | K85: 2 | L85: 1 | M85: =IF(L85=1,COUNTIFS($C$2:$C$1090,C85,$L$2:$L$1090,1),"") -> 11 | N85: =IF(L85=1,1+COUNTIFS($C$2:$C$1090,C85,$L$2:$L$1090,1,$G$2:$G$1090,">"&G85),"") -> 3 | O85: =IF(L85=1,1+COUNTIFS($C$2:$C$1090,C85,$L$2:$L$1090,1,$H$2:$H$1090,">"&H85),"") -> 2 | P85: =IF(L85=1,N85-O85,"") -> 1 | Q85: =INDEX(Directions!$D$2:$D$100,MATCH(C85,Directions!$A$2:$A$100,0)) -> 0 | R85: =IF(L85=1,P85*Q85,"") -> 0 | S85: =IF(L85<>1,"Excluded",IF(Q85=0,"No direction",IF(R85>0,"Better",IF(R85<0,"Worse","No change")))) -> No direction | T85: 2018 basis uncertain (stated nominal US$, text says PPP); 2026 is PPP | U85: =C85&"|"&E85 -> F1_08|CHE
A86: 1 | B86: Spending | C86: F1_08 | D86: Mean spending on health per capita, US $ | E86: DNK | F86: Denmark | G86: 6463 | H86: 7262 | I86: 2024 | J86: 4 | K86: 8 | L86: 1 | M86: =IF(L86=1,COUNTIFS($C$2:$C$1090,C86,$L$2:$L$1090,1),"") -> 11 | N86: =IF(L86=1,1+COUNTIFS($C$2:$C$1090,C86,$L$2:$L$1090,1,$G$2:$G$1090,">"&G86),"") -> 4 | O86: =IF(L86=1,1+COUNTIFS($C$2:$C$1090,C86,$L$2:$L$1090,1,$H$2:$H$1090,">"&H86),"") -> 8 | P86: =IF(L86=1,N86-O86,"") -> -4 | Q86: =INDEX(Directions!$D$2:$D$100,MATCH(C86,Directions!$A$2:$A$100,0)) -> 0 | R86: =IF(L86=1,P86*Q86,"") -> 0 | S86: =IF(L86<>1,"Excluded",IF(Q86=0,"No direction",IF(R86>0,"Better",IF(R86<0,"Worse","No change")))) -> No direction | T86: 2018 basis uncertain (stated nominal US$, text says PPP); 2026 is PPP | U86: =C86&"|"&E86 -> F1_08|DNK
A87: 1 | B87: Spending | C87: F1_08 | D87: Mean spending on health per capita, US $ | E87: CAN | F87: Canada | G87: 4641 | H87: 7646 | I87: 2024 | J87: 7 | K87: 7 | L87: 1 | M87: =IF(L87=1,COUNTIFS($C$2:$C$1090,C87,$L$2:$L$1090,1),"") -> 11 | N87: =IF(L87=1,1+COUNTIFS($C$2:$C$1090,C87,$L$2:$L$1090,1,$G$2:$G$1090,">"&G87),"") -> 7 | O87: =IF(L87=1,1+COUNTIFS($C$2:$C$1090,C87,$L$2:$L$1090,1,$H$2:$H$1090,">"&H87),"") -> 7 | P87: =IF(L87=1,N87-O87,"") -> 0 | Q87: =INDEX(Directions!$D$2:$D$100,MATCH(C87,Directions!$A$2:$A$100,0)) -> 0 | R87: =IF(L87=1,P87*Q87,"") -> 0 | S87: =IF(L87<>1,"Excluded",IF(Q87=0,"No direction",IF(R87>0,"Better",IF(R87<0,"Worse","No change")))) -> No direction | T87: 2018 basis uncertain (stated nominal US$, text says PPP); 2026 is PPP | U87: =C87&"|"&E87 -> F1_08|CAN
A88: 1 | B88: Spending | C88: F1_08 | D88: Mean spending on health per capita, US $ | E88: JPN | F88: Japan | G88: 3727 | H88: 5365 | I88: 2023 | J88: 9 | K88: 11 | L88: 1 | M88: =IF(L88=1,COUNTIFS($C$2:$C$1090,C88,$L$2:$L$1090,1),"") -> 11 | N88: =IF(L88=1,1+COUNTIFS($C$2:$C$1090,C88,$L$2:$L$1090,1,$G$2:$G$1090,">"&G88),"") -> 9 | O88: =IF(L88=1,1+COUNTIFS($C$2:$C$1090,C88,$L$2:$L$1090,1,$H$2:$H$1090,">"&H88),"") -> 11 | P88: =IF(L88=1,N88-O88,"") -> -2 | Q88: =INDEX(Directions!$D$2:$D$100,MATCH(C88,Directions!$A$2:$A$100,0)) -> 0 | R88: =IF(L88=1,P88*Q88,"") -> 0 | S88: =IF(L88<>1,"Excluded",IF(Q88=0,"No direction",IF(R88>0,"Better",IF(R88<0,"Worse","No change")))) -> No direction | T88: 2018 basis uncertain (stated nominal US$, text says PPP); 2026 is PPP | U88: =C88&"|"&E88 -> F1_08|JPN
A89: 1 | B89: Spending | C89: F1_08 | D89: Mean spending on health per capita, US $ | E89: AUS | F89: Australia | G89: 4357 | H89: 7691 | I89: 2023 | J89: 8 | K89: 6 | L89: 1 | M89: =IF(L89=1,COUNTIFS($C$2:$C$1090,C89,$L$2:$L$1090,1),"") -> 11 | N89: =IF(L89=1,1+COUNTIFS($C$2:$C$1090,C89,$L$2:$L$1090,1,$G$2:$G$1090,">"&G89),"") -> 8 | O89: =IF(L89=1,1+COUNTIFS($C$2:$C$1090,C89,$L$2:$L$1090,1,$H$2:$H$1090,">"&H89),"") -> 6 | P89: =IF(L89=1,N89-O89,"") -> 2 | Q89: =INDEX(Directions!$D$2:$D$100,MATCH(C89,Directions!$A$2:$A$100,0)) -> 0 | R89: =IF(L89=1,P89*Q89,"") -> 0 | S89: =IF(L89<>1,"Excluded",IF(Q89=0,"No direction",IF(R89>0,"Better",IF(R89<0,"Worse","No change")))) -> No direction | T89: 2018 basis uncertain (stated nominal US$, text says PPP); 2026 is PPP | U89: =C89&"|"&E89 -> F1_08|AUS
A90: 1 | B90: Spending | C90: F1_09 | D90: Inpatient care | E90: USA | F90: US | G90: 19 | H90: 16.5 | I90: 2018 | J90: 10 | K90: 9 | L90: 1 | M90: =IF(L90=1,COUNTIFS($C$2:$C$1090,C90,$L$2:$L$1090,1),"") -> 10 | N90: =IF(L90=1,1+COUNTIFS($C$2:$C$1090,C90,$L$2:$L$1090,1,$G$2:$G$1090,">"&G90),"") -> 9 | O90: =IF(L90=1,1+COUNTIFS($C$2:$C$1090,C90,$L$2:$L$1090,1,$H$2:$H$1090,">"&H90),"") -> 9 | P90: =IF(L90=1,N90-O90,"") -> 0 | Q90: =INDEX(Directions!$D$2:$D$100,MATCH(C90,Directions!$A$2:$A$100,0)) -> 0 | R90: =IF(L90=1,P90*Q90,"") -> 0 | S90: =IF(L90<>1,"Excluded",IF(Q90=0,"No direction",IF(R90>0,"Better",IF(R90<0,"Worse","No change")))) -> No direction | T90: US 2018 health-accounts data (latest split); 2018 paper adjusted US inpatient +2 pts | U90: =C90&"|"&E90 -> F1_09|USA
A91: 1 | B91: Spending | C91: F1_09 | D91: Inpatient care | E91: GBR | F91: UK | G91: 24 | H91: 25.1 | I91: 2024 | J91: 8 | K91: 5 | L91: 1 | M91: =IF(L91=1,COUNTIFS($C$2:$C$1090,C91,$L$2:$L$1090,1),"") -> 10 | N91: =IF(L91=1,1+COUNTIFS($C$2:$C$1090,C91,$L$2:$L$1090,1,$G$2:$G$1090,">"&G91),"") -> 7 | O91: =IF(L91=1,1+COUNTIFS($C$2:$C$1090,C91,$L$2:$L$1090,1,$H$2:$H$1090,">"&H91),"") -> 5 | P91: =IF(L91=1,N91-O91,"") -> 2 | Q91: =INDEX(Directions!$D$2:$D$100,MATCH(C91,Directions!$A$2:$A$100,0)) -> 0 | R91: =IF(L91=1,P91*Q91,"") -> 0 | S91: =IF(L91<>1,"Excluded",IF(Q91=0,"No direction",IF(R91>0,"Better",IF(R91<0,"Worse","No change")))) -> No direction | U91: =C91&"|"&E91 -> F1_09|GBR
A92: 1 | B92: Spending | C92: F1_09 | D92: Inpatient care | E92: DEU | F92: Germany | G92: 27 | H92: 25.2 | I92: 2024 | J92: 6 | K92: 3 | L92: 1 | M92: =IF(L92=1,COUNTIFS($C$2:$C$1090,C92,$L$2:$L$1090,1),"") -> 10 | N92: =IF(L92=1,1+COUNTIFS($C$2:$C$1090,C92,$L$2:$L$1090,1,$G$2:$G$1090,">"&G92),"") -> 5 | O92: =IF(L92=1,1+COUNTIFS($C$2:$C$1090,C92,$L$2:$L$1090,1,$H$2:$H$1090,">"&H92),"") -> 3 | P92: =IF(L92=1,N92-O92,"") -> 2 | Q92: =INDEX(Directions!$D$2:$D$100,MATCH(C92,Directions!$A$2:$A$100,0)) -> 0 | R92: =IF(L92=1,P92*Q92,"") -> 0 | S92: =IF(L92<>1,"Excluded",IF(Q92=0,"No direction",IF(R92>0,"Better",IF(R92<0,"Worse","No change")))) -> No direction | U92: =C92&"|"&E92 -> F1_09|DEU
A93: 1 | B93: Spending | C93: F1_09 | D93: Inpatient care | E93: SWE | F93: Sweden | G93: 21 | H93: 19.8 | I93: 2024 | J93: 9 | K93: 8 | L93: 1 | M93: =IF(L93=1,COUNTIFS($C$2:$C$1090,C93,$L$2:$L$1090,1),"") -> 10 | N93: =IF(L93=1,1+COUNTIFS($C$2:$C$1090,C93,$L$2:$L$1090,1,$G$2:$G$1090,">"&G93),"") -> 8 | O93: =IF(L93=1,1+COUNTIFS($C$2:$C$1090,C93,$L$2:$L$1090,1,$H$2:$H$1090,">"&H93),"") -> 8 | P93: =IF(L93=1,N93-O93,"") -> 0 | Q93: =INDEX(Directions!$D$2:$D$100,MATCH(C93,Directions!$A$2:$A$100,0)) -> 0 | R93: =IF(L93=1,P93*Q93,"") -> 0 | S93: =IF(L93<>1,"Excluded",IF(Q93=0,"No direction",IF(R93>0,"Better",IF(R93<0,"Worse","No change")))) -> No direction | U93: =C93&"|"&E93 -> F1_09|SWE
A94: 1 | B94: Spending | C94: F1_09 | D94: Inpatient care | E94: FRA | F94: France | G94: 30 | H94: 25.2 | I94: 2024 | J94: 3 | K94: 4 | L94: 1 | M94: =IF(L94=1,COUNTIFS($C$2:$C$1090,C94,$L$2:$L$1090,1),"") -> 10 | N94: =IF(L94=1,1+COUNTIFS($C$2:$C$1090,C94,$L$2:$L$1090,1,$G$2:$G$1090,">"&G94),"") -> 2 | O94: =IF(L94=1,1+COUNTIFS($C$2:$C$1090,C94,$L$2:$L$1090,1,$H$2:$H$1090,">"&H94),"") -> 3 | P94: =IF(L94=1,N94-O94,"") -> -1 | Q94: =INDEX(Directions!$D$2:$D$100,MATCH(C94,Directions!$A$2:$A$100,0)) -> 0 | R94: =IF(L94=1,P94*Q94,"") -> 0 | S94: =IF(L94<>1,"Excluded",IF(Q94=0,"No direction",IF(R94>0,"Better",IF(R94<0,"Worse","No change")))) -> No direction | U94: =C94&"|"&E94 -> F1_09|FRA
A95: 1 | B95: Spending | C95: F1_09 | D95: Inpatient care | E95: NLD | F95: NLD | G95: 32 | H95: 14.5 | I95: 2025 | J95: 1 | K95: 11 | L95: 0 | M95: =IF(L95=1,COUNTIFS($C$2:$C$1090,C95,$L$2:$L$1090,1),"") | N95: =IF(L95=1,1+COUNTIFS($C$2:$C$1090,C95,$L$2:$L$1090,1,$G$2:$G$1090,">"&G95),"") | O95: =IF(L95=1,1+COUNTIFS($C$2:$C$1090,C95,$L$2:$L$1090,1,$H$2:$H$1090,">"&H95),"") | P95: =IF(L95=1,N95-O95,"") | Q95: =INDEX(Directions!$D$2:$D$100,MATCH(C95,Directions!$A$2:$A$100,0)) -> 0 | R95: =IF(L95=1,P95*Q95,"") | S95: =IF(L95<>1,"Excluded",IF(Q95=0,"No direction",IF(R95>0,"Better",IF(R95<0,"Worse","No change")))) -> Excluded | T95: Excluded: Health-accounts series break 2021 (reclassification between functions) | U95: =C95&"|"&E95 -> F1_09|NLD
A96: 1 | B96: Spending | C96: F1_09 | D96: Inpatient care | E96: CHE | F96: CHE | G96: 28 | H96: 23.4 | I96: 2024 | J96: 4 | K96: 6 | L96: 1 | M96: =IF(L96=1,COUNTIFS($C$2:$C$1090,C96,$L$2:$L$1090,1),"") -> 10 | N96: =IF(L96=1,1+COUNTIFS($C$2:$C$1090,C96,$L$2:$L$1090,1,$G$2:$G$1090,">"&G96),"") -> 3 | O96: =IF(L96=1,1+COUNTIFS($C$2:$C$1090,C96,$L$2:$L$1090,1,$H$2:$H$1090,">"&H96),"") -> 6 | P96: =IF(L96=1,N96-O96,"") -> -3 | Q96: =INDEX(Directions!$D$2:$D$100,MATCH(C96,Directions!$A$2:$A$100,0)) -> 0 | R96: =IF(L96=1,P96*Q96,"") -> 0 | S96: =IF(L96<>1,"Excluded",IF(Q96=0,"No direction",IF(R96>0,"Better",IF(R96<0,"Worse","No change")))) -> No direction | U96: =C96&"|"&E96 -> F1_09|CHE
A97: 1 | B97: Spending | C97: F1_09 | D97: Inpatient care | E97: DNK | F97: Denmark | G97: 28 | H97: 21.7 | I97: 2025 | J97: 5 | K97: 7 | L97: 1 | M97: =IF(L97=1,COUNTIFS($C$2:$C$1090,C97,$L$2:$L$1090,1),"") -> 10 | N97: =IF(L97=1,1+COUNTIFS($C$2:$C$1090,C97,$L$2:$L$1090,1,$G$2:$G$1090,">"&G97),"") -> 3 | O97: =IF(L97=1,1+COUNTIFS($C$2:$C$1090,C97,$L$2:$L$1090,1,$H$2:$H$1090,">"&H97),"") -> 7 | P97: =IF(L97=1,N97-O97,"") -> -4 | Q97: =INDEX(Directions!$D$2:$D$100,MATCH(C97,Directions!$A$2:$A$100,0)) -> 0 | R97: =IF(L97=1,P97*Q97,"") -> 0 | S97: =IF(L97<>1,"Excluded",IF(Q97=0,"No direction",IF(R97>0,"Better",IF(R97<0,"Worse","No change")))) -> No direction | U97: =C97&"|"&E97 -> F1_09|DNK
A98: 1 | B98: Spending | C98: F1_09 | D98: Inpatient care | E98: CAN | F98: Canada | G98: 17 | H98: 15 | I98: 2025 | J98: 11 | K98: 10 | L98: 1 | M98: =IF(L98=1,COUNTIFS($C$2:$C$1090,C98,$L$2:$L$1090,1),"") -> 10 | N98: =IF(L98=1,1+COUNTIFS($C$2:$C$1090,C98,$L$2:$L$1090,1,$G$2:$G$1090,">"&G98),"") -> 10 | O98: =IF(L98=1,1+COUNTIFS($C$2:$C$1090,C98,$L$2:$L$1090,1,$H$2:$H$1090,">"&H98),"") -> 10 | P98: =IF(L98=1,N98-O98,"") -> 0 | Q98: =INDEX(Directions!$D$2:$D$100,MATCH(C98,Directions!$A$2:$A$100,0)) -> 0 | R98: =IF(L98=1,P98*Q98,"") -> 0 | S98: =IF(L98<>1,"Excluded",IF(Q98=0,"No direction",IF(R98>0,"Better",IF(R98<0,"Worse","No change")))) -> No direction | U98: =C98&"|"&E98 -> F1_09|CAN
A99: 1 | B99: Spending | C99: F1_09 | D99: Inpatient care | E99: JPN | F99: Japan | G99: 27 | H99: 26.2 | I99: 2023 | J99: 7 | K99: 1 | L99: 1 | M99: =IF(L99=1,COUNTIFS($C$2:$C$1090,C99,$L$2:$L$1090,1),"") -> 10 | N99: =IF(L99=1,1+COUNTIFS($C$2:$C$1090,C99,$L$2:$L$1090,1,$G$2:$G$1090,">"&G99),"") -> 5 | O99: =IF(L99=1,1+COUNTIFS($C$2:$C$1090,C99,$L$2:$L$1090,1,$H$2:$H$1090,">"&H99),"") -> 1 | P99: =IF(L99=1,N99-O99,"") -> 4 | Q99: =INDEX(Directions!$D$2:$D$100,MATCH(C99,Directions!$A$2:$A$100,0)) -> 0 | R99: =IF(L99=1,P99*Q99,"") -> 0 | S99: =IF(L99<>1,"Excluded",IF(Q99=0,"No direction",IF(R99>0,"Better",IF(R99<0,"Worse","No change")))) -> No direction | U99: =C99&"|"&E99 -> F1_09|JPN
A100: 1 | B100: Spending | C100: F1_09 | D100: Inpatient care | E100: AUS | F100: Australia | G100: 31 | H100: 26.1 | I100: 2023 | J100: 2 | K100: 2 | L100: 1 | M100: =IF(L100=1,COUNTIFS($C$2:$C$1090,C100,$L$2:$L$1090,1),"") -> 10 | N100: =IF(L100=1,1+COUNTIFS($C$2:$C$1090,C100,$L$2:$L$1090,1,$G$2:$G$1090,">"&G100),"") -> 1 | O100: =IF(L100=1,1+COUNTIFS($C$2:$C$1090,C100,$L$2:$L$1090,1,$H$2:$H$1090,">"&H100),"") -> 2 | P100: =IF(L100=1,N100-O100,"") -> -1 | Q100: =INDEX(Directions!$D$2:$D$100,MATCH(C100,Directions!$A$2:$A$100,0)) -> 0 | R100: =IF(L100=1,P100*Q100,"") -> 0 | S100: =IF(L100<>1,"Excluded",IF(Q100=0,"No direction",IF(R100>0,"Better",IF(R100<0,"Worse","No change")))) -> No direction | U100: =C100&"|"&E100 -> F1_09|AUS
A101: 1 | B101: Spending | C101: F1_10 | D101: Outpatient care | E101: USA | F101: US | G101: 44 | H101: 44.8 | I101: 2018 | J101: 1 | K101: 1 | L101: 1 | M101: =IF(L101=1,COUNTIFS($C$2:$C$1090,C101,$L$2:$L$1090,1),"") -> 10 | N101: =IF(L101=1,1+COUNTIFS($C$2:$C$1090,C101,$L$2:$L$1090,1,$G$2:$G$1090,">"&G101),"") -> 1 | O101: =IF(L101=1,1+COUNTIFS($C$2:$C$1090,C101,$L$2:$L$1090,1,$H$2:$H$1090,">"&H101),"") -> 1 | P101: =IF(L101=1,N101-O101,"") -> 0 | Q101: =INDEX(Directions!$D$2:$D$100,MATCH(C101,Directions!$A$2:$A$100,0)) -> 0 | R101: =IF(L101=1,P101*Q101,"") -> 0 | S101: =IF(L101<>1,"Excluded",IF(Q101=0,"No direction",IF(R101>0,"Better",IF(R101<0,"Worse","No change")))) -> No direction | T101: US 2018 health-accounts data (latest split); 2018 paper adjusted US inpatient +2 pts | U101: =C101&"|"&E101 -> F1_10|USA
A102: 1 | B102: Spending | C102: F1_10 | D102: Outpatient care | E102: GBR | F102: UK | G102: 30 | H102: 32 | I102: 2024 | J102: 7 | K102: 6 | L102: 1 | M102: =IF(L102=1,COUNTIFS($C$2:$C$1090,C102,$L$2:$L$1090,1),"") -> 10 | N102: =IF(L102=1,1+COUNTIFS($C$2:$C$1090,C102,$L$2:$L$1090,1,$G$2:$G$1090,">"&G102),"") -> 7 | O102: =IF(L102=1,1+COUNTIFS($C$2:$C$1090,C102,$L$2:$L$1090,1,$H$2:$H$1090,">"&H102),"") -> 5 | P102: =IF(L102=1,N102-O102,"") -> 2 | Q102: =INDEX(Directions!$D$2:$D$100,MATCH(C102,Directions!$A$2:$A$100,0)) -> 0 | R102: =IF(L102=1,P102*Q102,"") -> 0 | S102: =IF(L102<>1,"Excluded",IF(Q102=0,"No direction",IF(R102>0,"Better",IF(R102<0,"Worse","No change")))) -> No direction | U102: =C102&"|"&E102 -> F1_10|GBR
A103: 1 | B103: Spending | C103: F1_10 | D103: Outpatient care | E103: DEU | F103: Germany | G103: 23 | H103: 21.3 | I103: 2024 | J103: 9 | K103: 11 | L103: 1 | M103: =IF(L103=1,COUNTIFS($C$2:$C$1090,C103,$L$2:$L$1090,1),"") -> 10 | N103: =IF(L103=1,1+COUNTIFS($C$2:$C$1090,C103,$L$2:$L$1090,1,$G$2:$G$1090,">"&G103),"") -> 9 | O103: =IF(L103=1,1+COUNTIFS($C$2:$C$1090,C103,$L$2:$L$1090,1,$H$2:$H$1090,">"&H103),"") -> 10 | P103: =IF(L103=1,N103-O103,"") -> -1 | Q103: =INDEX(Directions!$D$2:$D$100,MATCH(C103,Directions!$A$2:$A$100,0)) -> 0 | R103: =IF(L103=1,P103*Q103,"") -> 0 | S103: =IF(L103<>1,"Excluded",IF(Q103=0,"No direction",IF(R103>0,"Better",IF(R103<0,"Worse","No change")))) -> No direction | U103: =C103&"|"&E103 -> F1_10|DEU
A104: 1 | B104: Spending | C104: F1_10 | D104: Outpatient care | E104: SWE | F104: Sweden | G104: 31 | H104: 30.3 | I104: 2024 | J104: 6 | K104: 7 | L104: 1 | M104: =IF(L104=1,COUNTIFS($C$2:$C$1090,C104,$L$2:$L$1090,1),"") -> 10 | N104: =IF(L104=1,1+COUNTIFS($C$2:$C$1090,C104,$L$2:$L$1090,1,$G$2:$G$1090,">"&G104),"") -> 6 | O104: =IF(L104=1,1+COUNTIFS($C$2:$C$1090,C104,$L$2:$L$1090,1,$H$2:$H$1090,">"&H104),"") -> 6 | P104: =IF(L104=1,N104-O104,"") -> 0 | Q104: =INDEX(Directions!$D$2:$D$100,MATCH(C104,Directions!$A$2:$A$100,0)) -> 0 | R104: =IF(L104=1,P104*Q104,"") -> 0 | S104: =IF(L104<>1,"Excluded",IF(Q104=0,"No direction",IF(R104>0,"Better",IF(R104<0,"Worse","No change")))) -> No direction | U104: =C104&"|"&E104 -> F1_10|SWE
A105: 1 | B105: Spending | C105: F1_10 | D105: Outpatient care | E105: FRA | F105: France | G105: 23 | H105: 24.7 | I105: 2024 | J105: 10 | K105: 9 | L105: 1 | M105: =IF(L105=1,COUNTIFS($C$2:$C$1090,C105,$L$2:$L$1090,1),"") -> 10 | N105: =IF(L105=1,1+COUNTIFS($C$2:$C$1090,C105,$L$2:$L$1090,1,$G$2:$G$1090,">"&G105),"") -> 9 | O105: =IF(L105=1,1+COUNTIFS($C$2:$C$1090,C105,$L$2:$L$1090,1,$H$2:$H$1090,">"&H105),"") -> 8 | P105: =IF(L105=1,N105-O105,"") -> 1 | Q105: =INDEX(Directions!$D$2:$D$100,MATCH(C105,Directions!$A$2:$A$100,0)) -> 0 | R105: =IF(L105=1,P105*Q105,"") -> 0 | S105: =IF(L105<>1,"Excluded",IF(Q105=0,"No direction",IF(R105>0,"Better",IF(R105<0,"Worse","No change")))) -> No direction | U105: =C105&"|"&E105 -> F1_10|FRA
A106: 1 | B106: Spending | C106: F1_10 | D106: Outpatient care | E106: NLD | F106: NLD | G106: 22 | H106: 35 | I106: 2025 | J106: 11 | K106: 3 | L106: 0 | M106: =IF(L106=1,COUNTIFS($C$2:$C$1090,C106,$L$2:$L$1090,1),"") | N106: =IF(L106=1,1+COUNTIFS($C$2:$C$1090,C106,$L$2:$L$1090,1,$G$2:$G$1090,">"&G106),"") | O106: =IF(L106=1,1+COUNTIFS($C$2:$C$1090,C106,$L$2:$L$1090,1,$H$2:$H$1090,">"&H106),"") | P106: =IF(L106=1,N106-O106,"") | Q106: =INDEX(Directions!$D$2:$D$100,MATCH(C106,Directions!$A$2:$A$100,0)) -> 0 | R106: =IF(L106=1,P106*Q106,"") | S106: =IF(L106<>1,"Excluded",IF(Q106=0,"No direction",IF(R106>0,"Better",IF(R106<0,"Worse","No change")))) -> Excluded | T106: Excluded: Health-accounts series break 2021 (reclassification between functions) | U106: =C106&"|"&E106 -> F1_10|NLD
A107: 1 | B107: Spending | C107: F1_10 | D107: Outpatient care | E107: CHE | F107: CHE | G107: 33 | H107: 24.6 | I107: 2024 | J107: 5 | K107: 10 | L107: 1 | M107: =IF(L107=1,COUNTIFS($C$2:$C$1090,C107,$L$2:$L$1090,1),"") -> 10 | N107: =IF(L107=1,1+COUNTIFS($C$2:$C$1090,C107,$L$2:$L$1090,1,$G$2:$G$1090,">"&G107),"") -> 5 | O107: =IF(L107=1,1+COUNTIFS($C$2:$C$1090,C107,$L$2:$L$1090,1,$H$2:$H$1090,">"&H107),"") -> 9 | P107: =IF(L107=1,N107-O107,"") -> -4 | Q107: =INDEX(Directions!$D$2:$D$100,MATCH(C107,Directions!$A$2:$A$100,0)) -> 0 | R107: =IF(L107=1,P107*Q107,"") -> 0 | S107: =IF(L107<>1,"Excluded",IF(Q107=0,"No direction",IF(R107>0,"Better",IF(R107<0,"Worse","No change")))) -> No direction | U107: =C107&"|"&E107 -> F1_10|CHE
A108: 1 | B108: Spending | C108: F1_10 | D108: Outpatient care | E108: DNK | F108: Denmark | G108: 34 | H108: 38.6 | I108: 2025 | J108: 4 | K108: 2 | L108: 1 | M108: =IF(L108=1,COUNTIFS($C$2:$C$1090,C108,$L$2:$L$1090,1),"") -> 10 | N108: =IF(L108=1,1+COUNTIFS($C$2:$C$1090,C108,$L$2:$L$1090,1,$G$2:$G$1090,">"&G108),"") -> 4 | O108: =IF(L108=1,1+COUNTIFS($C$2:$C$1090,C108,$L$2:$L$1090,1,$H$2:$H$1090,">"&H108),"") -> 2 | P108: =IF(L108=1,N108-O108,"") -> 2 | Q108: =INDEX(Directions!$D$2:$D$100,MATCH(C108,Directions!$A$2:$A$100,0)) -> 0 | R108: =IF(L108=1,P108*Q108,"") -> 0 | S108: =IF(L108<>1,"Excluded",IF(Q108=0,"No direction",IF(R108>0,"Better",IF(R108<0,"Worse","No change")))) -> No direction | U108: =C108&"|"&E108 -> F1_10|DNK
A109: 1 | B109: Spending | C109: F1_10 | D109: Outpatient care | E109: CAN | F109: Canada | G109: 36 | H109: 32.3 | I109: 2025 | J109: 3 | K109: 5 | L109: 1 | M109: =IF(L109=1,COUNTIFS($C$2:$C$1090,C109,$L$2:$L$1090,1),"") -> 10 | N109: =IF(L109=1,1+COUNTIFS($C$2:$C$1090,C109,$L$2:$L$1090,1,$G$2:$G$1090,">"&G109),"") -> 3 | O109: =IF(L109=1,1+COUNTIFS($C$2:$C$1090,C109,$L$2:$L$1090,1,$H$2:$H$1090,">"&H109),"") -> 4 | P109: =IF(L109=1,N109-O109,"") -> -1 | Q109: =INDEX(Directions!$D$2:$D$100,MATCH(C109,Directions!$A$2:$A$100,0)) -> 0 | R109: =IF(L109=1,P109*Q109,"") -> 0 | S109: =IF(L109<>1,"Excluded",IF(Q109=0,"No direction",IF(R109>0,"Better",IF(R109<0,"Worse","No change")))) -> No direction | U109: =C109&"|"&E109 -> F1_10|CAN
A110: 1 | B110: Spending | C110: F1_10 | D110: Outpatient care | E110: JPN | F110: Japan | G110: 27 | H110: 27.7 | I110: 2023 | J110: 8 | K110: 8 | L110: 1 | M110: =IF(L110=1,COUNTIFS($C$2:$C$1090,C110,$L$2:$L$1090,1),"") -> 10 | N110: =IF(L110=1,1+COUNTIFS($C$2:$C$1090,C110,$L$2:$L$1090,1,$G$2:$G$1090,">"&G110),"") -> 8 | O110: =IF(L110=1,1+COUNTIFS($C$2:$C$1090,C110,$L$2:$L$1090,1,$H$2:$H$1090,">"&H110),"") -> 7 | P110: =IF(L110=1,N110-O110,"") -> 1 | Q110: =INDEX(Directions!$D$2:$D$100,MATCH(C110,Directions!$A$2:$A$100,0)) -> 0 | R110: =IF(L110=1,P110*Q110,"") -> 0 | S110: =IF(L110<>1,"Excluded",IF(Q110=0,"No direction",IF(R110>0,"Better",IF(R110<0,"Worse","No change")))) -> No direction | U110: =C110&"|"&E110 -> F1_10|JPN
A111: 1 | B111: Spending | C111: F1_10 | D111: Outpatient care | E111: AUS | F111: Australia | G111: 39 | H111: 35 | I111: 2023 | J111: 2 | K111: 4 | L111: 1 | M111: =IF(L111=1,COUNTIFS($C$2:$C$1090,C111,$L$2:$L$1090,1),"") -> 10 | N111: =IF(L111=1,1+COUNTIFS($C$2:$C$1090,C111,$L$2:$L$1090,1,$G$2:$G$1090,">"&G111),"") -> 2 | O111: =IF(L111=1,1+COUNTIFS($C$2:$C$1090,C111,$L$2:$L$1090,1,$H$2:$H$1090,">"&H111),"") -> 3 | P111: =IF(L111=1,N111-O111,"") -> -1 | Q111: =INDEX(Directions!$D$2:$D$100,MATCH(C111,Directions!$A$2:$A$100,0)) -> 0 | R111: =IF(L111=1,P111*Q111,"") -> 0 | S111: =IF(L111<>1,"Excluded",IF(Q111=0,"No direction",IF(R111>0,"Better",IF(R111<0,"Worse","No change")))) -> No direction | U111: =C111&"|"&E111 -> F1_10|AUS
A112: 1 | B112: Spending | C112: F1_11 | D112: Long-term care | E112: USA | F112: US | G112: 5 | H112: 7.9 | I112: 2018 | J112: 10 | K112: 11 | L112: 1 | M112: =IF(L112=1,COUNTIFS($C$2:$C$1090,C112,$L$2:$L$1090,1),"") -> 10 | N112: =IF(L112=1,1+COUNTIFS($C$2:$C$1090,C112,$L$2:$L$1090,1,$G$2:$G$1090,">"&G112),"") -> 9 | O112: =IF(L112=1,1+COUNTIFS($C$2:$C$1090,C112,$L$2:$L$1090,1,$H$2:$H$1090,">"&H112),"") -> 10 | P112: =IF(L112=1,N112-O112,"") -> -1 | Q112: =INDEX(Directions!$D$2:$D$100,MATCH(C112,Directions!$A$2:$A$100,0)) -> 0 | R112: =IF(L112=1,P112*Q112,"") -> 0 | S112: =IF(L112<>1,"Excluded",IF(Q112=0,"No direction",IF(R112>0,"Better",IF(R112<0,"Worse","No change")))) -> No direction | T112: US 2018 health-accounts data (latest split); 2018 paper adjusted US inpatient +2 pts | U112: =C112&"|"&E112 -> F1_11|USA
A113: 1 | B113: Spending | C113: F1_11 | D113: Long-term care | E113: GBR | F113: UK | G113: 18 | H113: 19.8 | I113: 2024 | J113: 6 | K113: 7 | L113: 1 | M113: =IF(L113=1,COUNTIFS($C$2:$C$1090,C113,$L$2:$L$1090,1),"") -> 10 | N113: =IF(L113=1,1+COUNTIFS($C$2:$C$1090,C113,$L$2:$L$1090,1,$G$2:$G$1090,">"&G113),"") -> 5 | O113: =IF(L113=1,1+COUNTIFS($C$2:$C$1090,C113,$L$2:$L$1090,1,$H$2:$H$1090,">"&H113),"") -> 6 | P113: =IF(L113=1,N113-O113,"") -> -1 | Q113: =INDEX(Directions!$D$2:$D$100,MATCH(C113,Directions!$A$2:$A$100,0)) -> 0 | R113: =IF(L113=1,P113*Q113,"") -> 0 | S113: =IF(L113<>1,"Excluded",IF(Q113=0,"No direction",IF(R113>0,"Better",IF(R113<0,"Worse","No change")))) -> No direction | U113: =C113&"|"&E113 -> F1_11|GBR
A114: 1 | B114: Spending | C114: F1_11 | D114: Long-term care | E114: DEU | F114: Germany | G114: 16 | H114: 21.9 | I114: 2024 | J114: 7 | K114: 4 | L114: 1 | M114: =IF(L114=1,COUNTIFS($C$2:$C$1090,C114,$L$2:$L$1090,1),"") -> 10 | N114: =IF(L114=1,1+COUNTIFS($C$2:$C$1090,C114,$L$2:$L$1090,1,$G$2:$G$1090,">"&G114),"") -> 6 | O114: =IF(L114=1,1+COUNTIFS($C$2:$C$1090,C114,$L$2:$L$1090,1,$H$2:$H$1090,">"&H114),"") -> 3 | P114: =IF(L114=1,N114-O114,"") -> 3 | Q114: =INDEX(Directions!$D$2:$D$100,MATCH(C114,Directions!$A$2:$A$100,0)) -> 0 | R114: =IF(L114=1,P114*Q114,"") -> 0 | S114: =IF(L114<>1,"Excluded",IF(Q114=0,"No direction",IF(R114>0,"Better",IF(R114<0,"Worse","No change")))) -> No direction | U114: =C114&"|"&E114 -> F1_11|DEU
A115: 1 | B115: Spending | C115: F1_11 | D115: Long-term care | E115: SWE | F115: Sweden | G115: 26 | H115: 27.6 | I115: 2024 | J115: 1 | K115: 2 | L115: 1 | M115: =IF(L115=1,COUNTIFS($C$2:$C$1090,C115,$L$2:$L$1090,1),"") -> 10 | N115: =IF(L115=1,1+COUNTIFS($C$2:$C$1090,C115,$L$2:$L$1090,1,$G$2:$G$1090,">"&G115),"") -> 1 | O115: =IF(L115=1,1+COUNTIFS($C$2:$C$1090,C115,$L$2:$L$1090,1,$H$2:$H$1090,">"&H115),"") -> 1 | P115: =IF(L115=1,N115-O115,"") -> 0 | Q115: =INDEX(Directions!$D$2:$D$100,MATCH(C115,Directions!$A$2:$A$100,0)) -> 0 | R115: =IF(L115=1,P115*Q115,"") -> 0 | S115: =IF(L115<>1,"Excluded",IF(Q115=0,"No direction",IF(R115>0,"Better",IF(R115<0,"Worse","No change")))) -> No direction | U115: =C115&"|"&E115 -> F1_11|SWE
A116: 1 | B116: Spending | C116: F1_11 | D116: Long-term care | E116: FRA | F116: France | G116: 11 | H116: 15.6 | I116: 2024 | J116: 9 | K116: 9 | L116: 1 | M116: =IF(L116=1,COUNTIFS($C$2:$C$1090,C116,$L$2:$L$1090,1),"") -> 10 | N116: =IF(L116=1,1+COUNTIFS($C$2:$C$1090,C116,$L$2:$L$1090,1,$G$2:$G$1090,">"&G116),"") -> 8 | O116: =IF(L116=1,1+COUNTIFS($C$2:$C$1090,C116,$L$2:$L$1090,1,$H$2:$H$1090,">"&H116),"") -> 8 | P116: =IF(L116=1,N116-O116,"") -> 0 | Q116: =INDEX(Directions!$D$2:$D$100,MATCH(C116,Directions!$A$2:$A$100,0)) -> 0 | R116: =IF(L116=1,P116*Q116,"") -> 0 | S116: =IF(L116<>1,"Excluded",IF(Q116=0,"No direction",IF(R116>0,"Better",IF(R116<0,"Worse","No change")))) -> No direction | U116: =C116&"|"&E116 -> F1_11|FRA
A117: 1 | B117: Spending | C117: F1_11 | D117: Long-term care | E117: NLD | F117: NLD | G117: 26 | H117: 29.6 | I117: 2025 | J117: 2 | K117: 1 | L117: 0 | M117: =IF(L117=1,COUNTIFS($C$2:$C$1090,C117,$L$2:$L$1090,1),"") | N117: =IF(L117=1,1+COUNTIFS($C$2:$C$1090,C117,$L$2:$L$1090,1,$G$2:$G$1090,">"&G117),"") | O117: =IF(L117=1,1+COUNTIFS($C$2:$C$1090,C117,$L$2:$L$1090,1,$H$2:$H$1090,">"&H117),"") | P117: =IF(L117=1,N117-O117,"") | Q117: =INDEX(Directions!$D$2:$D$100,MATCH(C117,Directions!$A$2:$A$100,0)) -> 0 | R117: =IF(L117=1,P117*Q117,"") | S117: =IF(L117<>1,"Excluded",IF(Q117=0,"No direction",IF(R117>0,"Better",IF(R117<0,"Worse","No change")))) -> Excluded | T117: Excluded: Health-accounts series break 2021 (reclassification between functions) | U117: =C117&"|"&E117 -> F1_11|NLD
A118: 1 | B118: Spending | C118: F1_11 | D118: Long-term care | E118: CHE | F118: CHE | G118: 19 | H118: 21.5 | I118: 2024 | J118: 4 | K118: 5 | L118: 1 | M118: =IF(L118=1,COUNTIFS($C$2:$C$1090,C118,$L$2:$L$1090,1),"") -> 10 | N118: =IF(L118=1,1+COUNTIFS($C$2:$C$1090,C118,$L$2:$L$1090,1,$G$2:$G$1090,">"&G118),"") -> 3 | O118: =IF(L118=1,1+COUNTIFS($C$2:$C$1090,C118,$L$2:$L$1090,1,$H$2:$H$1090,">"&H118),"") -> 4 | P118: =IF(L118=1,N118-O118,"") -> -1 | Q118: =INDEX(Directions!$D$2:$D$100,MATCH(C118,Directions!$A$2:$A$100,0)) -> 0 | R118: =IF(L118=1,P118*Q118,"") -> 0 | S118: =IF(L118<>1,"Excluded",IF(Q118=0,"No direction",IF(R118>0,"Better",IF(R118<0,"Worse","No change")))) -> No direction | U118: =C118&"|"&E118 -> F1_11|CHE
A119: 1 | B119: Spending | C119: F1_11 | D119: Long-term care | E119: DNK | F119: Denmark | G119: 24 | H119: 21.5 | I119: 2025 | J119: 3 | K119: 6 | L119: 1 | M119: =IF(L119=1,COUNTIFS($C$2:$C$1090,C119,$L$2:$L$1090,1),"") -> 10 | N119: =IF(L119=1,1+COUNTIFS($C$2:$C$1090,C119,$L$2:$L$1090,1,$G$2:$G$1090,">"&G119),"") -> 2 | O119: =IF(L119=1,1+COUNTIFS($C$2:$C$1090,C119,$L$2:$L$1090,1,$H$2:$H$1090,">"&H119),"") -> 4 | P119: =IF(L119=1,N119-O119,"") -> -2 | Q119: =INDEX(Directions!$D$2:$D$100,MATCH(C119,Directions!$A$2:$A$100,0)) -> 0 | R119: =IF(L119=1,P119*Q119,"") -> 0 | S119: =IF(L119<>1,"Excluded",IF(Q119=0,"No direction",IF(R119>0,"Better",IF(R119<0,"Worse","No change")))) -> No direction | U119: =C119&"|"&E119 -> F1_11|DNK
A120: 1 | B120: Spending | C120: F1_11 | D120: Long-term care | E120: CAN | F120: Canada | G120: 14 | H120: 22 | I120: 2025 | J120: 8 | K120: 3 | L120: 1 | M120: =IF(L120=1,COUNTIFS($C$2:$C$1090,C120,$L$2:$L$1090,1),"") -> 10 | N120: =IF(L120=1,1+COUNTIFS($C$2:$C$1090,C120,$L$2:$L$1090,1,$G$2:$G$1090,">"&G120),"") -> 7 | O120: =IF(L120=1,1+COUNTIFS($C$2:$C$1090,C120,$L$2:$L$1090,1,$H$2:$H$1090,">"&H120),"") -> 2 | P120: =IF(L120=1,N120-O120,"") -> 5 | Q120: =INDEX(Directions!$D$2:$D$100,MATCH(C120,Directions!$A$2:$A$100,0)) -> 0 | R120: =IF(L120=1,P120*Q120,"") -> 0 | S120: =IF(L120<>1,"Excluded",IF(Q120=0,"No direction",IF(R120>0,"Better",IF(R120<0,"Worse","No change")))) -> No direction | U120: =C120&"|"&E120 -> F1_11|CAN
A121: 1 | B121: Spending | C121: F1_11 | D121: Long-term care | E121: JPN | F121: Japan | G121: 19 | H121: 19 | I121: 2023 | J121: 5 | K121: 8 | L121: 1 | M121: =IF(L121=1,COUNTIFS($C$2:$C$1090,C121,$L$2:$L$1090,1),"") -> 10 | N121: =IF(L121=1,1+COUNTIFS($C$2:$C$1090,C121,$L$2:$L$1090,1,$G$2:$G$1090,">"&G121),"") -> 3 | O121: =IF(L121=1,1+COUNTIFS($C$2:$C$1090,C121,$L$2:$L$1090,1,$H$2:$H$1090,">"&H121),"") -> 7 | P121: =IF(L121=1,N121-O121,"") -> -4 | Q121: =INDEX(Directions!$D$2:$D$100,MATCH(C121,Directions!$A$2:$A$100,0)) -> 0 | R121: =IF(L121=1,P121*Q121,"") -> 0 | S121: =IF(L121<>1,"Excluded",IF(Q121=0,"No direction",IF(R121>0,"Better",IF(R121<0,"Worse","No change")))) -> No direction | U121: =C121&"|"&E121 -> F1_11|JPN
A122: 1 | B122: Spending | C122: F1_11 | D122: Long-term care | E122: AUS | F122: Australia | G122: 2 | H122: 13.7 | I122: 2023 | J122: 11 | K122: 10 | L122: 1 | M122: =IF(L122=1,COUNTIFS($C$2:$C$1090,C122,$L$2:$L$1090,1),"") -> 10 | N122: =IF(L122=1,1+COUNTIFS($C$2:$C$1090,C122,$L$2:$L$1090,1,$G$2:$G$1090,">"&G122),"") -> 10 | O122: =IF(L122=1,1+COUNTIFS($C$2:$C$1090,C122,$L$2:$L$1090,1,$H$2:$H$1090,">"&H122),"") -> 9 | P122: =IF(L122=1,N122-O122,"") -> 1 | Q122: =INDEX(Directions!$D$2:$D$100,MATCH(C122,Directions!$A$2:$A$100,0)) -> 0 | R122: =IF(L122=1,P122*Q122,"") -> 0 | S122: =IF(L122<>1,"Excluded",IF(Q122=0,"No direction",IF(R122>0,"Better",IF(R122<0,"Worse","No change")))) -> No direction | U122: =C122&"|"&E122 -> F1_11|AUS
A123: 1 | B123: Spending | C123: F1_12 | D123: Medical goods | E123: USA | F123: US | G123: 14 | H123: 13.3 | I123: 2018 | J123: 7 | K123: 7 | L123: 1 | M123: =IF(L123=1,COUNTIFS($C$2:$C$1090,C123,$L$2:$L$1090,1),"") -> 10 | N123: =IF(L123=1,1+COUNTIFS($C$2:$C$1090,C123,$L$2:$L$1090,1,$G$2:$G$1090,">"&G123),"") -> 7 | O123: =IF(L123=1,1+COUNTIFS($C$2:$C$1090,C123,$L$2:$L$1090,1,$H$2:$H$1090,">"&H123),"") -> 7 | P123: =IF(L123=1,N123-O123,"") -> 0 | Q123: =INDEX(Directions!$D$2:$D$100,MATCH(C123,Directions!$A$2:$A$100,0)) -> 0 | R123: =IF(L123=1,P123*Q123,"") -> 0 | S123: =IF(L123<>1,"Excluded",IF(Q123=0,"No direction",IF(R123>0,"Better",IF(R123<0,"Worse","No change")))) -> No direction | T123: US 2018 health-accounts data (latest split); 2018 paper adjusted US inpatient +2 pts | U123: =C123&"|"&E123 -> F1_12|USA
A124: 1 | B124: Spending | C124: F1_12 | D124: Medical goods | E124: GBR | F124: UK | G124: 15 | H124: 10.6 | I124: 2024 | J124: 6 | K124: 10 | L124: 1 | M124: =IF(L124=1,COUNTIFS($C$2:$C$1090,C124,$L$2:$L$1090,1),"") -> 10 | N124: =IF(L124=1,1+COUNTIFS($C$2:$C$1090,C124,$L$2:$L$1090,1,$G$2:$G$1090,">"&G124),"") -> 6 | O124: =IF(L124=1,1+COUNTIFS($C$2:$C$1090,C124,$L$2:$L$1090,1,$H$2:$H$1090,">"&H124),"") -> 10 | P124: =IF(L124=1,N124-O124,"") -> -4 | Q124: =INDEX(Directions!$D$2:$D$100,MATCH(C124,Directions!$A$2:$A$100,0)) -> 0 | R124: =IF(L124=1,P124*Q124,"") -> 0 | S124: =IF(L124<>1,"Excluded",IF(Q124=0,"No direction",IF(R124>0,"Better",IF(R124<0,"Worse","No change")))) -> No direction | U124: =C124&"|"&E124 -> F1_12|GBR
A125: 1 | B125: Spending | C125: F1_12 | D125: Medical goods | E125: DEU | F125: Germany | G125: 20 | H125: 18.2 | I125: 2024 | J125: 1 | K125: 1 | L125: 1 | M125: =IF(L125=1,COUNTIFS($C$2:$C$1090,C125,$L$2:$L$1090,1),"") -> 10 | N125: =IF(L125=1,1+COUNTIFS($C$2:$C$1090,C125,$L$2:$L$1090,1,$G$2:$G$1090,">"&G125),"") -> 1 | O125: =IF(L125=1,1+COUNTIFS($C$2:$C$1090,C125,$L$2:$L$1090,1,$H$2:$H$1090,">"&H125),"") -> 1 | P125: =IF(L125=1,N125-O125,"") -> 0 | Q125: =INDEX(Directions!$D$2:$D$100,MATCH(C125,Directions!$A$2:$A$100,0)) -> 0 | R125: =IF(L125=1,P125*Q125,"") -> 0 | S125: =IF(L125<>1,"Excluded",IF(Q125=0,"No direction",IF(R125>0,"Better",IF(R125<0,"Worse","No change")))) -> No direction | U125: =C125&"|"&E125 -> F1_12|DEU
A126: 1 | B126: Spending | C126: F1_12 | D126: Medical goods | E126: SWE | F126: Sweden | G126: 12 | H126: 12.1 | I126: 2024 | J126: 9 | K126: 8 | L126: 1 | M126: =IF(L126=1,COUNTIFS($C$2:$C$1090,C126,$L$2:$L$1090,1),"") -> 10 | N126: =IF(L126=1,1+COUNTIFS($C$2:$C$1090,C126,$L$2:$L$1090,1,$G$2:$G$1090,">"&G126),"") -> 9 | O126: =IF(L126=1,1+COUNTIFS($C$2:$C$1090,C126,$L$2:$L$1090,1,$H$2:$H$1090,">"&H126),"") -> 8 | P126: =IF(L126=1,N126-O126,"") -> 1 | Q126: =INDEX(Directions!$D$2:$D$100,MATCH(C126,Directions!$A$2:$A$100,0)) -> 0 | R126: =IF(L126=1,P126*Q126,"") -> 0 | S126: =IF(L126<>1,"Excluded",IF(Q126=0,"No direction",IF(R126>0,"Better",IF(R126<0,"Worse","No change")))) -> No direction | U126: =C126&"|"&E126 -> F1_12|SWE
A127: 1 | B127: Spending | C127: F1_12 | D127: Medical goods | E127: FRA | F127: France | G127: 20 | H127: 17.4 | I127: 2024 | J127: 2 | K127: 3 | L127: 1 | M127: =IF(L127=1,COUNTIFS($C$2:$C$1090,C127,$L$2:$L$1090,1),"") -> 10 | N127: =IF(L127=1,1+COUNTIFS($C$2:$C$1090,C127,$L$2:$L$1090,1,$G$2:$G$1090,">"&G127),"") -> 1 | O127: =IF(L127=1,1+COUNTIFS($C$2:$C$1090,C127,$L$2:$L$1090,1,$H$2:$H$1090,">"&H127),"") -> 3 | P127: =IF(L127=1,N127-O127,"") -> -2 | Q127: =INDEX(Directions!$D$2:$D$100,MATCH(C127,Directions!$A$2:$A$100,0)) -> 0 | R127: =IF(L127=1,P127*Q127,"") -> 0 | S127: =IF(L127<>1,"Excluded",IF(Q127=0,"No direction",IF(R127>0,"Better",IF(R127<0,"Worse","No change")))) -> No direction | U127: =C127&"|"&E127 -> F1_12|FRA
A128: 1 | B128: Spending | C128: F1_12 | D128: Medical goods | E128: NLD | F128: NLD | G128: 12 | H128: 9.7 | I128: 2025 | J128: 10 | K128: 11 | L128: 0 | M128: =IF(L128=1,COUNTIFS($C$2:$C$1090,C128,$L$2:$L$1090,1),"") | N128: =IF(L128=1,1+COUNTIFS($C$2:$C$1090,C128,$L$2:$L$1090,1,$G$2:$G$1090,">"&G128),"") | O128: =IF(L128=1,1+COUNTIFS($C$2:$C$1090,C128,$L$2:$L$1090,1,$H$2:$H$1090,">"&H128),"") | P128: =IF(L128=1,N128-O128,"") | Q128: =INDEX(Directions!$D$2:$D$100,MATCH(C128,Directions!$A$2:$A$100,0)) -> 0 | R128: =IF(L128=1,P128*Q128,"") | S128: =IF(L128<>1,"Excluded",IF(Q128=0,"No direction",IF(R128>0,"Better",IF(R128<0,"Worse","No change")))) -> Excluded | T128: Excluded: Health-accounts series break 2021 (reclassification between functions) | U128: =C128&"|"&E128 -> F1_12|NLD
A129: 1 | B129: Spending | C129: F1_12 | D129: Medical goods | E129: CHE | F129: CHE | G129: 13 | H129: 14.5 | I129: 2024 | J129: 8 | K129: 6 | L129: 1 | M129: =IF(L129=1,COUNTIFS($C$2:$C$1090,C129,$L$2:$L$1090,1),"") -> 10 | N129: =IF(L129=1,1+COUNTIFS($C$2:$C$1090,C129,$L$2:$L$1090,1,$G$2:$G$1090,">"&G129),"") -> 8 | O129: =IF(L129=1,1+COUNTIFS($C$2:$C$1090,C129,$L$2:$L$1090,1,$H$2:$H$1090,">"&H129),"") -> 6 | P129: =IF(L129=1,N129-O129,"") -> 2 | Q129: =INDEX(Directions!$D$2:$D$100,MATCH(C129,Directions!$A$2:$A$100,0)) -> 0 | R129: =IF(L129=1,P129*Q129,"") -> 0 | S129: =IF(L129<>1,"Excluded",IF(Q129=0,"No direction",IF(R129>0,"Better",IF(R129<0,"Worse","No change")))) -> No direction | U129: =C129&"|"&E129 -> F1_12|CHE
A130: 1 | B130: Spending | C130: F1_12 | D130: Medical goods | E130: DNK | F130: Denmark | G130: 10 | H130: 11.8 | I130: 2025 | J130: 11 | K130: 9 | L130: 1 | M130: =IF(L130=1,COUNTIFS($C$2:$C$1090,C130,$L$2:$L$1090,1),"") -> 10 | N130: =IF(L130=1,1+COUNTIFS($C$2:$C$1090,C130,$L$2:$L$1090,1,$G$2:$G$1090,">"&G130),"") -> 10 | O130: =IF(L130=1,1+COUNTIFS($C$2:$C$1090,C130,$L$2:$L$1090,1,$H$2:$H$1090,">"&H130),"") -> 9 | P130: =IF(L130=1,N130-O130,"") -> 1 | Q130: =INDEX(Directions!$D$2:$D$100,MATCH(C130,Directions!$A$2:$A$100,0)) -> 0 | R130: =IF(L130=1,P130*Q130,"") -> 0 | S130: =IF(L130<>1,"Excluded",IF(Q130=0,"No direction",IF(R130>0,"Better",IF(R130<0,"Worse","No change")))) -> No direction | U130: =C130&"|"&E130 -> F1_12|DNK
A131: 1 | B131: Spending | C131: F1_12 | D131: Medical goods | E131: CAN | F131: Canada | G131: 20 | H131: 17.3 | I131: 2025 | J131: 3 | K131: 4 | L131: 1 | M131: =IF(L131=1,COUNTIFS($C$2:$C$1090,C131,$L$2:$L$1090,1),"") -> 10 | N131: =IF(L131=1,1+COUNTIFS($C$2:$C$1090,C131,$L$2:$L$1090,1,$G$2:$G$1090,">"&G131),"") -> 1 | O131: =IF(L131=1,1+COUNTIFS($C$2:$C$1090,C131,$L$2:$L$1090,1,$H$2:$H$1090,">"&H131),"") -> 4 | P131: =IF(L131=1,N131-O131,"") -> -3 | Q131: =INDEX(Directions!$D$2:$D$100,MATCH(C131,Directions!$A$2:$A$100,0)) -> 0 | R131: =IF(L131=1,P131*Q131,"") -> 0 | S131: =IF(L131<>1,"Excluded",IF(Q131=0,"No direction",IF(R131>0,"Better",IF(R131<0,"Worse","No change")))) -> No direction | U131: =C131&"|"&E131 -> F1_12|CAN
A132: 1 | B132: Spending | C132: F1_12 | D132: Medical goods | E132: JPN | F132: Japan | G132: 20 | H132: 18.1 | I132: 2023 | J132: 4 | K132: 2 | L132: 1 | M132: =IF(L132=1,COUNTIFS($C$2:$C$1090,C132,$L$2:$L$1090,1),"") -> 10 | N132: =IF(L132=1,1+COUNTIFS($C$2:$C$1090,C132,$L$2:$L$1090,1,$G$2:$G$1090,">"&G132),"") -> 1 | O132: =IF(L132=1,1+COUNTIFS($C$2:$C$1090,C132,$L$2:$L$1090,1,$H$2:$H$1090,">"&H132),"") -> 2 | P132: =IF(L132=1,N132-O132,"") -> -1 | Q132: =INDEX(Directions!$D$2:$D$100,MATCH(C132,Directions!$A$2:$A$100,0)) -> 0 | R132: =IF(L132=1,P132*Q132,"") -> 0 | S132: =IF(L132<>1,"Excluded",IF(Q132=0,"No direction",IF(R132>0,"Better",IF(R132<0,"Worse","No change")))) -> No direction | U132: =C132&"|"&E132 -> F1_12|JPN
A133: 1 | B133: Spending | C133: F1_12 | D133: Medical goods | E133: AUS | F133: Australia | G133: 17 | H133: 14.6 | I133: 2023 | J133: 5 | K133: 5 | L133: 1 | M133: =IF(L133=1,COUNTIFS($C$2:$C$1090,C133,$L$2:$L$1090,1),"") -> 10 | N133: =IF(L133=1,1+COUNTIFS($C$2:$C$1090,C133,$L$2:$L$1090,1,$G$2:$G$1090,">"&G133),"") -> 5 | O133: =IF(L133=1,1+COUNTIFS($C$2:$C$1090,C133,$L$2:$L$1090,1,$H$2:$H$1090,">"&H133),"") -> 5 | P133: =IF(L133=1,N133-O133,"") -> 0 | Q133: =INDEX(Directions!$D$2:$D$100,MATCH(C133,Directions!$A$2:$A$100,0)) -> 0 | R133: =IF(L133=1,P133*Q133,"") -> 0 | S133: =IF(L133<>1,"Excluded",IF(Q133=0,"No direction",IF(R133>0,"Better",IF(R133<0,"Worse","No change")))) -> No direction | U133: =C133&"|"&E133 -> F1_12|AUS
A134: 1 | B134: Spending | C134: F1_13 | D134: Governance and administration | E134: USA | F134: US | G134: 8 | H134: 8.8 | I134: 2018 | J134: 1 | K134: 1 | L134: 1 | M134: =IF(L134=1,COUNTIFS($C$2:$C$1090,C134,$L$2:$L$1090,1),"") -> 10 | N134: =IF(L134=1,1+COUNTIFS($C$2:$C$1090,C134,$L$2:$L$1090,1,$G$2:$G$1090,">"&G134),"") -> 1 | O134: =IF(L134=1,1+COUNTIFS($C$2:$C$1090,C134,$L$2:$L$1090,1,$H$2:$H$1090,">"&H134),"") -> 1 | P134: =IF(L134=1,N134-O134,"") -> 0 | Q134: =INDEX(Directions!$D$2:$D$100,MATCH(C134,Directions!$A$2:$A$100,0)) -> 0 | R134: =IF(L134=1,P134*Q134,"") -> 0 | S134: =IF(L134<>1,"Excluded",IF(Q134=0,"No direction",IF(R134>0,"Better",IF(R134<0,"Worse","No change")))) -> No direction | T134: US 2018 health-accounts data (latest split); 2018 paper adjusted US inpatient +2 pts | U134: =C134&"|"&E134 -> F1_13|USA
...

Sheet Performance_Matrix
A1: Relative performance change, 2018 → 2026 (positions gained among comparable countries)
A2: Green = better relative standing; red = worse; 0 = same position; – = not comparable. Indicators with a desirable direction only (see Directions). Example: +2 for a mortality row means the country moved 2 places toward the low-mortality end.
A4: Indicator ID | B4: Domain | C4: Indicator | D4: US | E4: UK | F4: Germany | G4: Sweden | H4: France | I4: NLD | J4: CHE | K4: Denmark | L4: Canada | M4: Japan | N4: Australia
A5: F1_05 | B5: Spending | C5: Poverty rate, % below poverty line of 60% | D5: =IFERROR(IF(INDEX(Rank_Changes!$R$2:$R$1090,MATCH($A5&"|"&"USA",Rank_Changes!$U$2:$U$1090,0))="","–",INDEX(Rank_Changes!$R$2:$R$1090,MATCH($A5&"|"&"USA",Rank_Changes!$U$2:$U$1090,0))),"–") -> 0 | E5: =IFERROR(IF(INDEX(Rank_Changes!$R$2:$R$1090,MATCH($A5&"|"&"GBR",Rank_Changes!$U$2:$U$1090,0))="","–",INDEX(Rank_Changes!$R$2:$R$1090,MATCH($A5&"|"&"GBR",Rank_Changes!$U$2:$U$1090,0))),"–") -> 0 | F5: =IFERROR(IF(INDEX(Rank_Changes!$R$2:$R$1090,MATCH($A5&"|"&"DEU",Rank_Changes!$U$2:$U$1090,0))="","–",INDEX(Rank_Changes!$R$2:$R$1090,MATCH($A5&"|"&"DEU",Rank_Changes!$U$2:$U$1090,0))),"–") -> -2 | G5: =IFERROR(IF(INDEX(Rank_Changes!$R$2:$R$1090,MATCH($A5&"|"&"SWE",Rank_Changes!$U$2:$U$1090,0))="","–",INDEX(Rank_Changes!$R$2:$R$1090,MATCH($A5&"|"&"SWE",Rank_Changes!$U$2:$U$1090,0))),"–") -> 2 | H5: =IFERROR(IF(INDEX(Rank_Changes!$R$2:$R$1090,MATCH($A5&"|"&"FRA",Rank_Changes!$U$2:$U$1090,0))="","–",INDEX(Rank_Changes!$R$2:$R$1090,MATCH($A5&"|"&"FRA",Rank_Changes!$U$2:$U$1090,0))),"–") -> 0 | I5: =IFERROR(IF(INDEX(Rank_Changes!$R$2:$R$1090,MATCH($A5&"|"&"NLD",Rank_Changes!$U$2:$U$1090,0))="","–",INDEX(Rank_Changes!$R$2:$R$1090,MATCH($A5&"|"&"NLD",Rank_Changes!$U$2:$U$1090,0))),"–") -> 1 | J5: =IFERROR(IF(INDEX(Rank_Changes!$R$2:$R$1090,MATCH($A5&"|"&"CHE",Rank_Changes!$U$2:$U$1090,0))="","–",INDEX(Rank_Changes!$R$2:$R$1090,MATCH($A5&"|"&"CHE",Rank_Changes!$U$2:$U$1090,0))),"–") -> 1 | K5: =IFERROR(IF(INDEX(Rank_Changes!$R$2:$R$1090,MATCH($A5&"|"&"DNK",Rank_Changes!$U$2:$U$1090,0))="","–",INDEX(Rank_Changes!$R$2:$R$1090,MATCH($A5&"|"&"DNK",Rank_Changes!$U$2:$U$1090,0))),"–") -> 0 | L5: =IFERROR(IF(INDEX(Rank_Changes!$R$2:$R$1090,MATCH($A5&"|"&"CAN",Rank_Changes!$U$2:$U$1090,0))="","–",INDEX(Rank_Changes!$R$2:$R$1090,MATCH($A5&"|"&"CAN",Rank_Changes!$U$2:$U$1090,0))),"–") -> 1 | M5: =IFERROR(IF(INDEX(Rank_Changes!$R$2:$R$1090,MATCH($A5&"|"&"JPN",Rank_Changes!$U$2:$U$1090,0))="","–",INDEX(Rank_Changes!$R$2:$R$1090,MATCH($A5&"|"&"JPN",Rank_Changes!$U$2:$U$1090,0))),"–") -> 0 | N5: =IFERROR(IF(INDEX(Rank_Changes!$R$2:$R$1090,MATCH($A5&"|"&"AUS",Rank_Changes!$U$2:$U$1090,0))="","–",INDEX(Rank_Changes!$R$2:$R$1090,MATCH($A5&"|"&"AUS",Rank_Changes!$U$2:$U$1090,0))),"–") -> -1
A6: F1_17 | B6: Spending | C6: Population with health care coverage, % | D6: =IFERROR(IF(INDEX(Rank_Changes!$R$2:$R$1090,MATCH($A6&"|"&"USA",Rank_Changes!$U$2:$U$1090,0))="","–",INDEX(Rank_Changes!$R$2:$R$1090,MATCH($A6&"|"&"USA",Rank_Changes!$U$2:$U$1090,0))),"–") -> 0 | E6: =IFERROR(IF(INDEX(Rank_Changes!$R$2:$R$1090,MATCH($A6&"|"&"GBR",Rank_Changes!$U$2:$U$1090,0))="","–",INDEX(Rank_Changes!$R$2:$R$1090,MATCH($A6&"|"&"GBR",Rank_Changes!$U$2:$U$1090,0))),"–") -> 0 | F6: =IFERROR(IF(INDEX(Rank_Changes!$R$2:$R$1090,MATCH($A6&"|"&"DEU",Rank_Changes!$U$2:$U$1090,0))="","–",INDEX(Rank_Changes!$R$2:$R$1090,MATCH($A6&"|"&"DEU",Rank_Changes!$U$2:$U$1090,0))),"–") -> 2 | G6: =IFERROR(IF(INDEX(Rank_Changes!$R$2:$R$1090,MATCH($A6&"|"&"SWE",Rank_Changes!$U$2:$U$1090,0))="","–",INDEX(Rank_Changes!$R$2:$R$1090,MATCH($A6&"|"&"SWE",Rank_Changes!$U$2:$U$1090,0))),"–") -> 0 | H6: =IFERROR(IF(INDEX(Rank_Changes!$R$2:$R$1090,MATCH($A6&"|"&"FRA",Rank_Changes!$U$2:$U$1090,0))="","–",INDEX(Rank_Changes!$R$2:$R$1090,MATCH($A6&"|"&"FRA",Rank_Changes!$U$2:$U$1090,0))),"–") -> 0 | I6: =IFERROR(IF(INDEX(Rank_Changes!$R$2:$R$1090,MATCH($A6&"|"&"NLD",Rank_Changes!$U$2:$U$1090,0))="","–",INDEX(Rank_Changes!$R$2:$R$1090,MATCH($A6&"|"&"NLD",Rank_Changes!$U$2:$U$1090,0))),"–") -> -2 | J6: =IFERROR(IF(INDEX(Rank_Changes!$R$2:$R$1090,MATCH($A6&"|"&"CHE",Rank_Changes!$U$2:$U$1090,0))="","–",INDEX(Rank_Changes!$R$2:$R$1090,MATCH($A6&"|"&"CHE",Rank_Changes!$U$2:$U$1090,0))),"–") -> 0 | K6: =IFERROR(IF(INDEX(Rank_Changes!$R$2:$R$1090,MATCH($A6&"|"&"DNK",Rank_Changes!$U$2:$U$1090,0))="","–",INDEX(Rank_Changes!$R$2:$R$1090,MATCH($A6&"|"&"DNK",Rank_Changes!$U$2:$U$1090,0))),"–") -> 0 | L6: =IFERROR(IF(INDEX(Rank_Changes!$R$2:$R$1090,MATCH($A6&"|"&"CAN",Rank_Changes!$U$2:$U$1090,0))="","–",INDEX(Rank_Changes!$R$2:$R$1090,MATCH($A6&"|"&"CAN",Rank_Changes!$U$2:$U$1090,0))),"–") -> 0 | M6: =IFERROR(IF(INDEX(Rank_Changes!$R$2:$R$1090,MATCH($A6&"|"&"JPN",Rank_Changes!$U$2:$U$1090,0))="","–",INDEX(Rank_Changes!$R$2:$R$1090,MATCH($A6&"|"&"JPN",Rank_Changes!$U$2:$U$1090,0))),"–") -> 0 | N6: =IFERROR(IF(INDEX(Rank_Changes!$R$2:$R$1090,MATCH($A6&"|"&"AUS",Rank_Changes!$U$2:$U$1090,0))="","–",INDEX(Rank_Changes!$R$2:$R$1090,MATCH($A6&"|"&"AUS",Rank_Changes!$U$2:$U$1090,0))),"–") -> 0
A7: F4_01 | B7: Population health | C7: Smoking, % of population aged ≥15 y who smoke daily | D7: =IFERROR(IF(INDEX(Rank_Changes!$R$2:$R$1090,MATCH($A7&"|"&"USA",Rank_Changes!$U$2:$U$1090,0))="","–",INDEX(Rank_Changes!$R$2:$R$1090,MATCH($A7&"|"&"USA",Rank_Changes!$U$2:$U$1090,0))),"–") -> 1 | E7: =IFERROR(IF(INDEX(Rank_Changes!$R$2:$R$1090,MATCH($A7&"|"&"GBR",Rank_Changes!$U$2:$U$1090,0))="","–",INDEX(Rank_Changes!$R$2:$R$1090,MATCH($A7&"|"&"GBR",Rank_Changes!$U$2:$U$1090,0))),"–") -> 0 | F7: =IFERROR(IF(INDEX(Rank_Changes!$R$2:$R$1090,MATCH($A7&"|"&"DEU",Rank_Changes!$U$2:$U$1090,0))="","–",INDEX(Rank_Changes!$R$2:$R$1090,MATCH($A7&"|"&"DEU",Rank_Changes!$U$2:$U$1090,0))),"–") -> 2 | G7: =IFERROR(IF(INDEX(Rank_Changes!$R$2:$R$1090,MATCH($A7&"|"&"SWE",Rank_Changes!$U$2:$U$1090,0))="","–",INDEX(Rank_Changes!$R$2:$R$1090,MATCH($A7&"|"&"SWE",Rank_Changes!$U$2:$U$1090,0))),"–") -> -2 | H7: =IFERROR(IF(INDEX(Rank_Changes!$R$2:$R$1090,MATCH($A7&"|"&"FRA",Rank_Changes!$U$2:$U$1090,0))="","–",INDEX(Rank_Changes!$R$2:$R$1090,MATCH($A7&"|"&"FRA",Rank_Changes!$U$2:$U$1090,0))),"–") -> 0 | I7: =IFERROR(IF(INDEX(Rank_Changes!$R$2:$R$1090,MATCH($A7&"|"&"NLD",Rank_Changes!$U$2:$U$1090,0))="","–",INDEX(Rank_Changes!$R$2:$R$1090,MATCH($A7&"|"&"NLD",Rank_Changes!$U$2:$U$1090,0))),"–") -> 1 | J7: =IFERROR(IF(INDEX(Rank_Changes!$R$2:$R$1090,MATCH($A7&"|"&"CHE",Rank_Changes!$U$2:$U$1090,0))="","–",INDEX(Rank_Changes!$R$2:$R$1090,MATCH($A7&"|"&"CHE",Rank_Changes!$U$2:$U$1090,0))),"–") -> -1 | K7: =IFERROR(IF(INDEX(Rank_Changes!$R$2:$R$1090,MATCH($A7&"|"&"DNK",Rank_Changes!$U$2:$U$1090,0))="","–",INDEX(Rank_Changes!$R$2:$R$1090,MATCH($A7&"|"&"DNK",Rank_Changes!$U$2:$U$1090,0))),"–") -> 0 | L7: =IFERROR(IF(INDEX(Rank_Changes!$R$2:$R$1090,MATCH($A7&"|"&"CAN",Rank_Changes!$U$2:$U$1090,0))="","–",INDEX(Rank_Changes!$R$2:$R$1090,MATCH($A7&"|"&"CAN",Rank_Changes!$U$2:$U$1090,0))),"–") -> 2 | M7: =IFERROR(IF(INDEX(Rank_Changes!$R$2:$R$1090,MATCH($A7&"|"&"JPN",Rank_Changes!$U$2:$U$1090,0))="","–",INDEX(Rank_Changes!$R$2:$R$1090,MATCH($A7&"|"&"JPN",Rank_Changes!$U$2:$U$1090,0))),"–") -> -2 | N7: =IFERROR(IF(INDEX(Rank_Changes!$R$2:$R$1090,MATCH($A7&"|"&"AUS",Rank_Changes!$U$2:$U$1090,0))="","–",INDEX(Rank_Changes!$R$2:$R$1090,MATCH($A7&"|"&"AUS",Rank_Changes!$U$2:$U$1090,0))),"–") -> -1
A8: F4_02 | B8: Population health | C8: Alcohol consumption, L per capita in population aged ≥15 y | D8: =IFERROR(IF(INDEX(Rank_Changes!$R$2:$R$1090,MATCH($A8&"|"&"USA",Rank_Changes!$U$2:$U$1090,0))="","–",INDEX(Rank_Changes!$R$2:$R$1090,MATCH($A8&"|"&"USA",Rank_Changes!$U$2:$U$1090,0))),"–") -> -3 | E8: =IFERROR(IF(INDEX(Rank_Changes!$R$2:$R$1090,MATCH($A8&"|"&"GBR",Rank_Changes!$U$2:$U$1090,0))="","–",INDEX(Rank_Changes!$R$2:$R$1090,MATCH($A8&"|"&"GBR",Rank_Changes!$U$2:$U$1090,0))),"–") -> 2 | F8: =IFERROR(IF(INDEX(Rank_Changes!$R$2:$R$1090,MATCH($A8&"|"&"DEU",Rank_Changes!$U$2:$U$1090,0))="","–",INDEX(Rank_Changes!$R$2:$R$1090,MATCH($A8&"|"&"DEU",Rank_Changes!$U$2:$U$1090,0))),"–") -> -1 | G8: =IFERROR(IF(INDEX(Rank_Changes!$R$2:$R$1090,MATCH($A8&"|"&"SWE",Rank_Changes!$U$2:$U$1090,0))="","–",INDEX(Rank_Changes!$R$2:$R$1090,MATCH($A8&"|"&"SWE",Rank_Changes!$U$2:$U$1090,0))),"–") -> -1 | H8: =IFERROR(IF(INDEX(Rank_Changes!$R$2:$R$1090,MATCH($A8&"|"&"FRA",Rank_Changes!$U$2:$U$1090,0))="","–",INDEX(Rank_Changes!$R$2:$R$1090,MATCH($A8&"|"&"FRA",Rank_Changes!$U$2:$U$1090,0))),"–") -> 1 | I8: =IFERROR(IF(INDEX(Rank_Changes!$R$2:$R$1090,MATCH($A8&"|"&"NLD",Rank_Changes!$U$2:$U$1090,0))="","–",INDEX(Rank_Changes!$R$2:$R$1090,MATCH($A8&"|"&"NLD",Rank_Changes!$U$2:$U$1090,0))),"–") -> 0 | J8: =IFERROR(IF(INDEX(Rank_Changes!$R$2:$R$1090,MATCH($A8&"|"&"CHE",Rank_Changes!$U$2:$U$1090,0))="","–",INDEX(Rank_Changes!$R$2:$R$1090,MATCH($A8&"|"&"CHE",Rank_Changes!$U$2:$U$1090,0))),"–") -> 4 | K8: =IFERROR(IF(INDEX(Rank_Changes!$R$2:$R$1090,MATCH($A8&"|"&"DNK",Rank_Changes!$U$2:$U$1090,0))="","–",INDEX(Rank_Changes!$R$2:$R$1090,MATCH($A8&"|"&"DNK",Rank_Changes!$U$2:$U$1090,0))),"–") -> -1 | L8: =IFERROR(IF(INDEX(Rank_Changes!$R$2:$R$1090,MATCH($A8&"|"&"CAN",Rank_Changes!$U$2:$U$1090,0))="","–",INDEX(Rank_Changes!$R$2:$R$1090,MATCH($A8&"|"&"CAN",Rank_Changes!$U$2:$U$1090,0))),"–") -> -1 | M8: =IFERROR(IF(INDEX(Rank_Changes!$R$2:$R$1090,MATCH($A8&"|"&"JPN",Rank_Changes!$U$2:$U$1090,0))="","–",INDEX(Rank_Changes!$R$2:$R$1090,MATCH($A8&"|"&"JPN",Rank_Changes!$U$2:$U$1090,0))),"–") -> 1 | N8: =IFERROR(IF(INDEX(Rank_Changes!$R$2:$R$1090,MATCH($A8&"|"&"AUS",Rank_Changes!$U$2:$U$1090,0))="","–",INDEX(Rank_Changes!$R$2:$R$1090,MATCH($A8&"|"&"AUS",Rank_Changes!$U$2:$U$1090,0))),"–") -> -1
A9: F4_03 | B9: Population health | C9: Obese or overweight, % of population aged ≥15 y | D9: =IFERROR(IF(INDEX(Rank_Changes!$R$2:$R$1090,MATCH($A9&"|"&"USA",Rank_Changes!$U$2:$U$1090,0))="","–",INDEX(Rank_Changes!$R$2:$R$1090,MATCH($A9&"|"&"USA",Rank_Changes!$U$2:$U$1090,0))),"–") -> 0 | E9: =IFERROR(IF(INDEX(Rank_Changes!$R$2:$R$1090,MATCH($A9&"|"&"GBR",Rank_Changes!$U$2:$U$1090,0))="","–",INDEX(Rank_Changes!$R$2:$R$1090,MATCH($A9&"|"&"GBR",Rank_Changes!$U$2:$U$1090,0))),"–") -> -1 | F9: =IFERROR(IF(INDEX(Rank_Changes!$R$2:$R$1090,MATCH($A9&"|"&"DEU",Rank_Changes!$U$2:$U$1090,0))="","–",INDEX(Rank_Changes!$R$2:$R$1090,MATCH($A9&"|"&"DEU",Rank_Changes!$U$2:$U$1090,0))),"–") -> – | G9: =IFERROR(IF(INDEX(Rank_Changes!$R$2:$R$1090,MATCH($A9&"|"&"SWE",Rank_Changes!$U$2:$U$1090,0))="","–",INDEX(Rank_Changes!$R$2:$R$1090,MATCH($A9&"|"&"SWE",Rank_Changes!$U$2:$U$1090,0))),"–") -> -1 | H9: =IFERROR(IF(INDEX(Rank_Changes!$R$2:$R$1090,MATCH($A9&"|"&"FRA",Rank_Changes!$U$2:$U$1090,0))="","–",INDEX(Rank_Changes!$R$2:$R$1090,MATCH($A9&"|"&"FRA",Rank_Changes!$U$2:$U$1090,0))),"–") -> 3 | I9: =IFERROR(IF(INDEX(Rank_Changes!$R$2:$R$1090,MATCH($A9&"|"&"NLD",Rank_Changes!$U$2:$U$1090,0))="","–",INDEX(Rank_Changes!$R$2:$R$1090,MATCH($A9&"|"&"NLD",Rank_Changes!$U$2:$U$1090,0))),"–") -> 0 | J9: =IFERROR(IF(INDEX(Rank_Changes!$R$2:$R$1090,MATCH($A9&"|"&"CHE",Rank_Changes!$U$2:$U$1090,0))="","–",INDEX(Rank_Changes!$R$2:$R$1090,MATCH($A9&"|"&"CHE",Rank_Changes!$U$2:$U$1090,0))),"–") -> 0 | K9: =IFERROR(IF(INDEX(Rank_Changes!$R$2:$R$1090,MATCH($A9&"|"&"DNK",Rank_Changes!$U$2:$U$1090,0))="","–",INDEX(Rank_Changes!$R$2:$R$1090,MATCH($A9&"|"&"DNK",Rank_Changes!$U$2:$U$1090,0))),"–") -> -1 | L9: =IFERROR(IF(INDEX(Rank_Changes!$R$2:$R$1090,MATCH($A9&"|"&"CAN",Rank_Changes!$U$2:$U$1090,0))="","–",INDEX(Rank_Changes!$R$2:$R$1090,MATCH($A9&"|"&"CAN",Rank_Changes!$U$2:$U$1090,0))),"–") -> 0 | M9: =IFERROR(IF(INDEX(Rank_Changes!$R$2:$R$1090,MATCH($A9&"|"&"JPN",Rank_Changes!$U$2:$U$1090,0))="","–",INDEX(Rank_Changes!$R$2:$R$1090,MATCH($A9&"|"&"JPN",Rank_Changes!$U$2:$U$1090,0))),"–") -> 0 | N9: =IFERROR(IF(INDEX(Rank_Changes!$R$2:$R$1090,MATCH($A9&"|"&"AUS",Rank_Changes!$U$2:$U$1090,0))="","–",INDEX(Rank_Changes!$R$2:$R$1090,MATCH($A9&"|"&"AUS",Rank_Changes!$U$2:$U$1090,0))),"–") -> 1
A10: F4_04 | B10: Population health | C10: Life expectancy in total population at birth, mean, y | D10: =IFERROR(IF(INDEX(Rank_Changes!$R$2:$R$1090,MATCH($A10&"|"&"USA",Rank_Changes!$U$2:$U$1090,0))="","–",INDEX(Rank_Changes!$R$2:$R$1090,MATCH($A10&"|"&"USA",Rank_Changes!$U$2:$U$1090,0))),"–") -> 0 | E10: =IFERROR(IF(INDEX(Rank_Changes!$R$2:$R$1090,MATCH($A10&"|"&"GBR",Rank_Changes!$U$2:$U$1090,0))="","–",INDEX(Rank_Changes!$R$2:$R$1090,MATCH($A10&"|"&"GBR",Rank_Changes!$U$2:$U$1090,0))),"–") -> -1 | F10: =IFERROR(IF(INDEX(Rank_Changes!$R$2:$R$1090,MATCH($A10&"|"&"DEU",Rank_Changes!$U$2:$U$1090,0))="","–",INDEX(Rank_Changes!$R$2:$R$1090,MATCH($A10&"|"&"DEU",Rank_Changes!$U$2:$U$1090,0))),"–") -> 0 | G10: =IFERROR(IF(INDEX(Rank_Changes!$R$2:$R$1090,MATCH($A10&"|"&"SWE",Rank_Changes!$U$2:$U$1090,0))="","–",INDEX(Rank_Changes!$R$2:$R$1090,MATCH($A10&"|"&"SWE",Rank_Changes!$U$2:$U$1090,0))),"–") -> 2 | H10: =IFERROR(IF(INDEX(Rank_Changes!$R$2:$R$1090,MATCH($A10&"|"&"FRA",Rank_Changes!$U$2:$U$1090,0))="","–",INDEX(Rank_Changes!$R$2:$R$1090,MATCH($A10&"|"&"FRA",Rank_Changes!$U$2:$U$1090,0))),"–") -> 0 | I10: =IFERROR(IF(INDEX(Rank_Changes!$R$2:$R$1090,MATCH($A10&"|"&"NLD",Rank_Changes!$U$2:$U$1090,0))="","–",INDEX(Rank_Changes!$R$2:$R$1090,MATCH($A10&"|"&"NLD",Rank_Changes!$U$2:$U$1090,0))),"–") -> -1 | J10: =IFERROR(IF(INDEX(Rank_Changes!$R$2:$R$1090,MATCH($A10&"|"&"CHE",Rank_Changes!$U$2:$U$1090,0))="","–",INDEX(Rank_Changes!$R$2:$R$1090,MATCH($A10&"|"&"CHE",Rank_Changes!$U$2:$U$1090,0))),"–") -> 1 | K10: =IFERROR(IF(INDEX(Rank_Changes!$R$2:$R$1090,MATCH($A10&"|"&"DNK",Rank_Changes!$U$2:$U$1090,0))="","–",INDEX(Rank_Changes!$R$2:$R$1090,MATCH($A10&"|"&"DNK",Rank_Changes!$U$2:$U$1090,0))),"–") -> 2 | L10: =IFERROR(IF(INDEX(Rank_Changes!$R$2:$R$1090,MATCH($A10&"|"&"CAN",Rank_Changes!$U$2:$U$1090,0))="","–",INDEX(Rank_Changes!$R$2:$R$1090,MATCH($A10&"|"&"CAN",Rank_Changes!$U$2:$U$1090,0))),"–") -> 0 | M10: =IFERROR(IF(INDEX(Rank_Changes!$R$2:$R$1090,MATCH($A10&"|"&"JPN",Rank_Changes!$U$2:$U$1090,0))="","–",INDEX(Rank_Changes!$R$2:$R$1090,MATCH($A10&"|"&"JPN",Rank_Changes!$U$2:$U$1090,0))),"–") -> -1 | N10: =IFERROR(IF(INDEX(Rank_Changes!$R$2:$R$1090,MATCH($A10&"|"&"AUS",Rank_Changes!$U$2:$U$1090,0))="","–",INDEX(Rank_Changes!$R$2:$R$1090,MATCH($A10&"|"&"AUS",Rank_Changes!$U$2:$U$1090,0))),"–") -> -1
A11: F4_05 | B11: Population health | C11: Health-adjusted life expectancy, mean, y | D11: =IFERROR(IF(INDEX(Rank_Changes!$R$2:$R$1090,MATCH($A11&"|"&"USA",Rank_Changes!$U$2:$U$1090,0))="","–",INDEX(Rank_Changes!$R$2:$R$1090,MATCH($A11&"|"&"USA",Rank_Changes!$U$2:$U$1090,0))),"–") -> 0 | E11: =IFERROR(IF(INDEX(Rank_Changes!$R$2:$R$1090,MATCH($A11&"|"&"GBR",Rank_Changes!$U$2:$U$1090,0))="","–",INDEX(Rank_Changes!$R$2:$R$1090,MATCH($A11&"|"&"GBR",Rank_Changes!$U$2:$U$1090,0))),"–") -> -2 | F11: =IFERROR(IF(INDEX(Rank_Changes!$R$2:$R$1090,MATCH($A11&"|"&"DEU",Rank_Changes!$U$2:$U$1090,0))="","–",INDEX(Rank_Changes!$R$2:$R$1090,MATCH($A11&"|"&"DEU",Rank_Changes!$U$2:$U$1090,0))),"–") -> 0 | G11: =IFERROR(IF(INDEX(Rank_Changes!$R$2:$R$1090,MATCH($A11&"|"&"SWE",Rank_Changes!$U$2:$U$1090,0))="","–",INDEX(Rank_Changes!$R$2:$R$1090,MATCH($A11&"|"&"SWE",Rank_Changes!$U$2:$U$1090,0))),"–") -> 3 | H11: =IFERROR(IF(INDEX(Rank_Changes!$R$2:$R$1090,MATCH($A11&"|"&"FRA",Rank_Changes!$U$2:$U$1090,0))="","–",INDEX(Rank_Changes!$R$2:$R$1090,MATCH($A11&"|"&"FRA",Rank_Changes!$U$2:$U$1090,0))),"–") -> -2 | I11: =IFERROR(IF(INDEX(Rank_Changes!$R$2:$R$1090,MATCH($A11&"|"&"NLD",Rank_Changes!$U$2:$U$1090,0))="","–",INDEX(Rank_Changes!$R$2:$R$1090,MATCH($A11&"|"&"NLD",Rank_Changes!$U$2:$U$1090,0))),"–") -> -2 | J11: =IFERROR(IF(INDEX(Rank_Changes!$R$2:$R$1090,MATCH($A11&"|"&"CHE",Rank_Changes!$U$2:$U$1090,0))="","–",INDEX(Rank_Changes!$R$2:$R$1090,MATCH($A11&"|"&"CHE",Rank_Changes!$U$2:$U$1090,0))),"–") -> 0 | K11: =IFERROR(IF(INDEX(Rank_Changes!$R$2:$R$1090,MATCH($A11&"|"&"DNK",Rank_Changes!$U$2:$U$1090,0))="","–",INDEX(Rank_Changes!$R$2:$R$1090,MATCH($A11&"|"&"DNK",Rank_Changes!$U$2:$U$1090,0))),"–") -> 4 | L11: =IFERROR(IF(INDEX(Rank_Changes!$R$2:$R$1090,MATCH($A11&"|"&"CAN",Rank_Changes!$U$2:$U$1090,0))="","–",INDEX(Rank_Changes!$R$2:$R$1090,MATCH($A11&"|"&"CAN",Rank_Changes!$U$2:$U$1090,0))),"–") -> -4 | M11: =IFERROR(IF(INDEX(Rank_Changes!$R$2:$R$1090,MATCH($A11&"|"&"JPN",Rank_Changes!$U$2:$U$1090,0))="","–",INDEX(Rank_Changes!$R$2:$R$1090,MATCH($A11&"|"&"JPN",Rank_Changes!$U$2:$U$1090,0))),"–") -> 0 | N11: =IFERROR(IF(INDEX(Rank_Changes!$R$2:$R$1090,MATCH($A11&"|"&"AUS",Rank_Changes!$U$2:$U$1090,0))="","–",INDEX(Rank_Changes!$R$2:$R$1090,MATCH($A11&"|"&"AUS",Rank_Changes!$U$2:$U$1090,0))),"–") -> 3
A12: F4_06 | B12: Population health | C12: Life expectancy for women aged ≥40 y, mean, y | D12: =IFERROR(IF(INDEX(Rank_Changes!$R$2:$R$1090,MATCH($A12&"|"&"USA",Rank_Changes!$U$2:$U$1090,0))="","–",INDEX(Rank_Changes!$R$2:$R$1090,MATCH($A12&"|"&"USA",Rank_Changes!$U$2:$U$1090,0))),"–") -> 0 | E12: =IFERROR(IF(INDEX(Rank_Changes!$R$2:$R$1090,MATCH($A12&"|"&"GBR",Rank_Changes!$U$2:$U$1090,0))="","–",INDEX(Rank_Changes!$R$2:$R$1090,MATCH($A12&"|"&"GBR",Rank_Changes!$U$2:$U$1090,0))),"–") -> 1 | F12: =IFERROR(IF(INDEX(Rank_Changes!$R$2:$R$1090,MATCH($A12&"|"&"DEU",Rank_Changes!$U$2:$U$1090,0))="","–",INDEX(Rank_Changes!$R$2:$R$1090,MATCH($A12&"|"&"DEU",Rank_Changes!$U$2:$U$1090,0))),"–") -> -1 | G12: =IFERROR(IF(INDEX(Rank_Changes!$R$2:$R$1090,MATCH($A12&"|"&"SWE",Rank_Changes!$U$2:$U$1090,0))="","–",INDEX(Rank_Changes!$R$2:$R$1090,MATCH($A12&"|"&"SWE",Rank_Changes!$U$2:$U$1090,0))),"–") -> 1 | H12: =IFERROR(IF(INDEX(Rank_Changes!$R$2:$R$1090,MATCH($A12&"|"&"FRA",Rank_Changes!$U$2:$U$1090,0))="","–",INDEX(Rank_Changes!$R$2:$R$1090,MATCH($A12&"|"&"FRA",Rank_Changes!$U$2:$U$1090,0))),"–") -> 0 | I12: =IFERROR(IF(INDEX(Rank_Changes!$R$2:$R$1090,MATCH($A12&"|"&"NLD",Rank_Changes!$U$2:$U$1090,0))="","–",INDEX(Rank_Changes!$R$2:$R$1090,MATCH($A12&"|"&"NLD",Rank_Changes!$U$2:$U$1090,0))),"–") -> -3 | J12: =IFERROR(IF(INDEX(Rank_Changes!$R$2:$R$1090,MATCH($A12&"|"&"CHE",Rank_Changes!$U$2:$U$1090,0))="","–",INDEX(Rank_Changes!$R$2:$R$1090,MATCH($A12&"|"&"CHE",Rank_Changes!$U$2:$U$1090,0))),"–") -> 1 | K12: =IFERROR(IF(INDEX(Rank_Changes!$R$2:$R$1090,MATCH($A12&"|"&"DNK",Rank_Changes!$U$2:$U$1090,0))="","–",INDEX(Rank_Changes!$R$2:$R$1090,MATCH($A12&"|"&"DNK",Rank_Changes!$U$2:$U$1090,0))),"–") -> 3 | L12: =IFERROR(IF(INDEX(Rank_Changes!$R$2:$R$1090,MATCH($A12&"|"&"CAN",Rank_Changes!$U$2:$U$1090,0))="","–",INDEX(Rank_Changes!$R$2:$R$1090,MATCH($A12&"|"&"CAN",Rank_Changes!$U$2:$U$1090,0))),"–") -> -1 | M12: =IFERROR(IF(INDEX(Rank_Changes!$R$2:$R$1090,MATCH($A12&"|"&"JPN",Rank_Changes!$U$2:$U$1090,0))="","–",INDEX(Rank_Changes!$R$2:$R$1090,MATCH($A12&"|"&"JPN",Rank_Changes!$U$2:$U$1090,0))),"–") -> 0 | N12: =IFERROR(IF(INDEX(Rank_Changes!$R$2:$R$1090,MATCH($A12&"|"&"AUS",Rank_Changes!$U$2:$U$1090,0))="","–",INDEX(Rank_Changes!$R$2:$R$1090,MATCH($A12&"|"&"AUS",Rank_Changes!$U$2:$U$1090,0))),"–") -> 0
A13: F4_07 | B13: Population health | C13: Life expectancy for men aged ≥40 y, mean, y | D13: =IFERROR(IF(INDEX(Rank_Changes!$R$2:$R$1090,MATCH($A13&"|"&"USA",Rank_Changes!$U$2:$U$1090,0))="","–",INDEX(Rank_Changes!$R$2:$R$1090,MATCH($A13&"|"&"USA",Rank_Changes!$U$2:$U$1090,0))),"–") -> 0 | E13: =IFERROR(IF(INDEX(Rank_Changes!$R$2:$R$1090,MATCH($A13&"|"&"GBR",Rank_Changes!$U$2:$U$1090,0))="","–",INDEX(Rank_Changes!$R$2:$R$1090,MATCH($A13&"|"&"GBR",Rank_Changes!$U$2:$U$1090,0))),"–") -> -1 | F13: =IFERROR(IF(INDEX(Rank_Changes!$R$2:$R$1090,MATCH($A13&"|"&"DEU",Rank_Changes!$U$2:$U$1090,0))="","–",INDEX(Rank_Changes!$R$2:$R$1090,MATCH($A13&"|"&"DEU",Rank_Changes!$U$2:$U$1090,0))),"–") -> 0 | G13: =IFERROR(IF(INDEX(Rank_Changes!$R$2:$R$1090,MATCH($A13&"|"&"SWE",Rank_Changes!$U$2:$U$1090,0))="","–",INDEX(Rank_Changes!$R$2:$R$1090,MATCH($A13&"|"&"SWE",Rank_Changes!$U$2:$U$1090,0))),"–") -> 2 | H13: =IFERROR(IF(INDEX(Rank_Changes!$R$2:$R$1090,MATCH($A13&"|"&"FRA",Rank_Changes!$U$2:$U$1090,0))="","–",INDEX(Rank_Changes!$R$2:$R$1090,MATCH($A13&"|"&"FRA",Rank_Changes!$U$2:$U$1090,0))),"–") -> 1 | I13: =IFERROR(IF(INDEX(Rank_Changes!$R$2:$R$1090,MATCH($A13&"|"&"NLD",Rank_Changes!$U$2:$U$1090,0))="","–",INDEX(Rank_Changes!$R$2:$R$1090,MATCH($A13&"|"&"NLD",Rank_Changes!$U$2:$U$1090,0))),"–") -> -1 | J13: =IFERROR(IF(INDEX(Rank_Changes!$R$2:$R$1090,MATCH($A13&"|"&"CHE",Rank_Changes!$U$2:$U$1090,0))="","–",INDEX(Rank_Changes!$R$2:$R$1090,MATCH($A13&"|"&"CHE",Rank_Changes!$U$2:$U$1090,0))),"–") -> 0 | K13: =IFERROR(IF(INDEX(Rank_Changes!$R$2:$R$1090,MATCH($A13&"|"&"DNK",Rank_Changes!$U$2:$U$1090,0))="","–",INDEX(Rank_Changes!$R$2:$R$1090,MATCH($A13&"|"&"DNK",Rank_Changes!$U$2:$U$1090,0))),"–") -> 1 | L13: =IFERROR(IF(INDEX(Rank_Changes!$R$2:$R$1090,MATCH($A13&"|"&"CAN",Rank_Changes!$U$2:$U$1090,0))="","–",INDEX(Rank_Changes!$R$2:$R$1090,MATCH($A13&"|"&"CAN",Rank_Changes!$U$2:$U$1090,0))),"–") -> 0 | M13: =IFERROR(IF(INDEX(Rank_Changes!$R$2:$R$1090,MATCH($A13&"|"&"JPN",Rank_Changes!$U$2:$U$1090,0))="","–",INDEX(Rank_Changes!$R$2:$R$1090,MATCH($A13&"|"&"JPN",Rank_Changes!$U$2:$U$1090,0))),"–") -> -2 | N13: =IFERROR(IF(INDEX(Rank_Changes!$R$2:$R$1090,MATCH($A13&"|"&"AUS",Rank_Changes!$U$2:$U$1090,0))="","–",INDEX(Rank_Changes!$R$2:$R$1090,MATCH($A13&"|"&"AUS",Rank_Changes!$U$2:$U$1090,0))),"–") -> 0
A14: F4_08 | B14: Population health | C14: Maternal mortality, deaths per 100 000 live births | D14: =IFERROR(IF(INDEX(Rank_Changes!$R$2:$R$1090,MATCH($A14&"|"&"USA",Rank_Changes!$U$2:$U$1090,0))="","–",INDEX(Rank_Changes!$R$2:$R$1090,MATCH($A14&"|"&"USA",Rank_Changes!$U$2:$U$1090,0))),"–") -> 0 | E14: =IFERROR(IF(INDEX(Rank_Changes!$R$2:$R$1090,MATCH($A14&"|"&"GBR",Rank_Changes!$U$2:$U$1090,0))="","–",INDEX(Rank_Changes!$R$2:$R$1090,MATCH($A14&"|"&"GBR",Rank_Changes!$U$2:$U$1090,0))),"–") -> 1 | F14: =IFERROR(IF(INDEX(Rank_Changes!$R$2:$R$1090,MATCH($A14&"|"&"DEU",Rank_Changes!$U$2:$U$1090,0))="","–",INDEX(Rank_Changes!$R$2:$R$1090,MATCH($A14&"|"&"DEU",Rank_Changes!$U$2:$U$1090,0))),"–") -> 5 | G14: =IFERROR(IF(INDEX(Rank_Changes!$R$2:$R$1090,MATCH($A14&"|"&"SWE",Rank_Changes!$U$2:$U$1090,0))="","–",INDEX(Rank_Changes!$R$2:$R$1090,MATCH($A14&"|"&"SWE",Rank_Changes!$U$2:$U$1090,0))),"–") -> -3 | H14: =IFERROR(IF(INDEX(Rank_Changes!$R$2:$R$1090,MATCH($A14&"|"&"FRA",Rank_Changes!$U$2:$U$1090,0))="","–",INDEX(Rank_Changes!$R$2:$R$1090,MATCH($A14&"|"&"FRA",Rank_Changes!$U$2:$U$1090,0))),"–") -> 0 | I14: =IFERROR(IF(INDEX(Rank_Changes!$R$2:$R$1090,MATCH($A14&"|"&"NLD",Rank_Changes!$U$2:$U$1090,0))="","–",INDEX(Rank_Changes!$R$2:$R$1090,MATCH($A14&"|"&"NLD",Rank_Changes!$U$2:$U$1090,0))),"–") -> 4 | J14: =IFERROR(IF(INDEX(Rank_Changes!$R$2:$R$1090,MATCH($A14&"|"&"CHE",Rank_Changes!$U$2:$U$1090,0))="","–",INDEX(Rank_Changes!$R$2:$R$1090,MATCH($A14&"|"&"CHE",Rank_Changes!$U$2:$U$1090,0))),"–") -> -2 | K14: =IFERROR(IF(INDEX(Rank_Changes!$R$2:$R$1090,MATCH($A14&"|"&"DNK",Rank_Changes!$U$2:$U$1090,0))="","–",INDEX(Rank_Changes!$R$2:$R$1090,MATCH($A14&"|"&"DNK",Rank_Changes!$U$2:$U$1090,0))),"–") -> 0 | L14: =IFERROR(IF(INDEX(Rank_Changes!$R$2:$R$1090,MATCH($A14&"|"&"CAN",Rank_Changes!$U$2:$U$1090,0))="","–",INDEX(Rank_Changes!$R$2:$R$1090,MATCH($A14&"|"&"CAN",Rank_Changes!$U$2:$U$1090,0))),"–") -> -3 | M14: =IFERROR(IF(INDEX(Rank_Changes!$R$2:$R$1090,MATCH($A14&"|"&"JPN",Rank_Changes!$U$2:$U$1090,0))="","–",INDEX(Rank_Changes!$R$2:$R$1090,MATCH($A14&"|"&"JPN",Rank_Changes!$U$2:$U$1090,0))),"–") -> 1 | N14: =IFERROR(IF(INDEX(Rank_Changes!$R$2:$R$1090,MATCH($A14&"|"&"AUS",Rank_Changes!$U$2:$U$1090,0))="","–",INDEX(Rank_Changes!$R$2:$R$1090,MATCH($A14&"|"&"AUS",Rank_Changes!$U$2:$U$1090,0))),"–") -> -4
A15: F4_09 | B15: Population health | C15: Infant mortality, deaths per 1000 live births | D15: =IFERROR(IF(INDEX(Rank_Changes!$R$2:$R$1090,MATCH($A15&"|"&"USA",Rank_Changes!$U$2:$U$1090,0))="","–",INDEX(Rank_Changes!$R$2:$R$1090,MATCH($A15&"|"&"USA",Rank_Changes!$U$2:$U$1090,0))),"–") -> 0 | E15: =IFERROR(IF(INDEX(Rank_Changes!$R$2:$R$1090,MATCH($A15&"|"&"GBR",Rank_Changes!$U$2:$U$1090,0))="","–",INDEX(Rank_Changes!$R$2:$R$1090,MATCH($A15&"|"&"GBR",Rank_Changes!$U$2:$U$1090,0))),"–") -> 0 | F15: =IFERROR(IF(INDEX(Rank_Changes!$R$2:$R$1090,MATCH($A15&"|"&"DEU",Rank_Changes!$U$2:$U$1090,0))="","–",INDEX(Rank_Changes!$R$2:$R$1090,MATCH($A15&"|"&"DEU",Rank_Changes!$U$2:$U$1090,0))),"–") -> -2 | G15: =IFERROR(IF(INDEX(Rank_Changes!$R$2:$R$1090,MATCH($A15&"|"&"SWE",Rank_Changes!$U$2:$U$1090,0))="","–",INDEX(Rank_Changes!$R$2:$R$1090,MATCH($A15&"|"&"SWE",Rank_Changes!$U$2:$U$1090,0))),"–") -> 1 | H15: =IFERROR(IF(INDEX(Rank_Changes!$R$2:$R$1090,MATCH($A15&"|"&"FRA",Rank_Changes!$U$2:$U$1090,0))="","–",INDEX(Rank_Changes!$R$2:$R$1090,MATCH($A15&"|"&"FRA",Rank_Changes!$U$2:$U$1090,0))),"–") -> -1 | I15: =IFERROR(IF(INDEX(Rank_Changes!$R$2:$R$1090,MATCH($A15&"|"&"NLD",Rank_Changes!$U$2:$U$1090,0))="","–",INDEX(Rank_Changes!$R$2:$R$1090,MATCH($A15&"|"&"NLD",Rank_Changes!$U$2:$U$1090,0))),"–") -> -4 | J15: =IFERROR(IF(INDEX(Rank_Changes!$R$2:$R$1090,MATCH($A15&"|"&"CHE",Rank_Changes!$U$2:$U$1090,0))="","–",INDEX(Rank_Changes!$R$2:$R$1090,MATCH($A15&"|"&"CHE",Rank_Changes!$U$2:$U$1090,0))),"–") -> 2 | K15: =IFERROR(IF(INDEX(Rank_Changes!$R$2:$R$1090,MATCH($A15&"|"&"DNK",Rank_Changes!$U$2:$U$1090,0))="","–",INDEX(Rank_Changes!$R$2:$R$1090,MATCH($A15&"|"&"DNK",Rank_Changes!$U$2:$U$1090,0))),"–") -> 3 | L15: =IFERROR(IF(INDEX(Rank_Changes!$R$2:$R$1090,MATCH($A15&"|"&"CAN",Rank_Changes!$U$2:$U$1090,0))="","–",INDEX(Rank_Changes!$R$2:$R$1090,MATCH($A15&"|"&"CAN",Rank_Changes!$U$2:$U$1090,0))),"–") -> 0 | M15: =IFERROR(IF(INDEX(Rank_Changes!$R$2:$R$1090,MATCH($A15&"|"&"JPN",Rank_Changes!$U$2:$U$1090,0))="","–",INDEX(Rank_Changes!$R$2:$R$1090,MATCH($A15&"|"&"JPN",Rank_Changes!$U$2:$U$1090,0))),"–") -> 0 | N15: =IFERROR(IF(INDEX(Rank_Changes!$R$2:$R$1090,MATCH($A15&"|"&"AUS",Rank_Changes!$U$2:$U$1090,0))="","–",INDEX(Rank_Changes!$R$2:$R$1090,MATCH($A15&"|"&"AUS",Rank_Changes!$U$2:$U$1090,0))),"–") -> -3
A16: F4_10 | B16: Population health | C16: Neonatal mortality, deaths per 1000 live births | D16: =IFERROR(IF(INDEX(Rank_Changes!$R$2:$R$1090,MATCH($A16&"|"&"USA",Rank_Changes!$U$2:$U$1090,0))="","–",INDEX(Rank_Changes!$R$2:$R$1090,MATCH($A16&"|"&"USA",Rank_Changes!$U$2:$U$1090,0))),"–") -> 0 | E16: =IFERROR(IF(INDEX(Rank_Changes!$R$2:$R$1090,MATCH($A16&"|"&"GBR",Rank_Changes!$U$2:$U$1090,0))="","–",INDEX(Rank_Changes!$R$2:$R$1090,MATCH($A16&"|"&"GBR",Rank_Changes!$U$2:$U$1090,0))),"–") -> -2 | F16: =IFERROR(IF(INDEX(Rank_Changes!$R$2:$R$1090,MATCH($A16&"|"&"DEU",Rank_Changes!$U$2:$U$1090,0))="","–",INDEX(Rank_Changes!$R$2:$R$1090,MATCH($A16&"|"&"DEU",Rank_Changes!$U$2:$U$1090,0))),"–") -> -1 | G16: =IFERROR(IF(INDEX(Rank_Changes!$R$2:$R$1090,MATCH($A16&"|"&"SWE",Rank_Changes!$U$2:$U$1090,0))="","–",INDEX(Rank_Changes!$R$2:$R$1090,MATCH($A16&"|"&"SWE",Rank_Changes!$U$2:$U$1090,0))),"–") -> 0 | H16: =IFERROR(IF(INDEX(Rank_Changes!$R$2:$R$1090,MATCH($A16&"|"&"FRA",Rank_Changes!$U$2:$U$1090,0))="","–",INDEX(Rank_Changes!$R$2:$R$1090,MATCH($A16&"|"&"FRA",Rank_Changes!$U$2:$U$1090,0))),"–") -> -2 | I16: =IFERROR(IF(INDEX(Rank_Changes!$R$2:$R$1090,MATCH($A16&"|"&"NLD",Rank_Changes!$U$2:$U$1090,0))="","–",INDEX(Rank_Changes!$R$2:$R$1090,MATCH($A16&"|"&"NLD",Rank_Changes!$U$2:$U$1090,0))),"–") -> -1 | J16: =IFERROR(IF(INDEX(Rank_Changes!$R$2:$R$1090,MATCH($A16&"|"&"CHE",Rank_Changes!$U$2:$U$1090,0))="","–",INDEX(Rank_Changes!$R$2:$R$1090,MATCH($A16&"|"&"CHE",Rank_Changes!$U$2:$U$1090,0))),"–") -> 2 | K16: =IFERROR(IF(INDEX(Rank_Changes!$R$2:$R$1090,MATCH($A16&"|"&"DNK",Rank_Changes!$U$2:$U$1090,0))="","–",INDEX(Rank_Changes!$R$2:$R$1090,MATCH($A16&"|"&"DNK",Rank_Changes!$U$2:$U$1090,0))),"–") -> 5 | L16: =IFERROR(IF(INDEX(Rank_Changes!$R$2:$R$1090,MATCH($A16&"|"&"CAN",Rank_Changes!$U$2:$U$1090,0))="","–",INDEX(Rank_Changes!$R$2:$R$1090,MATCH($A16&"|"&"CAN",Rank_Changes!$U$2:$U$1090,0))),"–") -> 0 | M16: =IFERROR(IF(INDEX(Rank_Changes!$R$2:$R$1090,MATCH($A16&"|"&"JPN",Rank_Changes!$U$2:$U$1090,0))="","–",INDEX(Rank_Changes!$R$2:$R$1090,MATCH($A16&"|"&"JPN",Rank_Changes!$U$2:$U$1090,0))),"–") -> 0 | N16: =IFERROR(IF(INDEX(Rank_Changes!$R$2:$R$1090,MATCH($A16&"|"&"AUS",Rank_Changes!$U$2:$U$1090,0))="","–",INDEX(Rank_Changes!$R$2:$R$1090,MATCH($A16&"|"&"AUS",Rank_Changes!$U$2:$U$1090,0))),"–") -> -1
... A41: F11_06 | B41: Equity | C41: % Unmet need, above-average income | D41: =IFERROR(IF(INDEX(Rank_Changes!$R$2:$R$1090,MATCH($A41&"|"&"USA",Rank_Changes!$U$2:$U$1090,0))="","–",INDEX(Rank_Changes!$R$2:$R$1090,MATCH($A41&"|"&"USA",Rank_Changes!$U$2:$U$1090,0))),"–") -> 0 | E41: =IFERROR(IF(INDEX(Rank_Changes!$R$2:$R$1090,MATCH($A41&"|"&"GBR",Rank_Changes!$U$2:$U$1090,0))="","–",INDEX(Rank_Changes!$R$2:$R$1090,MATCH($A41&"|"&"GBR",Rank_Changes!$U$2:$U$1090,0))),"–") -> -2 | F41: =IFERROR(IF(INDEX(Rank_Changes!$R$2:$R$1090,MATCH($A41&"|"&"DEU",Rank_Changes!$U$2:$U$1090,0))="","–",INDEX(Rank_Changes!$R$2:$R$1090,MATCH($A41&"|"&"DEU",Rank_Changes!$U$2:$U$1090,0))),"–") -> -3 | G41: =IFERROR(IF(INDEX(Rank_Changes!$R$2:$R$1090,MATCH($A41&"|"&"SWE",Rank_Changes!$U$2:$U$1090,0))="","–",INDEX(Rank_Changes!$R$2:$R$1090,MATCH($A41&"|"&"SWE",Rank_Changes!$U$2:$U$1090,0))),"–") -> 0 | H41: =IFERROR(IF(INDEX(Rank_Changes!$R$2:$R$1090,MATCH($A41&"|"&"FRA",Rank_Changes!$U$2:$U$1090,0))="","–",INDEX(Rank_Changes!$R$2:$R$1090,MATCH($A41&"|"&"FRA",Rank_Changes!$U$2:$U$1090,0))),"–") -> 3 | I41: =IFERROR(IF(INDEX(Rank_Changes!$R$2:$R$1090,MATCH($A41&"|"&"NLD",Rank_Changes!$U$2:$U$1090,0))="","–",INDEX(Rank_Changes!$R$2:$R$1090,MATCH($A41&"|"&"NLD",Rank_Changes!$U$2:$U$1090,0))),"–") -> 4 | J41: =IFERROR(IF(INDEX(Rank_Changes!$R$2:$R$1090,MATCH($A41&"|"&"CHE",Rank_Changes!$U$2:$U$1090,0))="","–",INDEX(Rank_Changes!$R$2:$R$1090,MATCH($A41&"|"&"CHE",Rank_Changes!$U$2:$U$1090,0))),"–") -> 1 | K41: =IFERROR(IF(INDEX(Rank_Changes!$R$2:$R$1090,MATCH($A41&"|"&"DNK",Rank_Changes!$U$2:$U$1090,0))="","–",INDEX(Rank_Changes!$R$2:$R$1090,MATCH($A41&"|"&"DNK",Rank_Changes!$U$2:$U$1090,0))),"–") -> – | L41: =IFERROR(IF(INDEX(Rank_Changes!$R$2:$R$1090,MATCH($A41&"|"&"CAN",Rank_Changes!$U$2:$U$1090,0))="","–",INDEX(Rank_Changes!$R$2:$R$1090,MATCH($A41&"|"&"CAN",Rank_Changes!$U$2:$U$1090,0))),"–") -> -1 | M41: =IFERROR(IF(INDEX(Rank_Changes!$R$2:$R$1090,MATCH($A41&"|"&"JPN",Rank_Changes!$U$2:$U$1090,0))="","–",INDEX(Rank_Changes!$R$2:$R$1090,MATCH($A41&"|"&"JPN",Rank_Changes!$U$2:$U$1090,0))),"–") -> – | N41: =IFERROR(IF(INDEX(Rank_Changes!$R$2:$R$1090,MATCH($A41&"|"&"AUS",Rank_Changes!$U$2:$U$1090,0))="","–",INDEX(Rank_Changes!$R$2:$R$1090,MATCH($A41&"|"&"AUS",Rank_Changes!$U$2:$U$1090,0))),"–") -> -3

Sheet Rank_Movement_Matrix
A1: Raw rank movement, 2018 → 2026 (all indicators; + = moved toward rank 1 / higher value)
A2: Blue = moved up (higher value relative to others); orange = moved down; – = not comparable. No judgment of good or bad.
A4: Indicator ID | B4: Domain | C4: Indicator | D4: US | E4: UK | F4: Germany | G4: Sweden | H4: France | I4: NLD | J4: CHE | K4: Denmark | L4: Canada | M4: Japan | N4: Australia
A5: F1_01 | B5: Spending | C5: Overall population (in millions) | D5: =IFERROR(IF(INDEX(Rank_Changes!$P$2:$P$1090,MATCH($A5&"|"&"USA",Rank_Changes!$U$2:$U$1090,0))="","–",INDEX(Rank_Changes!$P$2:$P$1090,MATCH($A5&"|"&"USA",Rank_Changes!$U$2:$U$1090,0))),"–") -> 0 | E5: =IFERROR(IF(INDEX(Rank_Changes!$P$2:$P$1090,MATCH($A5&"|"&"GBR",Rank_Changes!$U$2:$U$1090,0))="","–",INDEX(Rank_Changes!$P$2:$P$1090,MATCH($A5&"|"&"GBR",Rank_Changes!$U$2:$U$1090,0))),"–") -> 0 | F5: =IFERROR(IF(INDEX(Rank_Changes!$P$2:$P$1090,MATCH($A5&"|"&"DEU",Rank_Changes!$U$2:$U$1090,0))="","–",INDEX(Rank_Changes!$P$2:$P$1090,MATCH($A5&"|"&"DEU",Rank_Changes!$U$2:$U$1090,0))),"–") -> 0 | G5: =IFERROR(IF(INDEX(Rank_Changes!$P$2:$P$1090,MATCH($A5&"|"&"SWE",Rank_Changes!$U$2:$U$1090,0))="","–",INDEX(Rank_Changes!$P$2:$P$1090,MATCH($A5&"|"&"SWE",Rank_Changes!$U$2:$U$1090,0))),"–") -> 0 | H5: =IFERROR(IF(INDEX(Rank_Changes!$P$2:$P$1090,MATCH($A5&"|"&"FRA",Rank_Changes!$U$2:$U$1090,0))="","–",INDEX(Rank_Changes!$P$2:$P$1090,MATCH($A5&"|"&"FRA",Rank_Changes!$U$2:$U$1090,0))),"–") -> 0 | I5: =IFERROR(IF(INDEX(Rank_Changes!$P$2:$P$1090,MATCH($A5&"|"&"NLD",Rank_Changes!$U$2:$U$1090,0))="","–",INDEX(Rank_Changes!$P$2:$P$1090,MATCH($A5&"|"&"NLD",Rank_Changes!$U$2:$U$1090,0))),"–") -> 0 | J5: =IFERROR(IF(INDEX(Rank_Changes!$P$2:$P$1090,MATCH($A5&"|"&"CHE",Rank_Changes!$U$2:$U$1090,0))="","–",INDEX(Rank_Changes!$P$2:$P$1090,MATCH($A5&"|"&"CHE",Rank_Changes!$U$2:$U$1090,0))),"–") -> 0 | K5: =IFERROR(IF(INDEX(Rank_Changes!$P$2:$P$1090,MATCH($A5&"|"&"DNK",Rank_Changes!$U$2:$U$1090,0))="","–",INDEX(Rank_Changes!$P$2:$P$1090,MATCH($A5&"|"&"DNK",Rank_Changes!$U$2:$U$1090,0))),"–") -> 0 | L5: =IFERROR(IF(INDEX(Rank_Changes!$P$2:$P$1090,MATCH($A5&"|"&"CAN",Rank_Changes!$U$2:$U$1090,0))="","–",INDEX(Rank_Changes!$P$2:$P$1090,MATCH($A5&"|"&"CAN",Rank_Changes!$U$2:$U$1090,0))),"–") -> 0 | M5: =IFERROR(IF(INDEX(Rank_Changes!$P$2:$P$1090,MATCH($A5&"|"&"JPN",Rank_Changes!$U$2:$U$1090,0))="","–",INDEX(Rank_Changes!$P$2:$P$1090,MATCH($A5&"|"&"JPN",Rank_Changes!$U$2:$U$1090,0))),"–") -> 0 | N5: =IFERROR(IF(INDEX(Rank_Changes!$P$2:$P$1090,MATCH($A5&"|"&"AUS",Rank_Changes!$U$2:$U$1090,0))="","–",INDEX(Rank_Changes!$P$2:$P$1090,MATCH($A5&"|"&"AUS",Rank_Changes!$U$2:$U$1090,0))),"–") -> 0
A6: F1_02 | B6: Spending | C6: Population ≥65 y, % | D6: =IFERROR(IF(INDEX(Rank_Changes!$P$2:$P$1090,MATCH($A6&"|"&"USA",Rank_Changes!$U$2:$U$1090,0))="","–",INDEX(Rank_Changes!$P$2:$P$1090,MATCH($A6&"|"&"USA",Rank_Changes!$U$2:$U$1090,0))),"–") -> 1 | E6: =IFERROR(IF(INDEX(Rank_Changes!$P$2:$P$1090,MATCH($A6&"|"&"GBR",Rank_Changes!$U$2:$U$1090,0))="","–",INDEX(Rank_Changes!$P$2:$P$1090,MATCH($A6&"|"&"GBR",Rank_Changes!$U$2:$U$1090,0))),"–") -> -2 | F6: =IFERROR(IF(INDEX(Rank_Changes!$P$2:$P$1090,MATCH($A6&"|"&"DEU",Rank_Changes!$U$2:$U$1090,0))="","–",INDEX(Rank_Changes!$P$2:$P$1090,MATCH($A6&"|"&"DEU",Rank_Changes!$U$2:$U$1090,0))),"–") -> 0 | G6: =IFERROR(IF(INDEX(Rank_Changes!$P$2:$P$1090,MATCH($A6&"|"&"SWE",Rank_Changes!$U$2:$U$1090,0))="","–",INDEX(Rank_Changes!$P$2:$P$1090,MATCH($A6&"|"&"SWE",Rank_Changes!$U$2:$U$1090,0))),"–") -> -1 | H6: =IFERROR(IF(INDEX(Rank_Changes!$P$2:$P$1090,MATCH($A6&"|"&"FRA",Rank_Changes!$U$2:$U$1090,0))="","–",INDEX(Rank_Changes!$P$2:$P$1090,MATCH($A6&"|"&"FRA",Rank_Changes!$U$2:$U$1090,0))),"–") -> 1 | I6: =IFERROR(IF(INDEX(Rank_Changes!$P$2:$P$1090,MATCH($A6&"|"&"NLD",Rank_Changes!$U$2:$U$1090,0))="","–",INDEX(Rank_Changes!$P$2:$P$1090,MATCH($A6&"|"&"NLD",Rank_Changes!$U$2:$U$1090,0))),"–") -> 2 | J6: =IFERROR(IF(INDEX(Rank_Changes!$P$2:$P$1090,MATCH($A6&"|"&"CHE",Rank_Changes!$U$2:$U$1090,0))="","–",INDEX(Rank_Changes!$P$2:$P$1090,MATCH($A6&"|"&"CHE",Rank_Changes!$U$2:$U$1090,0))),"–") -> -1 | K6: =IFERROR(IF(INDEX(Rank_Changes!$P$2:$P$1090,MATCH($A6&"|"&"DNK",Rank_Changes!$U$2:$U$1090,0))="","–",INDEX(Rank_Changes!$P$2:$P$1090,MATCH($A6&"|"&"DNK",Rank_Changes!$U$2:$U$1090,0))),"–") -> 0 | L6: =IFERROR(IF(INDEX(Rank_Changes!$P$2:$P$1090,MATCH($A6&"|"&"CAN",Rank_Changes!$U$2:$U$1090,0))="","–",INDEX(Rank_Changes!$P$2:$P$1090,MATCH($A6&"|"&"CAN",Rank_Changes!$U$2:$U$1090,0))),"–") -> 1 | M6: =IFERROR(IF(INDEX(Rank_Changes!$P$2:$P$1090,MATCH($A6&"|"&"JPN",Rank_Changes!$U$2:$U$1090,0))="","–",INDEX(Rank_Changes!$P$2:$P$1090,MATCH($A6&"|"&"JPN",Rank_Changes!$U$2:$U$1090,0))),"–") -> 0 | N6: =IFERROR(IF(INDEX(Rank_Changes!$P$2:$P$1090,MATCH($A6&"|"&"AUS",Rank_Changes!$U$2:$U$1090,0))="","–",INDEX(Rank_Changes!$P$2:$P$1090,MATCH($A6&"|"&"AUS",Rank_Changes!$U$2:$U$1090,0))),"–") -> -1
A7: F1_03 | B7: Spending | C7: GDP per capita, US $ (in thousands) | D7: =IFERROR(IF(INDEX(Rank_Changes!$P$2:$P$1090,MATCH($A7&"|"&"USA",Rank_Changes!$U$2:$U$1090,0))="","–",INDEX(Rank_Changes!$P$2:$P$1090,MATCH($A7&"|"&"USA",Rank_Changes!$U$2:$U$1090,0))),"–") -> 1 | E7: =IFERROR(IF(INDEX(Rank_Changes!$P$2:$P$1090,MATCH($A7&"|"&"GBR",Rank_Changes!$U$2:$U$1090,0))="","–",INDEX(Rank_Changes!$P$2:$P$1090,MATCH($A7&"|"&"GBR",Rank_Changes!$U$2:$U$1090,0))),"–") -> 1 | F7: =IFERROR(IF(INDEX(Rank_Changes!$P$2:$P$1090,MATCH($A7&"|"&"DEU",Rank_Changes!$U$2:$U$1090,0))="","–",INDEX(Rank_Changes!$P$2:$P$1090,MATCH($A7&"|"&"DEU",Rank_Changes!$U$2:$U$1090,0))),"–") -> 2 | G7: =IFERROR(IF(INDEX(Rank_Changes!$P$2:$P$1090,MATCH($A7&"|"&"SWE",Rank_Changes!$U$2:$U$1090,0))="","–",INDEX(Rank_Changes!$P$2:$P$1090,MATCH($A7&"|"&"SWE",Rank_Changes!$U$2:$U$1090,0))),"–") -> -3 | H7: =IFERROR(IF(INDEX(Rank_Changes!$P$2:$P$1090,MATCH($A7&"|"&"FRA",Rank_Changes!$U$2:$U$1090,0))="","–",INDEX(Rank_Changes!$P$2:$P$1090,MATCH($A7&"|"&"FRA",Rank_Changes!$U$2:$U$1090,0))),"–") -> -1 | I7: =IFERROR(IF(INDEX(Rank_Changes!$P$2:$P$1090,MATCH($A7&"|"&"NLD",Rank_Changes!$U$2:$U$1090,0))="","–",INDEX(Rank_Changes!$P$2:$P$1090,MATCH($A7&"|"&"NLD",Rank_Changes!$U$2:$U$1090,0))),"–") -> 2 | J7: =IFERROR(IF(INDEX(Rank_Changes!$P$2:$P$1090,MATCH($A7&"|"&"CHE",Rank_Changes!$U$2:$U$1090,0))="","–",INDEX(Rank_Changes!$P$2:$P$1090,MATCH($A7&"|"&"CHE",Rank_Changes!$U$2:$U$1090,0))),"–") -> 0 | K7: =IFERROR(IF(INDEX(Rank_Changes!$P$2:$P$1090,MATCH($A7&"|"&"DNK",Rank_Changes!$U$2:$U$1090,0))="","–",INDEX(Rank_Changes!$P$2:$P$1090,MATCH($A7&"|"&"DNK",Rank_Changes!$U$2:$U$1090,0))),"–") -> -2 | L7: =IFERROR(IF(INDEX(Rank_Changes!$P$2:$P$1090,MATCH($A7&"|"&"CAN",Rank_Changes!$U$2:$U$1090,0))="","–",INDEX(Rank_Changes!$P$2:$P$1090,MATCH($A7&"|"&"CAN",Rank_Changes!$U$2:$U$1090,0))),"–") -> 0 | M7: =IFERROR(IF(INDEX(Rank_Changes!$P$2:$P$1090,MATCH($A7&"|"&"JPN",Rank_Changes!$U$2:$U$1090,0))="","–",INDEX(Rank_Changes!$P$2:$P$1090,MATCH($A7&"|"&"JPN",Rank_Changes!$U$2:$U$1090,0))),"–") -> 0 | N7: =IFERROR(IF(INDEX(Rank_Changes!$P$2:$P$1090,MATCH($A7&"|"&"AUS",Rank_Changes!$U$2:$U$1090,0))="","–",INDEX(Rank_Changes!$P$2:$P$1090,MATCH($A7&"|"&"AUS",Rank_Changes!$U$2:$U$1090,0))),"–") -> 0
A8: F1_04 | B8: Spending | C8: Land area (× 1000 sq km) | D8: =IFERROR(IF(INDEX(Rank_Changes!$P$2:$P$1090,MATCH($A8&"|"&"USA",Rank_Changes!$U$2:$U$1090,0))="","–",INDEX(Rank_Changes!$P$2:$P$1090,MATCH($A8&"|"&"USA",Rank_Changes!$U$2:$U$1090,0))),"–") -> 1 | E8: =IFERROR(IF(INDEX(Rank_Changes!$P$2:$P$1090,MATCH($A8&"|"&"GBR",Rank_Changes!$U$2:$U$1090,0))="","–",INDEX(Rank_Changes!$P$2:$P$1090,MATCH($A8&"|"&"GBR",Rank_Changes!$U$2:$U$1090,0))),"–") -> 0 | F8: =IFERROR(IF(INDEX(Rank_Changes!$P$2:$P$1090,MATCH($A8&"|"&"DEU",Rank_Changes!$U$2:$U$1090,0))="","–",INDEX(Rank_Changes!$P$2:$P$1090,MATCH($A8&"|"&"DEU",Rank_Changes!$U$2:$U$1090,0))),"–") -> 0 | G8: =IFERROR(IF(INDEX(Rank_Changes!$P$2:$P$1090,MATCH($A8&"|"&"SWE",Rank_Changes!$U$2:$U$1090,0))="","–",INDEX(Rank_Changes!$P$2:$P$1090,MATCH($A8&"|"&"SWE",Rank_Changes!$U$2:$U$1090,0))),"–") -> 0 | H8: =IFERROR(IF(INDEX(Rank_Changes!$P$2:$P$1090,MATCH($A8&"|"&"FRA",Rank_Changes!$U$2:$U$1090,0))="","–",INDEX(Rank_Changes!$P$2:$P$1090,MATCH($A8&"|"&"FRA",Rank_Changes!$U$2:$U$1090,0))),"–") -> 0 | I8: =IFERROR(IF(INDEX(Rank_Changes!$P$2:$P$1090,MATCH($A8&"|"&"NLD",Rank_Changes!$U$2:$U$1090,0))="","–",INDEX(Rank_Changes!$P$2:$P$1090,MATCH($A8&"|"&"NLD",Rank_Changes!$U$2:$U$1090,0))),"–") -> -1 | J8: =IFERROR(IF(INDEX(Rank_Changes!$P$2:$P$1090,MATCH($A8&"|"&"CHE",Rank_Changes!$U$2:$U$1090,0))="","–",INDEX(Rank_Changes!$P$2:$P$1090,MATCH($A8&"|"&"CHE",Rank_Changes!$U$2:$U$1090,0))),"–") -> 0 | K8: =IFERROR(IF(INDEX(Rank_Changes!$P$2:$P$1090,MATCH($A8&"|"&"DNK",Rank_Changes!$U$2:$U$1090,0))="","–",INDEX(Rank_Changes!$P$2:$P$1090,MATCH($A8&"|"&"DNK",Rank_Changes!$U$2:$U$1090,0))),"–") -> 0 | L8: =IFERROR(IF(INDEX(Rank_Changes!$P$2:$P$1090,MATCH($A8&"|"&"CAN",Rank_Changes!$U$2:$U$1090,0))="","–",INDEX(Rank_Changes!$P$2:$P$1090,MATCH($A8&"|"&"CAN",Rank_Changes!$U$2:$U$1090,0))),"–") -> -1 | M8: =IFERROR(IF(INDEX(Rank_Changes!$P$2:$P$1090,MATCH($A8&"|"&"JPN",Rank_Changes!$U$2:$U$1090,0))="","–",INDEX(Rank_Changes!$P$2:$P$1090,MATCH($A8&"|"&"JPN",Rank_Changes!$U$2:$U$1090,0))),"–") -> 0 | N8: =IFERROR(IF(INDEX(Rank_Changes!$P$2:$P$1090,MATCH($A8&"|"&"AUS",Rank_Changes!$U$2:$U$1090,0))="","–",INDEX(Rank_Changes!$P$2:$P$1090,MATCH($A8&"|"&"AUS",Rank_Changes!$U$2:$U$1090,0))),"–") -> 0
A9: F1_05 | B9: Spending | C9: Poverty rate, % below poverty line of 60% | D9: =IFERROR(IF(INDEX(Rank_Changes!$P$2:$P$1090,MATCH($A9&"|"&"USA",Rank_Changes!$U$2:$U$1090,0))="","–",INDEX(Rank_Changes!$P$2:$P$1090,MATCH($A9&"|"&"USA",Rank_Changes!$U$2:$U$1090,0))),"–") -> 0 | E9: =IFERROR(IF(INDEX(Rank_Changes!$P$2:$P$1090,MATCH($A9&"|"&"GBR",Rank_Changes!$U$2:$U$1090,0))="","–",INDEX(Rank_Changes!$P$2:$P$1090,MATCH($A9&"|"&"GBR",Rank_Changes!$U$2:$U$1090,0))),"–") -> 0 | F9: =IFERROR(IF(INDEX(Rank_Changes!$P$2:$P$1090,MATCH($A9&"|"&"DEU",Rank_Changes!$U$2:$U$1090,0))="","–",INDEX(Rank_Changes!$P$2:$P$1090,MATCH($A9&"|"&"DEU",Rank_Changes!$U$2:$U$1090,0))),"–") -> 2 | G9: =IFERROR(IF(INDEX(Rank_Changes!$P$2:$P$1090,MATCH($A9&"|"&"SWE",Rank_Changes!$U$2:$U$1090,0))="","–",INDEX(Rank_Changes!$P$2:$P$1090,MATCH($A9&"|"&"SWE",Rank_Changes!$U$2:$U$1090,0))),"–") -> -2 | H9: =IFERROR(IF(INDEX(Rank_Changes!$P$2:$P$1090,MATCH($A9&"|"&"FRA",Rank_Changes!$U$2:$U$1090,0))="","–",INDEX(Rank_Changes!$P$2:$P$1090,MATCH($A9&"|"&"FRA",Rank_Changes!$U$2:$U$1090,0))),"–") -> 0 | I9: =IFERROR(IF(INDEX(Rank_Changes!$P$2:$P$1090,MATCH($A9&"|"&"NLD",Rank_Changes!$U$2:$U$1090,0))="","–",INDEX(Rank_Changes!$P$2:$P$1090,MATCH($A9&"|"&"NLD",Rank_Changes!$U$2:$U$1090,0))),"–") -> -1 | J9: =IFERROR(IF(INDEX(Rank_Changes!$P$2:$P$1090,MATCH($A9&"|"&"CHE",Rank_Changes!$U$2:$U$1090,0))="","–",INDEX(Rank_Changes!$P$2:$P$1090,MATCH($A9&"|"&"CHE",Rank_Changes!$U$2:$U$1090,0))),"–") -> -1 | K9: =IFERROR(IF(INDEX(Rank_Changes!$P$2:$P$1090,MATCH($A9&"|"&"DNK",Rank_Changes!$U$2:$U$1090,0))="","–",INDEX(Rank_Changes!$P$2:$P$1090,MATCH($A9&"|"&"DNK",Rank_Changes!$U$2:$U$1090,0))),"–") -> 0 | L9: =IFERROR(IF(INDEX(Rank_Changes!$P$2:$P$1090,MATCH($A9&"|"&"CAN",Rank_Changes!$U$2:$U$1090,0))="","–",INDEX(Rank_Changes!$P$2:$P$1090,MATCH($A9&"|"&"CAN",Rank_Changes!$U$2:$U$1090,0))),"–") -> -1 | M9: =IFERROR(IF(INDEX(Rank_Changes!$P$2:$P$1090,MATCH($A9&"|"&"JPN",Rank_Changes!$U$2:$U$1090,0))="","–",INDEX(Rank_Changes!$P$2:$P$1090,MATCH($A9&"|"&"JPN",Rank_Changes!$U$2:$U$1090,0))),"–") -> 0 | N9: =IFERROR(IF(INDEX(Rank_Changes!$P$2:$P$1090,MATCH($A9&"|"&"AUS",Rank_Changes!$U$2:$U$1090,0))="","–",INDEX(Rank_Changes!$P$2:$P$1090,MATCH($A9&"|"&"AUS",Rank_Changes!$U$2:$U$1090,0))),"–") -> 1
A10: F1_06 | B10: Spending | C10: Total spending on health, % of total national GDP | D10: =IFERROR(IF(INDEX(Rank_Changes!$P$2:$P$1090,MATCH($A10&"|"&"USA",Rank_Changes!$U$2:$U$1090,0))="","–",INDEX(Rank_Changes!$P$2:$P$1090,MATCH($A10&"|"&"USA",Rank_Changes!$U$2:$U$1090,0))),"–") -> 0 | E10: =IFERROR(IF(INDEX(Rank_Changes!$P$2:$P$1090,MATCH($A10&"|"&"GBR",Rank_Changes!$U$2:$U$1090,0))="","–",INDEX(Rank_Changes!$P$2:$P$1090,MATCH($A10&"|"&"GBR",Rank_Changes!$U$2:$U$1090,0))),"–") -> 3 | F10: =IFERROR(IF(INDEX(Rank_Changes!$P$2:$P$1090,MATCH($A10&"|"&"DEU",Rank_Changes!$U$2:$U$1090,0))="","–",INDEX(Rank_Changes!$P$2:$P$1090,MATCH($A10&"|"&"DEU",Rank_Changes!$U$2:$U$1090,0))),"–") -> 2 | G10: =IFERROR(IF(INDEX(Rank_Changes!$P$2:$P$1090,MATCH($A10&"|"&"SWE",Rank_Changes!$U$2:$U$1090,0))="","–",INDEX(Rank_Changes!$P$2:$P$1090,MATCH($A10&"|"&"SWE",Rank_Changes!$U$2:$U$1090,0))),"–") -> -3 | H10: =IFERROR(IF(INDEX(Rank_Changes!$P$2:$P$1090,MATCH($A10&"|"&"FRA",Rank_Changes!$U$2:$U$1090,0))="","–",INDEX(Rank_Changes!$P$2:$P$1090,MATCH($A10&"|"&"FRA",Rank_Changes!$U$2:$U$1090,0))),"–") -> 1 | I10: =IFERROR(IF(INDEX(Rank_Changes!$P$2:$P$1090,MATCH($A10&"|"&"NLD",Rank_Changes!$U$2:$U$1090,0))="","–",INDEX(Rank_Changes!$P$2:$P$1090,MATCH($A10&"|"&"NLD",Rank_Changes!$U$2:$U$1090,0))),"–") -> -2 | J10: =IFERROR(IF(INDEX(Rank_Changes!$P$2:$P$1090,MATCH($A10&"|"&"CHE",Rank_Changes!$U$2:$U$1090,0))="","–",INDEX(Rank_Changes!$P$2:$P$1090,MATCH($A10&"|"&"CHE",Rank_Changes!$U$2:$U$1090,0))),"–") -> -1 | K10: =IFERROR(IF(INDEX(Rank_Changes!$P$2:$P$1090,MATCH($A10&"|"&"DNK",Rank_Changes!$U$2:$U$1090,0))="","–",INDEX(Rank_Changes!$P$2:$P$1090,MATCH($A10&"|"&"DNK",Rank_Changes!$U$2:$U$1090,0))),"–") -> -4 | L10: =IFERROR(IF(INDEX(Rank_Changes!$P$2:$P$1090,MATCH($A10&"|"&"CAN",Rank_Changes!$U$2:$U$1090,0))="","–",INDEX(Rank_Changes!$P$2:$P$1090,MATCH($A10&"|"&"CAN",Rank_Changes!$U$2:$U$1090,0))),"–") -> 4 | M10: =IFERROR(IF(INDEX(Rank_Changes!$P$2:$P$1090,MATCH($A10&"|"&"JPN",Rank_Changes!$U$2:$U$1090,0))="","–",INDEX(Rank_Changes!$P$2:$P$1090,MATCH($A10&"|"&"JPN",Rank_Changes!$U$2:$U$1090,0))),"–") -> -2 | N10: =IFERROR(IF(INDEX(Rank_Changes!$P$2:$P$1090,MATCH($A10&"|"&"AUS",Rank_Changes!$U$2:$U$1090,0))="","–",INDEX(Rank_Changes!$P$2:$P$1090,MATCH($A10&"|"&"AUS",Rank_Changes!$U$2:$U$1090,0))),"–") -> 2
A11: F1_07 | B11: Spending | C11: Public spending on health, % of total national GDP | D11: =IFERROR(IF(INDEX(Rank_Changes!$P$2:$P$1090,MATCH($A11&"|"&"USA",Rank_Changes!$U$2:$U$1090,0))="","–",INDEX(Rank_Changes!$P$2:$P$1090,MATCH($A11&"|"&"USA",Rank_Changes!$U$2:$U$1090,0))),"–") -> 2 | E11: =IFERROR(IF(INDEX(Rank_Changes!$P$2:$P$1090,MATCH($A11&"|"&"GBR",Rank_Changes!$U$2:$U$1090,0))="","–",INDEX(Rank_Changes!$P$2:$P$1090,MATCH($A11&"|"&"GBR",Rank_Changes!$U$2:$U$1090,0))),"–") -> 2 | F11: =IFERROR(IF(INDEX(Rank_Changes!$P$2:$P$1090,MATCH($A11&"|"&"DEU",Rank_Changes!$U$2:$U$1090,0))="","–",INDEX(Rank_Changes!$P$2:$P$1090,MATCH($A11&"|"&"DEU",Rank_Changes!$U$2:$U$1090,0))),"–") -> 1 | G11: =IFERROR(IF(INDEX(Rank_Changes!$P$2:$P$1090,MATCH($A11&"|"&"SWE",Rank_Changes!$U$2:$U$1090,0))="","–",INDEX(Rank_Changes!$P$2:$P$1090,MATCH($A11&"|"&"SWE",Rank_Changes!$U$2:$U$1090,0))),"–") -> 0 | H11: =IFERROR(IF(INDEX(Rank_Changes!$P$2:$P$1090,MATCH($A11&"|"&"FRA",Rank_Changes!$U$2:$U$1090,0))="","–",INDEX(Rank_Changes!$P$2:$P$1090,MATCH($A11&"|"&"FRA",Rank_Changes!$U$2:$U$1090,0))),"–") -> -4 | I11: =IFERROR(IF(INDEX(Rank_Changes!$P$2:$P$1090,MATCH($A11&"|"&"NLD",Rank_Changes!$U$2:$U$1090,0))="","–",INDEX(Rank_Changes!$P$2:$P$1090,MATCH($A11&"|"&"NLD",Rank_Changes!$U$2:$U$1090,0))),"–") -> – | J11: =IFERROR(IF(INDEX(Rank_Changes!$P$2:$P$1090,MATCH($A11&"|"&"CHE",Rank_Changes!$U$2:$U$1090,0))="","–",INDEX(Rank_Changes!$P$2:$P$1090,MATCH($A11&"|"&"CHE",Rank_Changes!$U$2:$U$1090,0))),"–") -> – | K11: =IFERROR(IF(INDEX(Rank_Changes!$P$2:$P$1090,MATCH($A11&"|"&"DNK",Rank_Changes!$U$2:$U$1090,0))="","–",INDEX(Rank_Changes!$P$2:$P$1090,MATCH($A11&"|"&"DNK",Rank_Changes!$U$2:$U$1090,0))),"–") -> -6 | L11: =IFERROR(IF(INDEX(Rank_Changes!$P$2:$P$1090,MATCH($A11&"|"&"CAN",Rank_Changes!$U$2:$U$1090,0))="","–",INDEX(Rank_Changes!$P$2:$P$1090,MATCH($A11&"|"&"CAN",Rank_Changes!$U$2:$U$1090,0))),"–") -> 2 | M11: =IFERROR(IF(INDEX(Rank_Changes!$P$2:$P$1090,MATCH($A11&"|"&"JPN",Rank_Changes!$U$2:$U$1090,0))="","–",INDEX(Rank_Changes!$P$2:$P$1090,MATCH($A11&"|"&"JPN",Rank_Changes!$U$2:$U$1090,0))),"–") -> 2 | N11: =IFERROR(IF(INDEX(Rank_Changes!$P$2:$P$1090,MATCH($A11&"|"&"AUS",Rank_Changes!$U$2:$U$1090,0))="","–",INDEX(Rank_Changes!$P$2:$P$1090,MATCH($A11&"|"&"AUS",Rank_Changes!$U$2:$U$1090,0))),"–") -> 0
A12: F1_08 | B12: Spending | C12: Mean spending on health per capita, US $ | D12: =IFERROR(IF(INDEX(Rank_Changes!$P$2:$P$1090,MATCH($A12&"|"&"USA",Rank_Changes!$U$2:$U$1090,0))="","–",INDEX(Rank_Changes!$P$2:$P$1090,MATCH($A12&"|"&"USA",Rank_Changes!$U$2:$U$1090,0))),"–") -> 0 | E12: =IFERROR(IF(INDEX(Rank_Changes!$P$2:$P$1090,MATCH($A12&"|"&"GBR",Rank_Changes!$U$2:$U$1090,0))="","–",INDEX(Rank_Changes!$P$2:$P$1090,MATCH($A12&"|"&"GBR",Rank_Changes!$U$2:$U$1090,0))),"–") -> 1 | F12: =IFERROR(IF(INDEX(Rank_Changes!$P$2:$P$1090,MATCH($A12&"|"&"DEU",Rank_Changes!$U$2:$U$1090,0))="","–",INDEX(Rank_Changes!$P$2:$P$1090,MATCH($A12&"|"&"DEU",Rank_Changes!$U$2:$U$1090,0))),"–") -> 3 | G12: =IFERROR(IF(INDEX(Rank_Changes!$P$2:$P$1090,MATCH($A12&"|"&"SWE",Rank_Changes!$U$2:$U$1090,0))="","–",INDEX(Rank_Changes!$P$2:$P$1090,MATCH($A12&"|"&"SWE",Rank_Changes!$U$2:$U$1090,0))),"–") -> -3 | H12: =IFERROR(IF(INDEX(Rank_Changes!$P$2:$P$1090,MATCH($A12&"|"&"FRA",Rank_Changes!$U$2:$U$1090,0))="","–",INDEX(Rank_Changes!$P$2:$P$1090,MATCH($A12&"|"&"FRA",Rank_Changes!$U$2:$U$1090,0))),"–") -> 1 | I12: =IFERROR(IF(INDEX(Rank_Changes!$P$2:$P$1090,MATCH($A12&"|"&"NLD",Rank_Changes!$U$2:$U$1090,0))="","–",INDEX(Rank_Changes!$P$2:$P$1090,MATCH($A12&"|"&"NLD",Rank_Changes!$U$2:$U$1090,0))),"–") -> 1 | J12: =IFERROR(IF(INDEX(Rank_Changes!$P$2:$P$1090,MATCH($A12&"|"&"CHE",Rank_Changes!$U$2:$U$1090,0))="","–",INDEX(Rank_Changes!$P$2:$P$1090,MATCH($A12&"|"&"CHE",Rank_Changes!$U$2:$U$1090,0))),"–") -> 1 | K12: =IFERROR(IF(INDEX(Rank_Changes!$P$2:$P$1090,MATCH($A12&"|"&"DNK",Rank_Changes!$U$2:$U$1090,0))="","–",INDEX(Rank_Changes!$P$2:$P$1090,MATCH($A12&"|"&"DNK",Rank_Changes!$U$2:$U$1090,0))),"–") -> -4 | L12: =IFERROR(IF(INDEX(Rank_Changes!$P$2:$P$1090,MATCH($A12&"|"&"CAN",Rank_Changes!$U$2:$U$1090,0))="","–",INDEX(Rank_Changes!$P$2:$P$1090,MATCH($A12&"|"&"CAN",Rank_Changes!$U$2:$U$1090,0))),"–") -> 0 | M12: =IFERROR(IF(INDEX(Rank_Changes!$P$2:$P$1090,MATCH($A12&"|"&"JPN",Rank_Changes!$U$2:$U$1090,0))="","–",INDEX(Rank_Changes!$P$2:$P$1090,MATCH($A12&"|"&"JPN",Rank_Changes!$U$2:$U$1090,0))),"–") -> -2 | N12: =IFERROR(IF(INDEX(Rank_Changes!$P$2:$P$1090,MATCH($A12&"|"&"AUS",Rank_Changes!$U$2:$U$1090,0))="","–",INDEX(Rank_Changes!$P$2:$P$1090,MATCH($A12&"|"&"AUS",Rank_Changes!$U$2:$U$1090,0))),"–") -> 2
A13: F1_09 | B13: Spending | C13: Inpatient care | D13: =IFERROR(IF(INDEX(Rank_Changes!$P$2:$P$1090,MATCH($A13&"|"&"USA",Rank_Changes!$U$2:$U$1090,0))="","–",INDEX(Rank_Changes!$P$2:$P$1090,MATCH($A13&"|"&"USA",Rank_Changes!$U$2:$U$1090,0))),"–") -> 0 | E13: =IFERROR(IF(INDEX(Rank_Changes!$P$2:$P$1090,MATCH($A13&"|"&"GBR",Rank_Changes!$U$2:$U$1090,0))="","–",INDEX(Rank_Changes!$P$2:$P$1090,MATCH($A13&"|"&"GBR",Rank_Changes!$U$2:$U$1090,0))),"–") -> 2 | F13: =IFERROR(IF(INDEX(Rank_Changes!$P$2:$P$1090,MATCH($A13&"|"&"DEU",Rank_Changes!$U$2:$U$1090,0))="","–",INDEX(Rank_Changes!$P$2:$P$1090,MATCH($A13&"|"&"DEU",Rank_Changes!$U$2:$U$1090,0))),"–") -> 2 | G13: =IFERROR(IF(INDEX(Rank_Changes!$P$2:$P$1090,MATCH($A13&"|"&"SWE",Rank_Changes!$U$2:$U$1090,0))="","–",INDEX(Rank_Changes!$P$2:$P$1090,MATCH($A13&"|"&"SWE",Rank_Changes!$U$2:$U$1090,0))),"–") -> 0 | H13: =IFERROR(IF(INDEX(Rank_Changes!$P$2:$P$1090,MATCH($A13&"|"&"FRA",Rank_Changes!$U$2:$U$1090,0))="","–",INDEX(Rank_Changes!$P$2:$P$1090,MATCH($A13&"|"&"FRA",Rank_Changes!$U$2:$U$1090,0))),"–") -> -1 | I13: =IFERROR(IF(INDEX(Rank_Changes!$P$2:$P$1090,MATCH($A13&"|"&"NLD",Rank_Changes!$U$2:$U$1090,0))="","–",INDEX(Rank_Changes!$P$2:$P$1090,MATCH($A13&"|"&"NLD",Rank_Changes!$U$2:$U$1090,0))),"–") -> – | J13: =IFERROR(IF(INDEX(Rank_Changes!$P$2:$P$1090,MATCH($A13&"|"&"CHE",Rank_Changes!$U$2:$U$1090,0))="","–",INDEX(Rank_Changes!$P$2:$P$1090,MATCH($A13&"|"&"CHE",Rank_Changes!$U$2:$U$1090,0))),"–") -> -3 | K13: =IFERROR(IF(INDEX(Rank_Changes!$P$2:$P$1090,MATCH($A13&"|"&"DNK",Rank_Changes!$U$2:$U$1090,0))="","–",INDEX(Rank_Changes!$P$2:$P$1090,MATCH($A13&"|"&"DNK",Rank_Changes!$U$2:$U$1090,0))),"–") -> -4 | L13: =IFERROR(IF(INDEX(Rank_Changes!$P$2:$P$1090,MATCH($A13&"|"&"CAN",Rank_Changes!$U$2:$U$1090,0))="","–",INDEX(Rank_Changes!$P$2:$P$1090,MATCH($A13&"|"&"CAN",Rank_Changes!$U$2:$U$1090,0))),"–") -> 0 | M13: =IFERROR(IF(INDEX(Rank_Changes!$P$2:$P$1090,MATCH($A13&"|"&"JPN",Rank_Changes!$U$2:$U$1090,0))="","–",INDEX(Rank_Changes!$P$2:$P$1090,MATCH($A13&"|"&"JPN",Rank_Changes!$U$2:$U$1090,0))),"–") -> 4 | N13: =IFERROR(IF(INDEX(Rank_Changes!$P$2:$P$1090,MATCH($A13&"|"&"AUS",Rank_Changes!$U$2:$U$1090,0))="","–",INDEX(Rank_Changes!$P$2:$P$1090,MATCH($A13&"|"&"AUS",Rank_Changes!$U$2:$U$1090,0))),"–") -> -1
A14: F1_10 | B14: Spending | C14: Outpatient care | D14: =IFERROR(IF(INDEX(Rank_Changes!$P$2:$P$1090,MATCH($A14&"|"&"USA",Rank_Changes!$U$2:$U$1090,0))="","–",INDEX(Rank_Changes!$P$2:$P$1090,MATCH($A14&"|"&"USA",Rank_Changes!$U$2:$U$1090,0))),"–") -> 0 | E14: =IFERROR(IF(INDEX(Rank_Changes!$P$2:$P$1090,MATCH($A14&"|"&"GBR",Rank_Changes!$U$2:$U$1090,0))="","–",INDEX(Rank_Changes!$P$2:$P$1090,MATCH($A14&"|"&"GBR",Rank_Changes!$U$2:$U$1090,0))),"–") -> 2 | F14: =IFERROR(IF(INDEX(Rank_Changes!$P$2:$P$1090,MATCH($A14&"|"&"DEU",Rank_Changes!$U$2:$U$1090,0))="","–",INDEX(Rank_Changes!$P$2:$P$1090,MATCH($A14&"|"&"DEU",Rank_Changes!$U$2:$U$1090,0))),"–") -> -1 | G14: =IFERROR(IF(INDEX(Rank_Changes!$P$2:$P$1090,MATCH($A14&"|"&"SWE",Rank_Changes!$U$2:$U$1090,0))="","–",INDEX(Rank_Changes!$P$2:$P$1090,MATCH($A14&"|"&"SWE",Rank_Changes!$U$2:$U$1090,0))),"–") -> 0 | H14: =IFERROR(IF(INDEX(Rank_Changes!$P$2:$P$1090,MATCH($A14&"|"&"FRA",Rank_Changes!$U$2:$U$1090,0))="","–",INDEX(Rank_Changes!$P$2:$P$1090,MATCH($A14&"|"&"FRA",Rank_Changes!$U$2:$U$1090,0))),"–") -> 1 | I14: =IFERROR(IF(INDEX(Rank_Changes!$P$2:$P$1090,MATCH($A14&"|"&"NLD",Rank_Changes!$U$2:$U$1090,0))="","–",INDEX(Rank_Changes!$P$2:$P$1090,MATCH($A14&"|"&"NLD",Rank_Changes!$U$2:$U$1090,0))),"–") -> – | J14: =IFERROR(IF(INDEX(Rank_Changes!$P$2:$P$1090,MATCH($A14&"|"&"CHE",Rank_Changes!$U$2:$U$1090,0))="","–",INDEX(Rank_Changes!$P$2:$P$1090,MATCH($A14&"|"&"CHE",Rank_Changes!$U$2:$U$1090,0))),"–") -> -4 | K14: =IFERROR(IF(INDEX(Rank_Changes!$P$2:$P$1090,MATCH($A14&"|"&"DNK",Rank_Changes!$U$2:$U$1090,0))="","–",INDEX(Rank_Changes!$P$2:$P$1090,MATCH($A14&"|"&"DNK",Rank_Changes!$U$2:$U$1090,0))),"–") -> 2 | L14: =IFERROR(IF(INDEX(Rank_Changes!$P$2:$P$1090,MATCH($A14&"|"&"CAN",Rank_Changes!$U$2:$U$1090,0))="","–",INDEX(Rank_Changes!$P$2:$P$1090,MATCH($A14&"|"&"CAN",Rank_Changes!$U$2:$U$1090,0))),"–") -> -1 | M14: =IFERROR(IF(INDEX(Rank_Changes!$P$2:$P$1090,MATCH($A14&"|"&"JPN",Rank_Changes!$U$2:$U$1090,0))="","–",INDEX(Rank_Changes!$P$2:$P$1090,MATCH($A14&"|"&"JPN",Rank_Changes!$U$2:$U$1090,0))),"–") -> 1 | N14: =IFERROR(IF(INDEX(Rank_Changes!$P$2:$P$1090,MATCH($A14&"|"&"AUS",Rank_Changes!$U$2:$U$1090,0))="","–",INDEX(Rank_Changes!$P$2:$P$1090,MATCH($A14&"|"&"AUS",Rank_Changes!$U$2:$U$1090,0))),"–") -> -1
A15: F1_11 | B15: Spending | C15: Long-term care | D15: =IFERROR(IF(INDEX(Rank_Changes!$P$2:$P$1090,MATCH($A15&"|"&"USA",Rank_Changes!$U$2:$U$1090,0))="","–",INDEX(Rank_Changes!$P$2:$P$1090,MATCH($A15&"|"&"USA",Rank_Changes!$U$2:$U$1090,0))),"–") -> -1 | E15: =IFERROR(IF(INDEX(Rank_Changes!$P$2:$P$1090,MATCH($A15&"|"&"GBR",Rank_Changes!$U$2:$U$1090,0))="","–",INDEX(Rank_Changes!$P$2:$P$1090,MATCH($A15&"|"&"GBR",Rank_Changes!$U$2:$U$1090,0))),"–") -> -1 | F15: =IFERROR(IF(INDEX(Rank_Changes!$P$2:$P$1090,MATCH($A15&"|"&"DEU",Rank_Changes!$U$2:$U$1090,0))="","–",INDEX(Rank_Changes!$P$2:$P$1090,MATCH($A15&"|"&"DEU",Rank_Changes!$U$2:$U$1090,0))),"–") -> 3 | G15: =IFERROR(IF(INDEX(Rank_Changes!$P$2:$P$1090,MATCH($A15&"|"&"SWE",Rank_Changes!$U$2:$U$1090,0))="","–",INDEX(Rank_Changes!$P$2:$P$1090,MATCH($A15&"|"&"SWE",Rank_Changes!$U$2:$U$1090,0))),"–") -> 0 | H15: =IFERROR(IF(INDEX(Rank_Changes!$P$2:$P$1090,MATCH($A15&"|"&"FRA",Rank_Changes!$U$2:$U$1090,0))="","–",INDEX(Rank_Changes!$P$2:$P$1090,MATCH($A15&"|"&"FRA",Rank_Changes!$U$2:$U$1090,0))),"–") -> 0 | I15: =IFERROR(IF(INDEX(Rank_Changes!$P$2:$P$1090,MATCH($A15&"|"&"NLD",Rank_Changes!$U$2:$U$1090,0))="","–",INDEX(Rank_Changes!$P$2:$P$1090,MATCH($A15&"|"&"NLD",Rank_Changes!$U$2:$U$1090,0))),"–") -> – | J15: =IFERROR(IF(INDEX(Rank_Changes!$P$2:$P$1090,MATCH($A15&"|"&"CHE",Rank_Changes!$U$2:$U$1090,0))="","–",INDEX(Rank_Changes!$P$2:$P$1090,MATCH($A15&"|"&"CHE",Rank_Changes!$U$2:$U$1090,0))),"–") -> -1 | K15: =IFERROR(IF(INDEX(Rank_Changes!$P$2:$P$1090,MATCH($A15&"|"&"DNK",Rank_Changes!$U$2:$U$1090,0))="","–",INDEX(Rank_Changes!$P$2:$P$1090,MATCH($A15&"|"&"DNK",Rank_Changes!$U$2:$U$1090,0))),"–") -> -2 | L15: =IFERROR(IF(INDEX(Rank_Changes!$P$2:$P$1090,MATCH($A15&"|"&"CAN",Rank_Changes!$U$2:$U$1090,0))="","–",INDEX(Rank_Changes!$P$2:$P$1090,MATCH($A15&"|"&"CAN",Rank_Changes!$U$2:$U$1090,0))),"–") -> 5 | M15: =IFERROR(IF(INDEX(Rank_Changes!$P$2:$P$1090,MATCH($A15&"|"&"JPN",Rank_Changes!$U$2:$U$1090,0))="","–",INDEX(Rank_Changes!$P$2:$P$1090,MATCH($A15&"|"&"JPN",Rank_Changes!$U$2:$U$1090,0))),"–") -> -4 | N15: =IFERROR(IF(INDEX(Rank_Changes!$P$2:$P$1090,MATCH($A15&"|"&"AUS",Rank_Changes!$U$2:$U$1090,0))="","–",INDEX(Rank_Changes!$P$2:$P$1090,MATCH($A15&"|"&"AUS",Rank_Changes!$U$2:$U$1090,0))),"–") -> 1
A16: F1_12 | B16: Spending | C16: Medical goods | D16: =IFERROR(IF(INDEX(Rank_Changes!$P$2:$P$1090,MATCH($A16&"|"&"USA",Rank_Changes!$U$2:$U$1090,0))="","–",INDEX(Rank_Changes!$P$2:$P$1090,MATCH($A16&"|"&"USA",Rank_Changes!$U$2:$U$1090,0))),"–") -> 0 | E16: =IFERROR(IF(INDEX(Rank_Changes!$P$2:$P$1090,MATCH($A16&"|"&"GBR",Rank_Changes!$U$2:$U$1090,0))="","–",INDEX(Rank_Changes!$P$2:$P$1090,MATCH($A16&"|"&"GBR",Rank_Changes!$U$2:$U$1090,0))),"–") -> -4 | F16: =IFERROR(IF(INDEX(Rank_Changes!$P$2:$P$1090,MATCH($A16&"|"&"DEU",Rank_Changes!$U$2:$U$1090,0))="","–",INDEX(Rank_Changes!$P$2:$P$1090,MATCH($A16&"|"&"DEU",Rank_Changes!$U$2:$U$1090,0))),"–") -> 0 | G16: =IFERROR(IF(INDEX(Rank_Changes!$P$2:$P$1090,MATCH($A16&"|"&"SWE",Rank_Changes!$U$2:$U$1090,0))="","–",INDEX(Rank_Changes!$P$2:$P$1090,MATCH($A16&"|"&"SWE",Rank_Changes!$U$2:$U$1090,0))),"–") -> 1 | H16: =IFERROR(IF(INDEX(Rank_Changes!$P$2:$P$1090,MATCH($A16&"|"&"FRA",Rank_Changes!$U$2:$U$1090,0))="","–",INDEX(Rank_Changes!$P$2:$P$1090,MATCH($A16&"|"&"FRA",Rank_Changes!$U$2:$U$1090,0))),"–") -> -2 | I16: =IFERROR(IF(INDEX(Rank_Changes!$P$2:$P$1090,MATCH($A16&"|"&"NLD",Rank_Changes!$U$2:$U$1090,0))="","–",INDEX(Rank_Changes!$P$2:$P$1090,MATCH($A16&"|"&"NLD",Rank_Changes!$U$2:$U$1090,0))),"–") -> – | J16: =IFERROR(IF(INDEX(Rank_Changes!$P$2:$P$1090,MATCH($A16&"|"&"CHE",Rank_Changes!$U$2:$U$1090,0))="","–",INDEX(Rank_Changes!$P$2:$P$1090,MATCH($A16&"|"&"CHE",Rank_Changes!$U$2:$U$1090,0))),"–") -> 2 | K16: =IFERROR(IF(INDEX(Rank_Changes!$P$2:$P$1090,MATCH($A16&"|"&"DNK",Rank_Changes!$U$2:$U$1090,0))="","–",INDEX(Rank_Changes!$P$2:$P$1090,MATCH($A16&"|"&"DNK",Rank_Changes!$U$2:$U$1090,0))),"–") -> 1 | L16: =IFERROR(IF(INDEX(Rank_Changes!$P$2:$P$1090,MATCH($A16&"|"&"CAN",Rank_Changes!$U$2:$U$1090,0))="","–",INDEX(Rank_Changes!$P$2:$P$1090,MATCH($A16&"|"&"CAN",Rank_Changes!$U$2:$U$1090,0))),"–") -> -3 | M16: =IFERROR(IF(INDEX(Rank_Changes!$P$2:$P$1090,MATCH($A16&"|"&"JPN",Rank_Changes!$U$2:$U$1090,0))="","–",INDEX(Rank_Changes!$P$2:$P$1090,MATCH($A16&"|"&"JPN",Rank_Changes!$U$2:$U$1090,0))),"–") -> -1 | N16: =IFERROR(IF(INDEX(Rank_Changes!$P$2:$P$1090,MATCH($A16&"|"&"AUS",Rank_Changes!$U$2:$U$1090,0))="","–",INDEX(Rank_Changes!$P$2:$P$1090,MATCH($A16&"|"&"AUS",Rank_Changes!$U$2:$U$1090,0))),"–") -> 0
... A103: F11_10 | B103: Equity | C103: Rural physicians per 1000 population | D103: =IFERROR(IF(INDEX(Rank_Changes!$P$2:$P$1090,MATCH($A103&"|"&"USA",Rank_Changes!$U$2:$U$1090,0))="","–",INDEX(Rank_Changes!$P$2:$P$1090,MATCH($A103&"|"&"USA",Rank_Changes!$U$2:$U$1090,0))),"–") -> – | E103: =IFERROR(IF(INDEX(Rank_Changes!$P$2:$P$1090,MATCH($A103&"|"&"GBR",Rank_Changes!$U$2:$U$1090,0))="","–",INDEX(Rank_Changes!$P$2:$P$1090,MATCH($A103&"|"&"GBR",Rank_Changes!$U$2:$U$1090,0))),"–") -> – | F103: =IFERROR(IF(INDEX(Rank_Changes!$P$2:$P$1090,MATCH($A103&"|"&"DEU",Rank_Changes!$U$2:$U$1090,0))="","–",INDEX(Rank_Changes!$P$2:$P$1090,MATCH($A103&"|"&"DEU",Rank_Changes!$U$2:$U$1090,0))),"–") -> – | G103: =IFERROR(IF(INDEX(Rank_Changes!$P$2:$P$1090,MATCH($A103&"|"&"SWE",Rank_Changes!$U$2:$U$1090,0))="","–",INDEX(Rank_Changes!$P$2:$P$1090,MATCH($A103&"|"&"SWE",Rank_Changes!$U$2:$U$1090,0))),"–") -> – | H103: =IFERROR(IF(INDEX(Rank_Changes!$P$2:$P$1090,MATCH($A103&"|"&"FRA",Rank_Changes!$U$2:$U$1090,0))="","–",INDEX(Rank_Changes!$P$2:$P$1090,MATCH($A103&"|"&"FRA",Rank_Changes!$U$2:$U$1090,0))),"–") -> – | I103: =IFERROR(IF(INDEX(Rank_Changes!$P$2:$P$1090,MATCH($A103&"|"&"NLD",Rank_Changes!$U$2:$U$1090,0))="","–",INDEX(Rank_Changes!$P$2:$P$1090,MATCH($A103&"|"&"NLD",Rank_Changes!$U$2:$U$1090,0))),"–") -> – | J103: =IFERROR(IF(INDEX(Rank_Changes!$P$2:$P$1090,MATCH($A103&"|"&"CHE",Rank_Changes!$U$2:$U$1090,0))="","–",INDEX(Rank_Changes!$P$2:$P$1090,MATCH($A103&"|"&"CHE",Rank_Changes!$U$2:$U$1090,0))),"–") -> – | K103: =IFERROR(IF(INDEX(Rank_Changes!$P$2:$P$1090,MATCH($A103&"|"&"DNK",Rank_Changes!$U$2:$U$1090,0))="","–",INDEX(Rank_Changes!$P$2:$P$1090,MATCH($A103&"|"&"DNK",Rank_Changes!$U$2:$U$1090,0))),"–") -> – | L103: =IFERROR(IF(INDEX(Rank_Changes!$P$2:$P$1090,MATCH($A103&"|"&"CAN",Rank_Changes!$U$2:$U$1090,0))="","–",INDEX(Rank_Changes!$P$2:$P$1090,MATCH($A103&"|"&"CAN",Rank_Changes!$U$2:$U$1090,0))),"–") -> – | M103: =IFERROR(IF(INDEX(Rank_Changes!$P$2:$P$1090,MATCH($A103&"|"&"JPN",Rank_Changes!$U$2:$U$1090,0))="","–",INDEX(Rank_Changes!$P$2:$P$1090,MATCH($A103&"|"&"JPN",Rank_Changes!$U$2:$U$1090,0))),"–") -> – | N103: =IFERROR(IF(INDEX(Rank_Changes!$P$2:$P$1090,MATCH($A103&"|"&"AUS",Rank_Changes!$U$2:$U$1090,0))="","–",INDEX(Rank_Changes!$P$2:$P$1090,MATCH($A103&"|"&"AUS",Rank_Changes!$U$2:$U$1090,0))),"–") -> –
